Workbook

Sheet Start
B2: TxDOT HIGHWAY CONSTRUCTION BID PROGRAM
B3: Unit-price proposal worksheet · Dallas District example · 2024 Standard Specifications
B5: This workbook prices a TxDOT highway proposal the way a contractor builds a bid: direct unit cost, job overhead, bond, insurance, profit, Item 500 mobilization, and the electronic bid guaranty. It does not submit a bid. Official proposals go through iCX (Integrated Contractor Exchange) after prequalification. Yellow cells with blue type are inputs. Green type is a cross-sheet formula. Replace the sample project before use.
B7: HOW TO USE THIS WORKBOOK
B8: Step | C8: Sheet | D8: What you do
B9: 1 | C9: Project | D9: Enter contractor, CSJ, highway, letting, engineer's estimate, working days, bidding capacity, and DBE goal.
B10: 2 | C10: Markups | D10: Set field overhead, duration, bond rate, insurance, home-office, and profit. The sheet solves a loaded bid that recovers those costs.
B11: 3 | C11: Unit Cost | D11: Build direct cost for production items from crew-day production, labor, equipment, material, waste, and subcontract.
B12: 4 | C12: Bid Proposal | D12: Confirm quantities from the proposal bid insert. Override any unit price. Blank override uses the loaded price.
B13: 5 | C13: Mobilization | D13: Price Item 500. Payment is staged under the 2024 spec and is capped relative to the contract on early estimates.
B14: 6 | C14: Bond & Checks | D14: Confirm the 2% bid guaranty, capacity, major items, zero prices, and mobilization share before iCX lock.
B16: RULES THIS MODEL FOLLOWS
B17: Bid form | C17: Unit price on every bid item. Total bid is the sum of quantity × unit price. A blank unit price is a non-responsive risk.
B18: Bid guaranty | C18: Required when the engineer's estimate exceeds $25,000. Amount is 2% of the estimate, rounded to the nearest $1,000, not to exceed $100,000. Electronic bids require an electronic bid bond (Surety2000 or Surepath).
B19: iCX | C19: Prequalified contractors bid in iCX. Paper bonds and checks are not bid guaranties on electronic bids. Bids must be in the vault by the letting time. Addenda must be acknowledged.
B20: Capacity | C20: Bidding capacity is set from the confidential questionnaire: net working capital × TxDOT factor. A bid over remaining capacity can be rejected.
B21: Major item | C21: An item whose extended amount is at least 5% of the original contract or $100,000, whichever is less. Major items stay major.
B22: Item 500 | C22: 2024 Mobilization is paid in stages (bond/insurance invoice, plant setup cap, then 1% / 5% / 10% earned). Early payments are the lesser of a percent of the lump sum and a percent of the contract. A very high mobilization bid draws review and slows cash.
B23: Unbalance | C23: TxDOT reviews materially unbalanced bids (front-loaded or token prices on items likely to overrun). This sheet flags $0 prices, penny prices, and unit prices outside the benchmark band.
B24: DBE / federal | C24: Federal-aid jobs carry a DBE goal. Commitment forms are part of the proposal, not a line on the bid schedule.
B26: DISCLAIMER · Not an official TxDOT form and not a substitute for the proposal, plans, general notes, or special provisions. Benchmark prices are planning figures drawn from published 2025–26 letting summaries (median low-bidder prices on common items) and typical Texas unit-price ranges. They are not TxDOT's official average low bid prices. Pull current district tabs from the TxDOT Bid Tabulations dashboard and data.texas.gov before you lock a number. Spec payment language is summarized from the 2024 Item 500; confirm the special provision actually in the proposal (SP 500-001 applies on large jobs).
B28: Import | C28: Paste the Whitley & Siddons EasyLinkPro export on WS Import. Proposal, estimate, and bond read that sheet.

Sheet WS Import
B2: WHITLEY & SIDDONS IMPORT
B3: EasyLinkPro export · paste the job header, then paste bid items under row 15
B5: In EasyLinkPro, open the job and export the bid-item list to Excel. Paste the control (CSJ), highway, county, district, letting date, and engineer's estimate into the yellow header. Paste item rows starting at row 16, under these columns. Accepted W&S names: Bid Item, Item, Item Number, Bid Code, Item Code; Description or Bid Item Description; Unit or UOM; Quantity, Qty, or Bid Qty. Codes can be 500-7001, 500 7001, or 5007001. Clear old rows before a new job. Direct cost and unit-price overrides stay on BidProposal.
B7: JOB HEADER | E7: FROM THE W&S JOB LINE
B8: CSJ / control | C8: 0047-14-128 | E8: Engineer's estimate | F8: 2850000 | G8: W&S column: Estimate
B9: Highway | C9: US 75 | E9: Description | F9: Mill, overlay, safety, and drainage
B10: Limits | C10: SH 121 to FM 455 | E10: Working days | F10: 140 | G10: From the proposal if W&S index does not carry it
B11: County | C11: Collin | E11: Items pasted | F11: =COUNTA(B16:B215) -> 33
B12: District | C12: Dallas | E12: Status | F12: =IF(F11=0,"Paste items under the headers","Proposal is reading this sheet") -> Proposal is reading this sheet
B13: Letting date | C13: 2026-11-04
B14: Bid Item / Item Number / Bid Code | C14: Description / Bid Item Description | D14: Unit / UOM | E14: Quantity / Qty / Bid Qty | F14: Optional | G14: Engineer unit, reference only | H14: Normalized
B15: Bid code | C15: Description | D15: Unit | E15: Quantity | F15: Category | G15: Eng. unit | H15: Code used
B16: 500-7001 | C16: Mobilization | D16: LS | E16: 1 | F16: Mobilization | H16: =IF(B16="","",IF(ISNUMBER(SEARCH("-",B16&"")),UPPER(TRIM(B16)),IF(LEN(SUBSTITUTE(SUBSTITUTE(UPPER(TRIM(B16&""))," ",""),"-",""))=8,LEFT(SUBSTITUTE(SUBSTITUTE(UPPER(TRIM(B16&""))," ",""),"-",""),4)&"-"&RIGHT(SUBSTITUTE(SUBSTITUTE(UPPER(TRIM(B16&""))," ",""),"-",""),4),IF(LEN(SUBSTITUTE(SUBSTITUTE(UPPER(TRIM(B16&""))," ",""),"-",""))=7,LEFT(SUBSTITUTE(SUBSTITUTE(UPPER(TRIM(B16&""))," ",""),"-",""),3)&"-"&RIGHT(SUBSTITUTE(SUBSTITUTE(UPPER(TRIM(B16&""))," ",""),"-",""),4),UPPER(TRIM(B16)))))) -> 500-7001
B17: 502-7001 | C17: Barricades, signs and traffic handling | D17: MO | E17: 7 | F17: Traffic control | H17: =IF(B17="","",IF(ISNUMBER(SEARCH("-",B17&"")),UPPER(TRIM(B17)),IF(LEN(SUBSTITUTE(SUBSTITUTE(UPPER(TRIM(B17&""))," ",""),"-",""))=8,LEFT(SUBSTITUTE(SUBSTITUTE(UPPER(TRIM(B17&""))," ",""),"-",""),4)&"-"&RIGHT(SUBSTITUTE(SUBSTITUTE(UPPER(TRIM(B17&""))," ",""),"-",""),4),IF(LEN(SUBSTITUTE(SUBSTITUTE(UPPER(TRIM(B17&""))," ",""),"-",""))=7,LEFT(SUBSTITUTE(SUBSTITUTE(UPPER(TRIM(B17&""))," ",""),"-",""),3)&"-"&RIGHT(SUBSTITUTE(SUBSTITUTE(UPPER(TRIM(B17&""))," ",""),"-",""),4),UPPER(TRIM(B17)))))) -> 502-7001
B18: 503-7001 | C18: Portable changeable message sign | D18: DAY | E18: 140 | F18: Traffic control | H18: =IF(B18="","",IF(ISNUMBER(SEARCH("-",B18&"")),UPPER(TRIM(B18)),IF(LEN(SUBSTITUTE(SUBSTITUTE(UPPER(TRIM(B18&""))," ",""),"-",""))=8,LEFT(SUBSTITUTE(SUBSTITUTE(UPPER(TRIM(B18&""))," ",""),"-",""),4)&"-"&RIGHT(SUBSTITUTE(SUBSTITUTE(UPPER(TRIM(B18&""))," ",""),"-",""),4),IF(LEN(SUBSTITUTE(SUBSTITUTE(UPPER(TRIM(B18&""))," ",""),"-",""))=7,LEFT(SUBSTITUTE(SUBSTITUTE(UPPER(TRIM(B18&""))," ",""),"-",""),3)&"-"&RIGHT(SUBSTITUTE(SUBSTITUTE(UPPER(TRIM(B18&""))," ",""),"-",""),4),UPPER(TRIM(B18)))))) -> 503-7001
B19: 505-7001 | C19: TMA (stationary) | D19: DAY | E19: 140 | F19: Traffic control | H19: =IF(B19="","",IF(ISNUMBER(SEARCH("-",B19&"")),UPPER(TRIM(B19)),IF(LEN(SUBSTITUTE(SUBSTITUTE(UPPER(TRIM(B19&""))," ",""),"-",""))=8,LEFT(SUBSTITUTE(SUBSTITUTE(UPPER(TRIM(B19&""))," ",""),"-",""),4)&"-"&RIGHT(SUBSTITUTE(SUBSTITUTE(UPPER(TRIM(B19&""))," ",""),"-",""),4),IF(LEN(SUBSTITUTE(SUBSTITUTE(UPPER(TRIM(B19&""))," ",""),"-",""))=7,LEFT(SUBSTITUTE(SUBSTITUTE(UPPER(TRIM(B19&""))," ",""),"-",""),3)&"-"&RIGHT(SUBSTITUTE(SUBSTITUTE(UPPER(TRIM(B19&""))," ",""),"-",""),4),UPPER(TRIM(B19)))))) -> 505-7001
B20: 505-7003 | C20: TMA (mobile operation) | D20: DAY | E20: 30 | F20: Traffic control | H20: =IF(B20="","",IF(ISNUMBER(SEARCH("-",B20&"")),UPPER(TRIM(B20)),IF(LEN(SUBSTITUTE(SUBSTITUTE(UPPER(TRIM(B20&""))," ",""),"-",""))=8,LEFT(SUBSTITUTE(SUBSTITUTE(UPPER(TRIM(B20&""))," ",""),"-",""),4)&"-"&RIGHT(SUBSTITUTE(SUBSTITUTE(UPPER(TRIM(B20&""))," ",""),"-",""),4),IF(LEN(SUBSTITUTE(SUBSTITUTE(UPPER(TRIM(B20&""))," ",""),"-",""))=7,LEFT(SUBSTITUTE(SUBSTITUTE(UPPER(TRIM(B20&""))," ",""),"-",""),3)&"-"&RIGHT(SUBSTITUTE(SUBSTITUTE(UPPER(TRIM(B20&""))," ",""),"-",""),4),UPPER(TRIM(B20)))))) -> 505-7003
B21: 506-7039 | C21: Temp sedmt cont fence (install) | D21: LF | E21: 4200 | F21: SW3P | H21: =IF(B21="","",IF(ISNUMBER(SEARCH("-",B21&"")),UPPER(TRIM(B21)),IF(LEN(SUBSTITUTE(SUBSTITUTE(UPPER(TRIM(B21&""))," ",""),"-",""))=8,LEFT(SUBSTITUTE(SUBSTITUTE(UPPER(TRIM(B21&""))," ",""),"-",""),4)&"-"&RIGHT(SUBSTITUTE(SUBSTITUTE(UPPER(TRIM(B21&""))," ",""),"-",""),4),IF(LEN(SUBSTITUTE(SUBSTITUTE(UPPER(TRIM(B21&""))," ",""),"-",""))=7,LEFT(SUBSTITUTE(SUBSTITUTE(UPPER(TRIM(B21&""))," ",""),"-",""),3)&"-"&RIGHT(SUBSTITUTE(SUBSTITUTE(UPPER(TRIM(B21&""))," ",""),"-",""),4),UPPER(TRIM(B21)))))) -> 506-7039
B22: 506-7041 | C22: Temp sedmt cont fence (remove) | D22: LF | E22: 4200 | F22: SW3P | H22: =IF(B22="","",IF(ISNUMBER(SEARCH("-",B22&"")),UPPER(TRIM(B22)),IF(LEN(SUBSTITUTE(SUBSTITUTE(UPPER(TRIM(B22&""))," ",""),"-",""))=8,LEFT(SUBSTITUTE(SUBSTITUTE(UPPER(TRIM(B22&""))," ",""),"-",""),4)&"-"&RIGHT(SUBSTITUTE(SUBSTITUTE(UPPER(TRIM(B22&""))," ",""),"-",""),4),IF(LEN(SUBSTITUTE(SUBSTITUTE(UPPER(TRIM(B22&""))," ",""),"-",""))=7,LEFT(SUBSTITUTE(SUBSTITUTE(UPPER(TRIM(B22&""))," ",""),"-",""),3)&"-"&RIGHT(SUBSTITUTE(SUBSTITUTE(UPPER(TRIM(B22&""))," ",""),"-",""),4),UPPER(TRIM(B22)))))) -> 506-7041
B23: 100-7002 | C23: Preparing right of way | D23: STA | E23: 18 | F23: Earthwork | H23: =IF(B23="","",IF(ISNUMBER(SEARCH("-",B23&"")),UPPER(TRIM(B23)),IF(LEN(SUBSTITUTE(SUBSTITUTE(UPPER(TRIM(B23&""))," ",""),"-",""))=8,LEFT(SUBSTITUTE(SUBSTITUTE(UPPER(TRIM(B23&""))," ",""),"-",""),4)&"-"&RIGHT(SUBSTITUTE(SUBSTITUTE(UPPER(TRIM(B23&""))," ",""),"-",""),4),IF(LEN(SUBSTITUTE(SUBSTITUTE(UPPER(TRIM(B23&""))," ",""),"-",""))=7,LEFT(SUBSTITUTE(SUBSTITUTE(UPPER(TRIM(B23&""))," ",""),"-",""),3)&"-"&RIGHT(SUBSTITUTE(SUBSTITUTE(UPPER(TRIM(B23&""))," ",""),"-",""),4),UPPER(TRIM(B23)))))) -> 100-7002
B24: 104-7006 | C24: Removing conc (pav) | D24: SY | E24: 2800 | F24: Earthwork | H24: =IF(B24="","",IF(ISNUMBER(SEARCH("-",B24&"")),UPPER(TRIM(B24)),IF(LEN(SUBSTITUTE(SUBSTITUTE(UPPER(TRIM(B24&""))," ",""),"-",""))=8,LEFT(SUBSTITUTE(SUBSTITUTE(UPPER(TRIM(B24&""))," ",""),"-",""),4)&"-"&RIGHT(SUBSTITUTE(SUBSTITUTE(UPPER(TRIM(B24&""))," ",""),"-",""),4),IF(LEN(SUBSTITUTE(SUBSTITUTE(UPPER(TRIM(B24&""))," ",""),"-",""))=7,LEFT(SUBSTITUTE(SUBSTITUTE(UPPER(TRIM(B24&""))," ",""),"-",""),3)&"-"&RIGHT(SUBSTITUTE(SUBSTITUTE(UPPER(TRIM(B24&""))," ",""),"-",""),4),UPPER(TRIM(B24)))))) -> 104-7006
B25: 110-7001 | C25: Excavation (roadway) | D25: CY | E25: 8600 | F25: Earthwork | H25: =IF(B25="","",IF(ISNUMBER(SEARCH("-",B25&"")),UPPER(TRIM(B25)),IF(LEN(SUBSTITUTE(SUBSTITUTE(UPPER(TRIM(B25&""))," ",""),"-",""))=8,LEFT(SUBSTITUTE(SUBSTITUTE(UPPER(TRIM(B25&""))," ",""),"-",""),4)&"-"&RIGHT(SUBSTITUTE(SUBSTITUTE(UPPER(TRIM(B25&""))," ",""),"-",""),4),IF(LEN(SUBSTITUTE(SUBSTITUTE(UPPER(TRIM(B25&""))," ",""),"-",""))=7,LEFT(SUBSTITUTE(SUBSTITUTE(UPPER(TRIM(B25&""))," ",""),"-",""),3)&"-"&RIGHT(SUBSTITUTE(SUBSTITUTE(UPPER(TRIM(B25&""))," ",""),"-",""),4),UPPER(TRIM(B25)))))) -> 110-7001
B26: 132-7005 | C26: Embankment (final)(ord comp)(ty C) | D26: CY | E26: 4100 | F26: Earthwork | H26: =IF(B26="","",IF(ISNUMBER(SEARCH("-",B26&"")),UPPER(TRIM(B26)),IF(LEN(SUBSTITUTE(SUBSTITUTE(UPPER(TRIM(B26&""))," ",""),"-",""))=8,LEFT(SUBSTITUTE(SUBSTITUTE(UPPER(TRIM(B26&""))," ",""),"-",""),4)&"-"&RIGHT(SUBSTITUTE(SUBSTITUTE(UPPER(TRIM(B26&""))," ",""),"-",""),4),IF(LEN(SUBSTITUTE(SUBSTITUTE(UPPER(TRIM(B26&""))," ",""),"-",""))=7,LEFT(SUBSTITUTE(SUBSTITUTE(UPPER(TRIM(B26&""))," ",""),"-",""),3)&"-"&RIGHT(SUBSTITUTE(SUBSTITUTE(UPPER(TRIM(B26&""))," ",""),"-",""),4),UPPER(TRIM(B26)))))) -> 132-7005
B27: 164-7002 | C27: Broadcast seed (perm)(rural)(clay) | D27: SY | E27: 18000 | F27: Roadside | H27: =IF(B27="","",IF(ISNUMBER(SEARCH("-",B27&"")),UPPER(TRIM(B27)),IF(LEN(SUBSTITUTE(SUBSTITUTE(UPPER(TRIM(B27&""))," ",""),"-",""))=8,LEFT(SUBSTITUTE(SUBSTITUTE(UPPER(TRIM(B27&""))," ",""),"-",""),4)&"-"&RIGHT(SUBSTITUTE(SUBSTITUTE(UPPER(TRIM(B27&""))," ",""),"-",""),4),IF(LEN(SUBSTITUTE(SUBSTITUTE(UPPER(TRIM(B27&""))," ",""),"-",""))=7,LEFT(SUBSTITUTE(SUBSTITUTE(UPPER(TRIM(B27&""))," ",""),"-",""),3)&"-"&RIGHT(SUBSTITUTE(SUBSTITUTE(UPPER(TRIM(B27&""))," ",""),"-",""),4),UPPER(TRIM(B27)))))) -> 164-7002
... B48: 512-7001 | C48: Port CTB (furn & inst)(safety shaped) | D48: LF | E48: 400 | F48: Traffic control | H48: =IF(B48="","",IF(ISNUMBER(SEARCH("-",B48&"")),UPPER(TRIM(B48)),IF(LEN(SUBSTITUTE(SUBSTITUTE(UPPER(TRIM(B48&""))," ",""),"-",""))=8,LEFT(SUBSTITUTE(SUBSTITUTE(UPPER(TRIM(B48&""))," ",""),"-",""),4)&"-"&RIGHT(SUBSTITUTE(SUBSTITUTE(UPPER(TRIM(B48&""))," ",""),"-",""),4),IF(LEN(SUBSTITUTE(SUBSTITUTE(UPPER(TRIM(B48&""))," ",""),"-",""))=7,LEFT(SUBSTITUTE(SUBSTITUTE(UPPER(TRIM(B48&""))," ",""),"-",""),3)&"-"&RIGHT(SUBSTITUTE(SUBSTITUTE(UPPER(TRIM(B48&""))," ",""),"-",""),4),UPPER(TRIM(B48)))))) -> 512-7001
H49: =IF(B49="","",IF(ISNUMBER(SEARCH("-",B49&"")),UPPER(TRIM(B49)),IF(LEN(SUBSTITUTE(SUBSTITUTE(UPPER(TRIM(B49&""))," ",""),"-",""))=8,LEFT(SUBSTITUTE(SUBSTITUTE(UPPER(TRIM(B49&""))," ",""),"-",""),4)&"-"&RIGHT(SUBSTITUTE(SUBSTITUTE(UPPER(TRIM(B49&""))," ",""),"-",""),4),IF(LEN(SUBSTITUTE(SUBSTITUTE(UPPER(TRIM(B49&""))," ",""),"-",""))=7,LEFT(SUBSTITUTE(SUBSTITUTE(UPPER(TRIM(B49&""))," ",""),"-",""),3)&"-"&RIGHT(SUBSTITUTE(SUBSTITUTE(UPPER(TRIM(B49&""))," ",""),"-",""),4),UPPER(TRIM(B49))))))
H50: =IF(B50="","",IF(ISNUMBER(SEARCH("-",B50&"")),UPPER(TRIM(B50)),IF(LEN(SUBSTITUTE(SUBSTITUTE(UPPER(TRIM(B50&""))," ",""),"-",""))=8,LEFT(SUBSTITUTE(SUBSTITUTE(UPPER(TRIM(B50&""))," ",""),"-",""),4)&"-"&RIGHT(SUBSTITUTE(SUBSTITUTE(UPPER(TRIM(B50&""))," ",""),"-",""),4),IF(LEN(SUBSTITUTE(SUBSTITUTE(UPPER(TRIM(B50&""))," ",""),"-",""))=7,LEFT(SUBSTITUTE(SUBSTITUTE(UPPER(TRIM(B50&""))," ",""),"-",""),3)&"-"&RIGHT(SUBSTITUTE(SUBSTITUTE(UPPER(TRIM(B50&""))," ",""),"-",""),4),UPPER(TRIM(B50))))))
H51: =IF(B51="","",IF(ISNUMBER(SEARCH("-",B51&"")),UPPER(TRIM(B51)),IF(LEN(SUBSTITUTE(SUBSTITUTE(UPPER(TRIM(B51&""))," ",""),"-",""))=8,LEFT(SUBSTITUTE(SUBSTITUTE(UPPER(TRIM(B51&""))," ",""),"-",""),4)&"-"&RIGHT(SUBSTITUTE(SUBSTITUTE(UPPER(TRIM(B51&""))," ",""),"-",""),4),IF(LEN(SUBSTITUTE(SUBSTITUTE(UPPER(TRIM(B51&""))," ",""),"-",""))=7,LEFT(SUBSTITUTE(SUBSTITUTE(UPPER(TRIM(B51&""))," ",""),"-",""),3)&"-"&RIGHT(SUBSTITUTE(SUBSTITUTE(UPPER(TRIM(B51&""))," ",""),"-",""),4),UPPER(TRIM(B51))))))
H52: =IF(B52="","",IF(ISNUMBER(SEARCH("-",B52&"")),UPPER(TRIM(B52)),IF(LEN(SUBSTITUTE(SUBSTITUTE(UPPER(TRIM(B52&""))," ",""),"-",""))=8,LEFT(SUBSTITUTE(SUBSTITUTE(UPPER(TRIM(B52&""))," ",""),"-",""),4)&"-"&RIGHT(SUBSTITUTE(SUBSTITUTE(UPPER(TRIM(B52&""))," ",""),"-",""),4),IF(LEN(SUBSTITUTE(SUBSTITUTE(UPPER(TRIM(B52&""))," ",""),"-",""))=7,LEFT(SUBSTITUTE(SUBSTITUTE(UPPER(TRIM(B52&""))," ",""),"-",""),3)&"-"&RIGHT(SUBSTITUTE(SUBSTITUTE(UPPER(TRIM(B52&""))," ",""),"-",""),4),UPPER(TRIM(B52))))))
H53: =IF(B53="","",IF(ISNUMBER(SEARCH("-",B53&"")),UPPER(TRIM(B53)),IF(LEN(SUBSTITUTE(SUBSTITUTE(UPPER(TRIM(B53&""))," ",""),"-",""))=8,LEFT(SUBSTITUTE(SUBSTITUTE(UPPER(TRIM(B53&""))," ",""),"-",""),4)&"-"&RIGHT(SUBSTITUTE(SUBSTITUTE(UPPER(TRIM(B53&""))," ",""),"-",""),4),IF(LEN(SUBSTITUTE(SUBSTITUTE(UPPER(TRIM(B53&""))," ",""),"-",""))=7,LEFT(SUBSTITUTE(SUBSTITUTE(UPPER(TRIM(B53&""))," ",""),"-",""),3)&"-"&RIGHT(SUBSTITUTE(SUBSTITUTE(UPPER(TRIM(B53&""))," ",""),"-",""),4),UPPER(TRIM(B53))))))
H54: =IF(B54="","",IF(ISNUMBER(SEARCH("-",B54&"")),UPPER(TRIM(B54)),IF(LEN(SUBSTITUTE(SUBSTITUTE(UPPER(TRIM(B54&""))," ",""),"-",""))=8,LEFT(SUBSTITUTE(SUBSTITUTE(UPPER(TRIM(B54&""))," ",""),"-",""),4)&"-"&RIGHT(SUBSTITUTE(SUBSTITUTE(UPPER(TRIM(B54&""))," ",""),"-",""),4),IF(LEN(SUBSTITUTE(SUBSTITUTE(UPPER(TRIM(B54&""))," ",""),"-",""))=7,LEFT(SUBSTITUTE(SUBSTITUTE(UPPER(TRIM(B54&""))," ",""),"-",""),3)&"-"&RIGHT(SUBSTITUTE(SUBSTITUTE(UPPER(TRIM(B54&""))," ",""),"-",""),4),UPPER(TRIM(B54))))))
H55: =IF(B55="","",IF(ISNUMBER(SEARCH("-",B55&"")),UPPER(TRIM(B55)),IF(LEN(SUBSTITUTE(SUBSTITUTE(UPPER(TRIM(B55&""))," ",""),"-",""))=8,LEFT(SUBSTITUTE(SUBSTITUTE(UPPER(TRIM(B55&""))," ",""),"-",""),4)&"-"&RIGHT(SUBSTITUTE(SUBSTITUTE(UPPER(TRIM(B55&""))," ",""),"-",""),4),IF(LEN(SUBSTITUTE(SUBSTITUTE(UPPER(TRIM(B55&""))," ",""),"-",""))=7,LEFT(SUBSTITUTE(SUBSTITUTE(UPPER(TRIM(B55&""))," ",""),"-",""),3)&"-"&RIGHT(SUBSTITUTE(SUBSTITUTE(UPPER(TRIM(B55&""))," ",""),"-",""),4),UPPER(TRIM(B55))))))
H56: =IF(B56="","",IF(ISNUMBER(SEARCH("-",B56&"")),UPPER(TRIM(B56)),IF(LEN(SUBSTITUTE(SUBSTITUTE(UPPER(TRIM(B56&""))," ",""),"-",""))=8,LEFT(SUBSTITUTE(SUBSTITUTE(UPPER(TRIM(B56&""))," ",""),"-",""),4)&"-"&RIGHT(SUBSTITUTE(SUBSTITUTE(UPPER(TRIM(B56&""))," ",""),"-",""),4),IF(LEN(SUBSTITUTE(SUBSTITUTE(UPPER(TRIM(B56&""))," ",""),"-",""))=7,LEFT(SUBSTITUTE(SUBSTITUTE(UPPER(TRIM(B56&""))," ",""),"-",""),3)&"-"&RIGHT(SUBSTITUTE(SUBSTITUTE(UPPER(TRIM(B56&""))," ",""),"-",""),4),UPPER(TRIM(B56))))))
H57: =IF(B57="","",IF(ISNUMBER(SEARCH("-",B57&"")),UPPER(TRIM(B57)),IF(LEN(SUBSTITUTE(SUBSTITUTE(UPPER(TRIM(B57&""))," ",""),"-",""))=8,LEFT(SUBSTITUTE(SUBSTITUTE(UPPER(TRIM(B57&""))," ",""),"-",""),4)&"-"&RIGHT(SUBSTITUTE(SUBSTITUTE(UPPER(TRIM(B57&""))," ",""),"-",""),4),IF(LEN(SUBSTITUTE(SUBSTITUTE(UPPER(TRIM(B57&""))," ",""),"-",""))=7,LEFT(SUBSTITUTE(SUBSTITUTE(UPPER(TRIM(B57&""))," ",""),"-",""),3)&"-"&RIGHT(SUBSTITUTE(SUBSTITUTE(UPPER(TRIM(B57&""))," ",""),"-",""),4),UPPER(TRIM(B57))))))
H58: =IF(B58="","",IF(ISNUMBER(SEARCH("-",B58&"")),UPPER(TRIM(B58)),IF(LEN(SUBSTITUTE(SUBSTITUTE(UPPER(TRIM(B58&""))," ",""),"-",""))=8,LEFT(SUBSTITUTE(SUBSTITUTE(UPPER(TRIM(B58&""))," ",""),"-",""),4)&"-"&RIGHT(SUBSTITUTE(SUBSTITUTE(UPPER(TRIM(B58&""))," ",""),"-",""),4),IF(LEN(SUBSTITUTE(SUBSTITUTE(UPPER(TRIM(B58&""))," ",""),"-",""))=7,LEFT(SUBSTITUTE(SUBSTITUTE(UPPER(TRIM(B58&""))," ",""),"-",""),3)&"-"&RIGHT(SUBSTITUTE(SUBSTITUTE(UPPER(TRIM(B58&""))," ",""),"-",""),4),UPPER(TRIM(B58))))))
H59: =IF(B59="","",IF(ISNUMBER(SEARCH("-",B59&"")),UPPER(TRIM(B59)),IF(LEN(SUBSTITUTE(SUBSTITUTE(UPPER(TRIM(B59&""))," ",""),"-",""))=8,LEFT(SUBSTITUTE(SUBSTITUTE(UPPER(TRIM(B59&""))," ",""),"-",""),4)&"-"&RIGHT(SUBSTITUTE(SUBSTITUTE(UPPER(TRIM(B59&""))," ",""),"-",""),4),IF(LEN(SUBSTITUTE(SUBSTITUTE(UPPER(TRIM(B59&""))," ",""),"-",""))=7,LEFT(SUBSTITUTE(SUBSTITUTE(UPPER(TRIM(B59&""))," ",""),"-",""),3)&"-"&RIGHT(SUBSTITUTE(SUBSTITUTE(UPPER(TRIM(B59&""))," ",""),"-",""),4),UPPER(TRIM(B59))))))
H60: =IF(B60="","",IF(ISNUMBER(SEARCH("-",B60&"")),UPPER(TRIM(B60)),IF(LEN(SUBSTITUTE(SUBSTITUTE(UPPER(TRIM(B60&""))," ",""),"-",""))=8,LEFT(SUBSTITUTE(SUBSTITUTE(UPPER(TRIM(B60&""))," ",""),"-",""),4)&"-"&RIGHT(SUBSTITUTE(SUBSTITUTE(UPPER(TRIM(B60&""))," ",""),"-",""),4),IF(LEN(SUBSTITUTE(SUBSTITUTE(UPPER(TRIM(B60&""))," ",""),"-",""))=7,LEFT(SUBSTITUTE(SUBSTITUTE(UPPER(TRIM(B60&""))," ",""),"-",""),3)&"-"&RIGHT(SUBSTITUTE(SUBSTITUTE(UPPER(TRIM(B60&""))," ",""),"-",""),4),UPPER(TRIM(B60))))))
... H215: =IF(B215="","",IF(ISNUMBER(SEARCH("-",B215&"")),UPPER(TRIM(B215)),IF(LEN(SUBSTITUTE(SUBSTITUTE(UPPER(TRIM(B215&""))," ",""),"-",""))=8,LEFT(SUBSTITUTE(SUBSTITUTE(UPPER(TRIM(B215&""))," ",""),"-",""),4)&"-"&RIGHT(SUBSTITUTE(SUBSTITUTE(UPPER(TRIM(B215&""))," ",""),"-",""),4),IF(LEN(SUBSTITUTE(SUBSTITUTE(UPPER(TRIM(B215&""))," ",""),"-",""))=7,LEFT(SUBSTITUTE(SUBSTITUTE(UPPER(TRIM(B215&""))," ",""),"-",""),3)&"-"&RIGHT(SUBSTITUTE(SUBSTITUTE(UPPER(TRIM(B215&""))," ",""),"-",""),4),UPPER(TRIM(B215))))))

Sheet Summary
B2: BID SUMMARY
B3: =CONCATENATE(Project!F7," · ",Project!F8," · ",Project!F10," District · ",Project!C6) -> US 75 · SH 121 to FM 455 · Dallas District · North Texas Paving, LLC
B5: BID BY CATEGORY
B6: Category | C6: Bid amount | D6: Share | E6: Direct cost
B7: Mobilization | C7: =SUMIF(BidProposal!$D$6:$D$155,B7,BidProposal!$N$6:$N$155) -> 134053.49 | D7: =IF(BidProposal!$N$156=0,0,C7/BidProposal!$N$156) -> 0.052132701 | E7: =SUMIF(BidProposal!$D$6:$D$155,B7,BidProposal!$I$6:$I$155) -> 0
B8: Traffic control | C8: =SUMIF(BidProposal!$D$6:$D$155,B8,BidProposal!$N$6:$N$155) -> 117701.36 | D8: =IF(BidProposal!$N$156=0,0,C8/BidProposal!$N$156) -> 0.045773445 | E8: =SUMIF(BidProposal!$D$6:$D$155,B8,BidProposal!$I$6:$I$155) -> 83100
B9: SW3P | C9: =SUMIF(BidProposal!$D$6:$D$155,B9,BidProposal!$N$6:$N$155) -> 18076.437 | D9: =IF(BidProposal!$N$156=0,0,C9/BidProposal!$N$156) -> 0.0070298317 | E9: =SUMIF(BidProposal!$D$6:$D$155,B9,BidProposal!$I$6:$I$155) -> 12762.4
B10: Earthwork | C10: =SUMIF(BidProposal!$D$6:$D$155,B10,BidProposal!$N$6:$N$155) -> 239185.73 | D10: =IF(BidProposal!$N$156=0,0,C10/BidProposal!$N$156) -> 0.093018079 | E10: =SUMIF(BidProposal!$D$6:$D$155,B10,BidProposal!$I$6:$I$155) -> 168870.89
B11: Base | C11: =SUMIF(BidProposal!$D$6:$D$155,B11,BidProposal!$N$6:$N$155) -> 176511.44 | D11: =IF(BidProposal!$N$156=0,0,C11/BidProposal!$N$156) -> 0.068644377 | E11: =SUMIF(BidProposal!$D$6:$D$155,B11,BidProposal!$I$6:$I$155) -> 124621.33
B12: Paving | C12: =SUMIF(BidProposal!$D$6:$D$155,B12,BidProposal!$N$6:$N$155) -> 1336351.3 | D12: =IF(BidProposal!$N$156=0,0,C12/BidProposal!$N$156) -> 0.51970005 | E12: =SUMIF(BidProposal!$D$6:$D$155,B12,BidProposal!$I$6:$I$155) -> 943496.25
B13: Drainage | C13: =SUMIF(BidProposal!$D$6:$D$155,B13,BidProposal!$N$6:$N$155) -> 178646.59 | D13: =IF(BidProposal!$N$156=0,0,C13/BidProposal!$N$156) -> 0.069474726 | E13: =SUMIF(BidProposal!$D$6:$D$155,B13,BidProposal!$I$6:$I$155) -> 126128.8
B14: Roadside | C14: =SUMIF(BidProposal!$D$6:$D$155,B14,BidProposal!$N$6:$N$155) -> 215648.94 | D14: =IF(BidProposal!$N$156=0,0,C14/BidProposal!$N$156) -> 0.083864745 | E14: =SUMIF(BidProposal!$D$6:$D$155,B14,BidProposal!$I$6:$I$155) -> 152253.35
B15: Safety | C15: =SUMIF(BidProposal!$D$6:$D$155,B15,BidProposal!$N$6:$N$155) -> 61986.553 | D15: =IF(BidProposal!$N$156=0,0,C15/BidProposal!$N$156) -> 0.024106246 | E15: =SUMIF(BidProposal!$D$6:$D$155,B15,BidProposal!$I$6:$I$155) -> 43764
B16: Signing | C16: =SUMIF(BidProposal!$D$6:$D$155,B16,BidProposal!$N$6:$N$155) -> 17690.614 | D16: =IF(BidProposal!$N$156=0,0,C16/BidProposal!$N$156) -> 0.0068797874 | E16: =SUMIF(BidProposal!$D$6:$D$155,B16,BidProposal!$I$6:$I$155) -> 12490
B17: Markings | C17: =SUMIF(BidProposal!$D$6:$D$155,B17,BidProposal!$N$6:$N$155) -> 75537.176 | D17: =IF(BidProposal!$N$156=0,0,C17/BidProposal!$N$156) -> 0.029376013 | E17: =SUMIF(BidProposal!$D$6:$D$155,B17,BidProposal!$I$6:$I$155) -> 53331.067
B18: Total | C18: =SUM(C7:C17) -> 2571389.7 | D18: =SUM(D7:D17) -> 1 | E18: =SUM(E7:E17) -> 1720818.1
B20: OUTCOME
B21: Total bid | C21: =BidProposal!N156 -> 2571389.7
B22: Engineer's estimate | C22: =EE -> 2850000
B23: Variance to estimate | C23: =C21-C22 -> -278610.32
B24: Variance percent | C24: =IF(C22=0,0,C21/C22-1) -> -0.097758006
B25: Bid guaranty | C25: ='Bond & Checks'!C11 -> 57000
B26: Capacity headroom | C26: ='Bond & Checks'!C17 -> 9028610.3

Sheet Project
B2: PROJECT SETUP
B3: Sample job is a Collin County mill-and-overlay with safety and drainage. Replace every yellow cell with the proposal in hand.
B5: CONTRACTOR | E5: PROJECT
B6: Legal name | C6: North Texas Paving, LLC | E6: CSJ | F6: ='WS Import'!C8 -> 0047-14-128 | G6: From WS Import. Paste the Whitley & Siddons job line there.
B7: TxDOT vendor ID | C7: VT00000000 | E7: Highway | F7: ='WS Import'!C9 -> US 75
B8: Estimator | C8: Estimator | E8: Limits | F8: ='WS Import'!C10 -> SH 121 to FM 455
B9: Date prepared | C9: 2026-10-02 | E9: County | F9: ='WS Import'!C11 -> Collin
E10: District | F10: ='WS Import'!C12 -> Dallas
E11: Letting date | F11: ='WS Import'!C13 -> 2026-11-04
E12: Spec book | F12: 2024
B14: MONEY AND TIME | E14: BID POLICY INPUTS
B15: Engineer's estimate | C15: ='WS Import'!F8 -> 2850000 | E15: Funding | F15: Federal-aid
B16: Working days | C16: ='WS Import'!F10 -> 140 | E16: DBE goal | F16: 0.08
B17: Months on site | C17: 7 | E17: Mobilization target share | F17: 0.055 | G17: Share of work items, before Item 500. Cash and review flag, not a spec cap on the bid.
B18: Bidding capacity | C18: 18000000 | E18: Contingency on direct | F18: 0.02 | G18: Unallocated field risk. Sits in the load, not as a bid item.
B19: Capacity already committed | C19: 6400000 | E19: Proposal addenda received | F19: 0 | G19: Count of addenda acknowledged in iCX. Must match the letting.
B20: Remaining capacity | C20: =C18-C19 -> 11600000
B22: LIVE SNAPSHOT · updates from the Bid Proposal
B23: Work-item direct cost | C23: =Markups!C11 -> 0.035 | E23: Capacity headroom is remaining prequalification capacity minus this bid. A negative number means this proposal, stacked on work already committed, exceeds the bidding capacity on the confidential questionnaire. TxDOT can reject a bid that exceeds available capacity. Capacity is net working capital times the factor in the approval letter — enter the letter amount, not a guess from revenue.
B24: Loaded work-item bid | C24: =Markups!C18 -> 2091234.5
B25: Item 500 mobilization bid | C25: =Mobilization!C12 -> 134053.49
B26: Total bid | C26: =BidProposal!N156 -> 2571389.7
B27: Bid vs engineer's estimate | C27: =IF(C15=0,"-",BidProposal!N156/C15-1) -> -0.097758006
B28: Bid guaranty required | C28: ='Bond & Checks'!C11 -> 57000
B29: Capacity headroom after this bid | C29: =C20-BidProposal!N156 -> 9028610.3

Sheet Markups
B2: INDIRECTS, BOND, INSURANCE, PROFIT
B3: Rates load the work items. Item 500 is priced on the Mobilization sheet so bond cash is not double-counted.
B5: JOB OVERHEAD AND RATES
B6: Field overhead per month | C6: 48000 | D6: Superintendent, pickup, field office, small tools, sanitation.
B7: Months on site | C7: =MonthsOnSite -> 7 | D7: From Project.
B8: Field overhead total | C8: =C6*C7 -> 336000 | D8: Fixed cost spread across work items.
B9: Bond rate on contract amount | C9: 0.009 | D9: Payment and performance bond. Often 0.6% to 1.5%.
B10: Insurance rate on contract amount | C10: 0.018 | D10: GL, builder's risk, umbrella. Workers' comp belongs in the labor rate.
B11: Home-office rate on contract amount | C11: 0.035 | D11: G&A share assigned to this job.
B12: Profit on contract amount | C12: 0.08 | D12: Target margin on the loaded work-item total, before Item 500.
B13: Contingency on direct | C13: =Contingency -> 0.02 | D13: From Project. Applied to direct cost, then loaded.
B15: LOAD SOLVE · work items only, Item 500 excluded
B16: Direct cost of work items | C16: =SUMIF(BidProposal!B6:B155,"<>500-7001",BidProposal!I6:I155) -> 1720818.1 | D16: Sum of quantity × direct unit cost, excluding Item 500.
B17: Contingency dollars | C17: =C16*C13 -> 34416.362 | D17: Contingency rate times direct.
B18: Direct + contingency + field overhead | C18: =C16+C17+C8 -> 2091234.5 | D18: Numerator of the load.
B19: Rate load (bond + insurance + G&A + profit) | C19: =C9+C10+C11+C12 -> 0.142 | D19: These rates apply to the loaded work-item bid.
B20: Loaded work-item bid | C20: =IF((1-C19)<=0,"Rate load must be under 100%",(C18)/(1-C19)) -> 2437336.2 | D20: C = (direct + contingency + field OH) / (1 − bond − insurance − G&A − profit).
B21: Markup factor on direct | C21: =IF(C16=0,1,C20/C16) -> 1.4163822 | D21: Suggested unit price = direct unit × this factor, unless overridden.
B22: Dollars of load | C22: =C20-C16 -> 716518.1 | D22: Overhead, contingency, bond, insurance, G&A, and profit.
B24: Why the division: bond, insurance, home office, and profit are percents of the bid, not of direct cost. Adding them on top of direct understates the bid. The solve grosses them up so the rates land on the contract amount. If you override unit prices on the proposal, the Bid Proposal sheet shows whether the overrides still recover this load.
B28: WHERE THE LOAD GOES
B29: Component | C29: Amount | D29: Share of loaded work bid
B30: Direct work | C30: =C16 -> 1720818.1 | D30: =IF($C$20=0,0,C30/$C$20) -> 0.7060241
B31: Contingency | C31: =C17 -> 34416.362 | D31: =IF($C$20=0,0,C31/$C$20) -> 0.014120482
B32: Field overhead | C32: =C8 -> 336000 | D32: =IF($C$20=0,0,C32/$C$20) -> 0.13785542
B33: Bond | C33: =C9*C20 -> 21936.026 | D33: =IF($C$20=0,0,C33/$C$20) -> 0.009
B34: Insurance | C34: =C10*C20 -> 43872.051 | D34: =IF($C$20=0,0,C34/$C$20) -> 0.018
B35: Home office | C35: =C11*C20 -> 85306.767 | D35: =IF($C$20=0,0,C35/$C$20) -> 0.035
B36: Profit | C36: =C12*C20 -> 194986.9 | D36: =IF($C$20=0,0,C36/$C$20) -> 0.08
B37: Loaded work-item bid | C37: =C20 -> 2437336.2 | D37: =IF($C$20=0,0,C37/$C$20) -> 1

Sheet Unit Cost
B2: DIRECT UNIT COST BUILDUP
B3: Crew-day method. Direct unit = labor/day÷production + equipment/day÷production + material×(1+waste) + subcontract. Items left off this sheet use the manual direct cost on Bid Proposal.
B5: Bid code | C5: Description | D5: Unit | E5: Production / crew-day | F5: Labor $ / day | G5: Equipment $ / day | H5: Material $ / unit | I5: Waste | J5: Sub $ / unit | K5: Labor $ / unit | L5: Equip $ / unit | M5: Material loaded | N5: Direct $ / unit
B6: 110-7001 | C6: Excavation (roadway) | D6: CY | E6: 900 | F6: 2400 | G6: 3100 | H6: 0 | I6: 0.05 | J6: 0 | K6: =IF(E6=0,0,F6/E6) -> 2.6666667 | L6: =IF(E6=0,0,G6/E6) -> 3.4444444 | M6: =H6*(1+I6) -> 0 | N6: =K6+L6+M6+J6 -> 6.1111111
B7: 132-7005 | C7: Embankment (final)(ord comp)(ty C) | D7: CY | E7: 750 | F7: 2200 | G7: 2800 | H7: 6.5 | I7: 0.08 | J7: 0 | K7: =IF(E7=0,0,F7/E7) -> 2.9333333 | L7: =IF(E7=0,0,G7/E7) -> 3.7333333 | M7: =H7*(1+I7) -> 7.02 | N7: =K7+L7+M7+J7 -> 13.686667
B8: 164-7002 | C8: Broadcast seed (perm)(rural)(clay) | D8: SY | E8: 8000 | F8: 1400 | G8: 900 | H8: 0.18 | I8: 0.05 | J8: 0 | K8: =IF(E8=0,0,F8/E8) -> 0.175 | L8: =IF(E8=0,0,G8/E8) -> 0.1125 | M8: =H8*(1+I8) -> 0.189 | N8: =K8+L8+M8+J8 -> 0.4765
B9: 247-7194 | C9: Flex base (compl in place)(ty A gr 4) | D9: CY | E9: 450 | F9: 2600 | G9: 3400 | H9: 22 | I9: 0.06 | J9: 0 | K9: =IF(E9=0,0,F9/E9) -> 5.7777778 | L9: =IF(E9=0,0,G9/E9) -> 7.5555556 | M9: =H9*(1+I9) -> 23.32 | N9: =K9+L9+M9+J9 -> 36.653333
B10: 310-7004 | C10: Prime coat | D10: GAL | E10: 6000 | F10: 1800 | G10: 1600 | H10: 2.4 | I10: 0.03 | J10: 0 | K10: =IF(E10=0,0,F10/E10) -> 0.3 | L10: =IF(E10=0,0,G10/E10) -> 0.26666667 | M10: =H10*(1+I10) -> 2.472 | N10: =K10+L10+M10+J10 -> 3.0386667
B11: 354-7051 | C11: Plane asph conc pav (2 in) | D11: SY | E11: 9000 | F11: 2200 | G11: 4500 | H11: 0 | I11: 0 | J11: 0 | K11: =IF(E11=0,0,F11/E11) -> 0.24444444 | L11: =IF(E11=0,0,G11/E11) -> 0.5 | M11: =H11*(1+I11) -> 0 | N11: =K11+L11+M11+J11 -> 0.74444444
B12: 3076-7022 | C12: D-GR HMA ty D SAC-B PG70-22 | D12: TON | E12: 1400 | F12: 3200 | G12: 6800 | H12: 78 | I12: 0.04 | J12: 0 | K12: =IF(E12=0,0,F12/E12) -> 2.2857143 | L12: =IF(E12=0,0,G12/E12) -> 4.8571429 | M12: =H12*(1+I12) -> 81.12 | N12: =K12+L12+M12+J12 -> 88.262857
B13: 3076-7008 | C13: D-GR HMA ty B PG64-22 | D13: TON | E13: 1500 | F13: 3000 | G13: 6400 | H13: 68 | I13: 0.04 | J13: 0 | K13: =IF(E13=0,0,F13/E13) -> 2 | L13: =IF(E13=0,0,G13/E13) -> 4.2666667 | M13: =H13*(1+I13) -> 70.72 | N13: =K13+L13+M13+J13 -> 76.986667
B14: 464-7005 | C14: RC pipe (cl III)(24 in) | D14: LF | E14: 160 | F14: 2400 | G14: 1800 | H14: 68 | I14: 0.03 | J14: 0 | K14: =IF(E14=0,0,F14/E14) -> 15 | L14: =IF(E14=0,0,G14/E14) -> 11.25 | M14: =H14*(1+I14) -> 70.04 | N14: =K14+L14+M14+J14 -> 96.29
B15: 529-7009 | C15: Curb and gutter (ty II) | D15: LF | E15: 350 | F15: 2100 | G15: 900 | H15: 14.5 | I15: 0.05 | J15: 0 | K15: =IF(E15=0,0,F15/E15) -> 6 | L15: =IF(E15=0,0,G15/E15) -> 2.5714286 | M15: =H15*(1+I15) -> 15.225 | N15: =K15+L15+M15+J15 -> 23.796429
B16: 531-7001 | C16: Conc sidewalks (4 in) | D16: SY | E16: 180 | F16: 1800 | G16: 700 | H16: 38 | I16: 0.05 | J16: 0 | K16: =IF(E16=0,0,F16/E16) -> 10 | L16: =IF(E16=0,0,G16/E16) -> 3.8888889 | M16: =H16*(1+I16) -> 39.9 | N16: =K16+L16+M16+J16 -> 53.788889
B17: 540-7001 | C17: MTL W-beam GD fen (tim post) | D17: LF | E17: 250 | F17: 1600 | G17: 800 | H17: 18 | I17: 0.02 | J17: 0 | K17: =IF(E17=0,0,F17/E17) -> 6.4 | L17: =IF(E17=0,0,G17/E17) -> 3.2 | M17: =H17*(1+I17) -> 18.36 | N17: =K17+L17+M17+J17 -> 27.96
... B21: 502-7001 | C21: Barricades, signs and traffic handling | D21: MO | E21: 1 | F21: 2800 | G21: 900 | H21: 600 | I21: 0 | J21: 0 | K21: =IF(E21=0,0,F21/E21) -> 2800 | L21: =IF(E21=0,0,G21/E21) -> 900 | M21: =H21*(1+I21) -> 600 | N21: =K21+L21+M21+J21 -> 4300
B23: Labor $/day is the loaded crew (wages, payroll tax, workers' comp), not bare wage. Equipment $/day is internal rate or rented blue-book, including fuel and the operator only if the operator is not already in the labor crew. Material is delivered price. Waste covers yield loss, not sales tax if tax is already in the material price. These starter rates are Dallas-area planning figures for a 2026 letting — replace them with your quotes. HMAC material near $68–$78/ton is binder plus aggregate before haul and placement; if your quote is a furnished-and-placed subcontract, put that price in Sub and zero out labor, equipment, and material.

Sheet BidProposal
A2: BID PROPOSAL · UNIT PRICE SCHEDULE
A3: =CONCATENATE("CSJ ",Project!F6," ",Project!F7," ",Project!F8," ",Project!F9," County ",Project!F10," District Letting ",TEXT(Project!F11,"YYYY-MM-DD")," ",Project!C6) -> CSJ 0047-14-128 US 75 SH 121 to FM 455 Collin County Dallas District Letting 2026-11-04 North Texas Paving, LLC
A4: Yellow cells are inputs. Bid unit price uses the override if one is entered; otherwise direct unit × markup factor. Benchmarks are planning bands, not the engineer's prices. A flag is a review item, not a rejection.
A5: Seq | B5: Bid code | C5: Description | D5: Category | E5: Unit | F5: Quantity | G5: Manual direct | H5: Buildup direct | I5: Direct amount | J5: Factor | K5: Suggested unit | L5: Override unit | M5: Bid unit price | N5: Bid amount | O5: % of bid | P5: Bench low | Q5: Bench typical | R5: Bench high | S5: Flag
A6: =IF('WS Import'!H16="","",ROW()-5) -> 1 | B6: =IF('WS Import'!H16="","",'WS Import'!H16) -> 500-7001 | C6: =IF('WS Import'!H16="","",'WS Import'!C16) -> Mobilization | D6: =IF(B6="","",IF('WS Import'!F16<>"",'WS Import'!F16,IF(LEFT(B6,3)="500","Mobilization",IF(OR(LEFT(B6,3)="502",LEFT(B6,3)="503",LEFT(B6,3)="505",LEFT(B6,3)="512"),"Traffic control",IF(LEFT(B6,3)="506","SW3P",IF(OR(LEFT(B6,3)="100",LEFT(B6,3)="104",LEFT(B6,3)="105",LEFT(B6,3)="110",LEFT(B6,3)="132"),"Earthwork",IF(LEFT(B6,3)="247","Base",IF(OR(LEFT(B6,3)="310",LEFT(B6,3)="316",LEFT(B6,3)="340",LEFT(B6,3)="341",LEFT(B6,3)="344",LEFT(B6,3)="354",LEFT(B6,4)="3076",LEFT(B6,4)="3077",LEFT(B6,4)="3080"),"Paving",IF(OR(LEFT(B6,3)="400",LEFT(B6,3)="416",LEFT(B6,3)="420",LEFT(B6,3)="422",LEFT(B6,3)="432",LEFT(B6,3)="450",LEFT(B6,3)="462",LEFT(B6,3)="464",LEFT(B6,3)="465",LEFT(B6,3)="466",LEFT(B6,3)="467",LEFT(B6,3)="496"),"Drainage",IF(OR(LEFT(B6,3)="164",LEFT(B6,3)="168",LEFT(B6,3)="169",LEFT(B6,3)="529",LEFT(B6,3)="530",LEFT(B6,3)="531"),"Roadside",IF(OR(LEFT(B6,3)="540",LEFT(B6,3)="542",LEFT(B6,3)="544",LEFT(B6,3)="545"),"Safety",IF(OR(LEFT(B6,3)="644",LEFT(B6,3)="636",LEFT(B6,3)="658"),"Signing",IF(OR(LEFT(B6,3)="666",LEFT(B6,3)="668",LEFT(B6,3)="672",LEFT(B6,3)="677",LEFT(B6,3)="678"),"Markings","Other"))))))))))))) -> Mobilization | E6: =IF(B6="","",'WS Import'!D16) -> LS | F6: =IF(B6="","",'WS Import'!E16) -> 1 | G6: 0 | H6: =IF(B6="","",IFERROR(INDEX('Unit Cost'!$N$6:$N$21,MATCH(B6,'Unit Cost'!$B$6:$B$21,0)),0)) -> 0 | I6: =IF(B6="","",F6*IF(H6>0,H6,G6)) -> 0 | J6: =IF(B6="","",IF(B6="500-7001",1,MarkupFactor)) -> 1 | K6: =IF(B6="","",IF(B6="500-7001",Mobilization!C11,IF(F6=0,0,IF(H6>0,H6,G6)*J6))) -> 134053.49 | M6: =IF(B6="","",IF(L6="",K6,L6)) -> 134053.49 | N6: =IF(B6="","",F6*M6) -> 134053.49 | O6: =IF(OR(B6="",$N$156=""),"",N6/$N$156) -> 0.052132701 | P6: 80000 | Q6: 250000 | R6: 450000 | S6: =IF(OR(B6="",F6=""),"",IF(M6=0,"ZERO PRICE",IF(AND(M6>0,M6<=0.05,Q6>1),"TOKEN PRICE",IF(AND(Q6>0,M6<P6*0.5),"UNDER BAND",IF(AND(R6>0,M6>R6*1.5),"OVER BAND",IF(AND(B6="500-7001",$N$156>0,N6/$N$156>0.1),"MOB > 10%","OK")))))) -> OK
A7: =IF('WS Import'!H17="","",ROW()-5) -> 2 | B7: =IF('WS Import'!H17="","",'WS Import'!H17) -> 502-7001 | C7: =IF('WS Import'!H17="","",'WS Import'!C17) -> Barricades, signs and traffic handling | D7: =IF(B7="","",IF('WS Import'!F17<>"",'WS Import'!F17,IF(LEFT(B7,3)="500","Mobilization",IF(OR(LEFT(B7,3)="502",LEFT(B7,3)="503",LEFT(B7,3)="505",LEFT(B7,3)="512"),"Traffic control",IF(LEFT(B7,3)="506","SW3P",IF(OR(LEFT(B7,3)="100",LEFT(B7,3)="104",LEFT(B7,3)="105",LEFT(B7,3)="110",LEFT(B7,3)="132"),"Earthwork",IF(LEFT(B7,3)="247","Base",IF(OR(LEFT(B7,3)="310",LEFT(B7,3)="316",LEFT(B7,3)="340",LEFT(B7,3)="341",LEFT(B7,3)="344",LEFT(B7,3)="354",LEFT(B7,4)="3076",LEFT(B7,4)="3077",LEFT(B7,4)="3080"),"Paving",IF(OR(LEFT(B7,3)="400",LEFT(B7,3)="416",LEFT(B7,3)="420",LEFT(B7,3)="422",LEFT(B7,3)="432",LEFT(B7,3)="450",LEFT(B7,3)="462",LEFT(B7,3)="464",LEFT(B7,3)="465",LEFT(B7,3)="466",LEFT(B7,3)="467",LEFT(B7,3)="496"),"Drainage",IF(OR(LEFT(B7,3)="164",LEFT(B7,3)="168",LEFT(B7,3)="169",LEFT(B7,3)="529",LEFT(B7,3)="530",LEFT(B7,3)="531"),"Roadside",IF(OR(LEFT(B7,3)="540",LEFT(B7,3)="542",LEFT(B7,3)="544",LEFT(B7,3)="545"),"Safety",IF(OR(LEFT(B7,3)="644",LEFT(B7,3)="636",LEFT(B7,3)="658"),"Signing",IF(OR(LEFT(B7,3)="666",LEFT(B7,3)="668",LEFT(B7,3)="672",LEFT(B7,3)="677",LEFT(B7,3)="678"),"Markings","Other"))))))))))))) -> Traffic control | E7: =IF(B7="","",'WS Import'!D17) -> MO | F7: =IF(B7="","",'WS Import'!E17) -> 7 | G7: 0 | H7: =IF(B7="","",IFERROR(INDEX('Unit Cost'!$N$6:$N$21,MATCH(B7,'Unit Cost'!$B$6:$B$21,0)),0)) -> 4300 | I7: =IF(B7="","",F7*IF(H7>0,H7,G7)) -> 30100 | J7: =IF(B7="","",IF(B7="500-7001",1,MarkupFactor)) -> 1.4163822 | K7: =IF(B7="","",IF(B7="500-7001",Mobilization!C11,IF(F7=0,0,IF(H7>0,H7,G7)*J7))) -> 6090.4437 | M7: =IF(B7="","",IF(L7="",K7,L7)) -> 6090.4437 | N7: =IF(B7="","",F7*M7) -> 42633.106 | O7: =IF(OR(B7="",$N$156=""),"",N7/$N$156) -> 0.016579792 | P7: 1800 | Q7: 3900 | R7: 8000 | S7: =IF(OR(B7="",F7=""),"",IF(M7=0,"ZERO PRICE",IF(AND(M7>0,M7<=0.05,Q7>1),"TOKEN PRICE",IF(AND(Q7>0,M7<P7*0.5),"UNDER BAND",IF(AND(R7>0,M7>R7*1.5),"OVER BAND",IF(AND(B7="500-7001",$N$156>0,N7/$N$156>0.1),"MOB > 10%","OK")))))) -> OK
A8: =IF('WS Import'!H18="","",ROW()-5) -> 3 | B8: =IF('WS Import'!H18="","",'WS Import'!H18) -> 503-7001 | C8: =IF('WS Import'!H18="","",'WS Import'!C18) -> Portable changeable message sign | D8: =IF(B8="","",IF('WS Import'!F18<>"",'WS Import'!F18,IF(LEFT(B8,3)="500","Mobilization",IF(OR(LEFT(B8,3)="502",LEFT(B8,3)="503",LEFT(B8,3)="505",LEFT(B8,3)="512"),"Traffic control",IF(LEFT(B8,3)="506","SW3P",IF(OR(LEFT(B8,3)="100",LEFT(B8,3)="104",LEFT(B8,3)="105",LEFT(B8,3)="110",LEFT(B8,3)="132"),"Earthwork",IF(LEFT(B8,3)="247","Base",IF(OR(LEFT(B8,3)="310",LEFT(B8,3)="316",LEFT(B8,3)="340",LEFT(B8,3)="341",LEFT(B8,3)="344",LEFT(B8,3)="354",LEFT(B8,4)="3076",LEFT(B8,4)="3077",LEFT(B8,4)="3080"),"Paving",IF(OR(LEFT(B8,3)="400",LEFT(B8,3)="416",LEFT(B8,3)="420",LEFT(B8,3)="422",LEFT(B8,3)="432",LEFT(B8,3)="450",LEFT(B8,3)="462",LEFT(B8,3)="464",LEFT(B8,3)="465",LEFT(B8,3)="466",LEFT(B8,3)="467",LEFT(B8,3)="496"),"Drainage",IF(OR(LEFT(B8,3)="164",LEFT(B8,3)="168",LEFT(B8,3)="169",LEFT(B8,3)="529",LEFT(B8,3)="530",LEFT(B8,3)="531"),"Roadside",IF(OR(LEFT(B8,3)="540",LEFT(B8,3)="542",LEFT(B8,3)="544",LEFT(B8,3)="545"),"Safety",IF(OR(LEFT(B8,3)="644",LEFT(B8,3)="636",LEFT(B8,3)="658"),"Signing",IF(OR(LEFT(B8,3)="666",LEFT(B8,3)="668",LEFT(B8,3)="672",LEFT(B8,3)="677",LEFT(B8,3)="678"),"Markings","Other"))))))))))))) -> Traffic control | E8: =IF(B8="","",'WS Import'!D18) -> DAY | F8: =IF(B8="","",'WS Import'!E18) -> 140 | G8: 55 | H8: =IF(B8="","",IFERROR(INDEX('Unit Cost'!$N$6:$N$21,MATCH(B8,'Unit Cost'!$B$6:$B$21,0)),0)) -> 0 | I8: =IF(B8="","",F8*IF(H8>0,H8,G8)) -> 7700 | J8: =IF(B8="","",IF(B8="500-7001",1,MarkupFactor)) -> 1.4163822 | K8: =IF(B8="","",IF(B8="500-7001",Mobilization!C11,IF(F8=0,0,IF(H8>0,H8,G8)*J8))) -> 77.901024 | M8: =IF(B8="","",IF(L8="",K8,L8)) -> 77.901024 | N8: =IF(B8="","",F8*M8) -> 10906.143 | O8: =IF(OR(B8="",$N$156=""),"",N8/$N$156) -> 0.0042413421 | P8: 40 | Q8: 90 | R8: 145 | S8: =IF(OR(B8="",F8=""),"",IF(M8=0,"ZERO PRICE",IF(AND(M8>0,M8<=0.05,Q8>1),"TOKEN PRICE",IF(AND(Q8>0,M8<P8*0.5),"UNDER BAND",IF(AND(R8>0,M8>R8*1.5),"OVER BAND",IF(AND(B8="500-7001",$N$156>0,N8/$N$156>0.1),"MOB > 10%","OK")))))) -> OK
A9: =IF('WS Import'!H19="","",ROW()-5) -> 4 | B9: =IF('WS Import'!H19="","",'WS Import'!H19) -> 505-7001 | C9: =IF('WS Import'!H19="","",'WS Import'!C19) -> TMA (stationary) | D9: =IF(B9="","",IF('WS Import'!F19<>"",'WS Import'!F19,IF(LEFT(B9,3)="500","Mobilization",IF(OR(LEFT(B9,3)="502",LEFT(B9,3)="503",LEFT(B9,3)="505",LEFT(B9,3)="512"),"Traffic control",IF(LEFT(B9,3)="506","SW3P",IF(OR(LEFT(B9,3)="100",LEFT(B9,3)="104",LEFT(B9,3)="105",LEFT(B9,3)="110",LEFT(B9,3)="132"),"Earthwork",IF(LEFT(B9,3)="247","Base",IF(OR(LEFT(B9,3)="310",LEFT(B9,3)="316",LEFT(B9,3)="340",LEFT(B9,3)="341",LEFT(B9,3)="344",LEFT(B9,3)="354",LEFT(B9,4)="3076",LEFT(B9,4)="3077",LEFT(B9,4)="3080"),"Paving",IF(OR(LEFT(B9,3)="400",LEFT(B9,3)="416",LEFT(B9,3)="420",LEFT(B9,3)="422",LEFT(B9,3)="432",LEFT(B9,3)="450",LEFT(B9,3)="462",LEFT(B9,3)="464",LEFT(B9,3)="465",LEFT(B9,3)="466",LEFT(B9,3)="467",LEFT(B9,3)="496"),"Drainage",IF(OR(LEFT(B9,3)="164",LEFT(B9,3)="168",LEFT(B9,3)="169",LEFT(B9,3)="529",LEFT(B9,3)="530",LEFT(B9,3)="531"),"Roadside",IF(OR(LEFT(B9,3)="540",LEFT(B9,3)="542",LEFT(B9,3)="544",LEFT(B9,3)="545"),"Safety",IF(OR(LEFT(B9,3)="644",LEFT(B9,3)="636",LEFT(B9,3)="658"),"Signing",IF(OR(LEFT(B9,3)="666",LEFT(B9,3)="668",LEFT(B9,3)="672",LEFT(B9,3)="677",LEFT(B9,3)="678"),"Markings","Other"))))))))))))) -> Traffic control | E9: =IF(B9="","",'WS Import'!D19) -> DAY | F9: =IF(B9="","",'WS Import'!E19) -> 140 | G9: 185 | H9: =IF(B9="","",IFERROR(INDEX('Unit Cost'!$N$6:$N$21,MATCH(B9,'Unit Cost'!$B$6:$B$21,0)),0)) -> 0 | I9: =IF(B9="","",F9*IF(H9>0,H9,G9)) -> 25900 | J9: =IF(B9="","",IF(B9="500-7001",1,MarkupFactor)) -> 1.4163822 | K9: =IF(B9="","",IF(B9="500-7001",Mobilization!C11,IF(F9=0,0,IF(H9>0,H9,G9)*J9))) -> 262.03072 | M9: =IF(B9="","",IF(L9="",K9,L9)) -> 262.03072 | N9: =IF(B9="","",F9*M9) -> 36684.3 | O9: =IF(OR(B9="",$N$156=""),"",N9/$N$156) -> 0.014266332 | P9: 50 | Q9: 150 | R9: 300 | S9: =IF(OR(B9="",F9=""),"",IF(M9=0,"ZERO PRICE",IF(AND(M9>0,M9<=0.05,Q9>1),"TOKEN PRICE",IF(AND(Q9>0,M9<P9*0.5),"UNDER BAND",IF(AND(R9>0,M9>R9*1.5),"OVER BAND",IF(AND(B9="500-7001",$N$156>0,N9/$N$156>0.1),"MOB > 10%","OK")))))) -> OK
A10: =IF('WS Import'!H20="","",ROW()-5) -> 5 | B10: =IF('WS Import'!H20="","",'WS Import'!H20) -> 505-7003 | C10: =IF('WS Import'!H20="","",'WS Import'!C20) -> TMA (mobile operation) | D10: =IF(B10="","",IF('WS Import'!F20<>"",'WS Import'!F20,IF(LEFT(B10,3)="500","Mobilization",IF(OR(LEFT(B10,3)="502",LEFT(B10,3)="503",LEFT(B10,3)="505",LEFT(B10,3)="512"),"Traffic control",IF(LEFT(B10,3)="506","SW3P",IF(OR(LEFT(B10,3)="100",LEFT(B10,3)="104",LEFT(B10,3)="105",LEFT(B10,3)="110",LEFT(B10,3)="132"),"Earthwork",IF(LEFT(B10,3)="247","Base",IF(OR(LEFT(B10,3)="310",LEFT(B10,3)="316",LEFT(B10,3)="340",LEFT(B10,3)="341",LEFT(B10,3)="344",LEFT(B10,3)="354",LEFT(B10,4)="3076",LEFT(B10,4)="3077",LEFT(B10,4)="3080"),"Paving",IF(OR(LEFT(B10,3)="400",LEFT(B10,3)="416",LEFT(B10,3)="420",LEFT(B10,3)="422",LEFT(B10,3)="432",LEFT(B10,3)="450",LEFT(B10,3)="462",LEFT(B10,3)="464",LEFT(B10,3)="465",LEFT(B10,3)="466",LEFT(B10,3)="467",LEFT(B10,3)="496"),"Drainage",IF(OR(LEFT(B10,3)="164",LEFT(B10,3)="168",LEFT(B10,3)="169",LEFT(B10,3)="529",LEFT(B10,3)="530",LEFT(B10,3)="531"),"Roadside",IF(OR(LEFT(B10,3)="540",LEFT(B10,3)="542",LEFT(B10,3)="544",LEFT(B10,3)="545"),"Safety",IF(OR(LEFT(B10,3)="644",LEFT(B10,3)="636",LEFT(B10,3)="658"),"Signing",IF(OR(LEFT(B10,3)="666",LEFT(B10,3)="668",LEFT(B10,3)="672",LEFT(B10,3)="677",LEFT(B10,3)="678"),"Markings","Other"))))))))))))) -> Traffic control | E10: =IF(B10="","",'WS Import'!D20) -> DAY | F10: =IF(B10="","",'WS Import'!E20) -> 30 | G10: 220 | H10: =IF(B10="","",IFERROR(INDEX('Unit Cost'!$N$6:$N$21,MATCH(B10,'Unit Cost'!$B$6:$B$21,0)),0)) -> 0 | I10: =IF(B10="","",F10*IF(H10>0,H10,G10)) -> 6600 | J10: =IF(B10="","",IF(B10="500-7001",1,MarkupFactor)) -> 1.4163822 | K10: =IF(B10="","",IF(B10="500-7001",Mobilization!C11,IF(F10=0,0,IF(H10>0,H10,G10)*J10))) -> 311.60409 | M10: =IF(B10="","",IF(L10="",K10,L10)) -> 311.60409 | N10: =IF(B10="","",F10*M10) -> 9348.1228 | O10: =IF(OR(B10="",$N$156=""),"",N10/$N$156) -> 0.0036354361 | P10: 40 | Q10: 110 | R10: 450 | S10: =IF(OR(B10="",F10=""),"",IF(M10=0,"ZERO PRICE",IF(AND(M10>0,M10<=0.05,Q10>1),"TOKEN PRICE",IF(AND(Q10>0,M10<P10*0.5),"UNDER BAND",IF(AND(R10>0,M10>R10*1.5),"OVER BAND",IF(AND(B10="500-7001",$N$156>0,N10/$N$156>0.1),"MOB > 10%","OK")))))) -> OK
A11: =IF('WS Import'!H21="","",ROW()-5) -> 6 | B11: =IF('WS Import'!H21="","",'WS Import'!H21) -> 506-7039 | C11: =IF('WS Import'!H21="","",'WS Import'!C21) -> Temp sedmt cont fence (install) | D11: =IF(B11="","",IF('WS Import'!F21<>"",'WS Import'!F21,IF(LEFT(B11,3)="500","Mobilization",IF(OR(LEFT(B11,3)="502",LEFT(B11,3)="503",LEFT(B11,3)="505",LEFT(B11,3)="512"),"Traffic control",IF(LEFT(B11,3)="506","SW3P",IF(OR(LEFT(B11,3)="100",LEFT(B11,3)="104",LEFT(B11,3)="105",LEFT(B11,3)="110",LEFT(B11,3)="132"),"Earthwork",IF(LEFT(B11,3)="247","Base",IF(OR(LEFT(B11,3)="310",LEFT(B11,3)="316",LEFT(B11,3)="340",LEFT(B11,3)="341",LEFT(B11,3)="344",LEFT(B11,3)="354",LEFT(B11,4)="3076",LEFT(B11,4)="3077",LEFT(B11,4)="3080"),"Paving",IF(OR(LEFT(B11,3)="400",LEFT(B11,3)="416",LEFT(B11,3)="420",LEFT(B11,3)="422",LEFT(B11,3)="432",LEFT(B11,3)="450",LEFT(B11,3)="462",LEFT(B11,3)="464",LEFT(B11,3)="465",LEFT(B11,3)="466",LEFT(B11,3)="467",LEFT(B11,3)="496"),"Drainage",IF(OR(LEFT(B11,3)="164",LEFT(B11,3)="168",LEFT(B11,3)="169",LEFT(B11,3)="529",LEFT(B11,3)="530",LEFT(B11,3)="531"),"Roadside",IF(OR(LEFT(B11,3)="540",LEFT(B11,3)="542",LEFT(B11,3)="544",LEFT(B11,3)="545"),"Safety",IF(OR(LEFT(B11,3)="644",LEFT(B11,3)="636",LEFT(B11,3)="658"),"Signing",IF(OR(LEFT(B11,3)="666",LEFT(B11,3)="668",LEFT(B11,3)="672",LEFT(B11,3)="677",LEFT(B11,3)="678"),"Markings","Other"))))))))))))) -> SW3P | E11: =IF(B11="","",'WS Import'!D21) -> LF | F11: =IF(B11="","",'WS Import'!E21) -> 4200 | G11: 0 | H11: =IF(B11="","",IFERROR(INDEX('Unit Cost'!$N$6:$N$21,MATCH(B11,'Unit Cost'!$B$6:$B$21,0)),0)) -> 2.1886667 | I11: =IF(B11="","",F11*IF(H11>0,H11,G11)) -> 9192.4 | J11: =IF(B11="","",IF(B11="500-7001",1,MarkupFactor)) -> 1.4163822 | K11: =IF(B11="","",IF(B11="500-7001",Mobilization!C11,IF(F11=0,0,IF(H11>0,H11,G11)*J11))) -> 3.0999886 | M11: =IF(B11="","",IF(L11="",K11,L11)) -> 3.0999886 | N11: =IF(B11="","",F11*M11) -> 13019.952 | O11: =IF(OR(B11="",$N$156=""),"",N11/$N$156) -> 0.0050633913 | P11: 3.25 | Q11: 4 | R11: 5.5 | S11: =IF(OR(B11="",F11=""),"",IF(M11=0,"ZERO PRICE",IF(AND(M11>0,M11<=0.05,Q11>1),"TOKEN PRICE",IF(AND(Q11>0,M11<P11*0.5),"UNDER BAND",IF(AND(R11>0,M11>R11*1.5),"OVER BAND",IF(AND(B11="500-7001",$N$156>0,N11/$N$156>0.1),"MOB > 10%","OK")))))) -> OK
A12: =IF('WS Import'!H22="","",ROW()-5) -> 7 | B12: =IF('WS Import'!H22="","",'WS Import'!H22) -> 506-7041 | C12: =IF('WS Import'!H22="","",'WS Import'!C22) -> Temp sedmt cont fence (remove) | D12: =IF(B12="","",IF('WS Import'!F22<>"",'WS Import'!F22,IF(LEFT(B12,3)="500","Mobilization",IF(OR(LEFT(B12,3)="502",LEFT(B12,3)="503",LEFT(B12,3)="505",LEFT(B12,3)="512"),"Traffic control",IF(LEFT(B12,3)="506","SW3P",IF(OR(LEFT(B12,3)="100",LEFT(B12,3)="104",LEFT(B12,3)="105",LEFT(B12,3)="110",LEFT(B12,3)="132"),"Earthwork",IF(LEFT(B12,3)="247","Base",IF(OR(LEFT(B12,3)="310",LEFT(B12,3)="316",LEFT(B12,3)="340",LEFT(B12,3)="341",LEFT(B12,3)="344",LEFT(B12,3)="354",LEFT(B12,4)="3076",LEFT(B12,4)="3077",LEFT(B12,4)="3080"),"Paving",IF(OR(LEFT(B12,3)="400",LEFT(B12,3)="416",LEFT(B12,3)="420",LEFT(B12,3)="422",LEFT(B12,3)="432",LEFT(B12,3)="450",LEFT(B12,3)="462",LEFT(B12,3)="464",LEFT(B12,3)="465",LEFT(B12,3)="466",LEFT(B12,3)="467",LEFT(B12,3)="496"),"Drainage",IF(OR(LEFT(B12,3)="164",LEFT(B12,3)="168",LEFT(B12,3)="169",LEFT(B12,3)="529",LEFT(B12,3)="530",LEFT(B12,3)="531"),"Roadside",IF(OR(LEFT(B12,3)="540",LEFT(B12,3)="542",LEFT(B12,3)="544",LEFT(B12,3)="545"),"Safety",IF(OR(LEFT(B12,3)="644",LEFT(B12,3)="636",LEFT(B12,3)="658"),"Signing",IF(OR(LEFT(B12,3)="666",LEFT(B12,3)="668",LEFT(B12,3)="672",LEFT(B12,3)="677",LEFT(B12,3)="678"),"Markings","Other"))))))))))))) -> SW3P | E12: =IF(B12="","",'WS Import'!D22) -> LF | F12: =IF(B12="","",'WS Import'!E22) -> 4200 | G12: 0.85 | H12: =IF(B12="","",IFERROR(INDEX('Unit Cost'!$N$6:$N$21,MATCH(B12,'Unit Cost'!$B$6:$B$21,0)),0)) -> 0 | I12: =IF(B12="","",F12*IF(H12>0,H12,G12)) -> 3570 | J12: =IF(B12="","",IF(B12="500-7001",1,MarkupFactor)) -> 1.4163822 | K12: =IF(B12="","",IF(B12="500-7001",Mobilization!C11,IF(F12=0,0,IF(H12>0,H12,G12)*J12))) -> 1.2039249 | M12: =IF(B12="","",IF(L12="",K12,L12)) -> 1.2039249 | N12: =IF(B12="","",F12*M12) -> 5056.4846 | O12: =IF(OR(B12="",$N$156=""),"",N12/$N$156) -> 0.0019664404 | P12: 0.75 | Q12: 1 | R12: 1.5 | S12: =IF(OR(B12="",F12=""),"",IF(M12=0,"ZERO PRICE",IF(AND(M12>0,M12<=0.05,Q12>1),"TOKEN PRICE",IF(AND(Q12>0,M12<P12*0.5),"UNDER BAND",IF(AND(R12>0,M12>R12*1.5),"OVER BAND",IF(AND(B12="500-7001",$N$156>0,N12/$N$156>0.1),"MOB > 10%","OK")))))) -> OK
A13: =IF('WS Import'!H23="","",ROW()-5) -> 8 | B13: =IF('WS Import'!H23="","",'WS Import'!H23) -> 100-7002 | C13: =IF('WS Import'!H23="","",'WS Import'!C23) -> Preparing right of way | D13: =IF(B13="","",IF('WS Import'!F23<>"",'WS Import'!F23,IF(LEFT(B13,3)="500","Mobilization",IF(OR(LEFT(B13,3)="502",LEFT(B13,3)="503",LEFT(B13,3)="505",LEFT(B13,3)="512"),"Traffic control",IF(LEFT(B13,3)="506","SW3P",IF(OR(LEFT(B13,3)="100",LEFT(B13,3)="104",LEFT(B13,3)="105",LEFT(B13,3)="110",LEFT(B13,3)="132"),"Earthwork",IF(LEFT(B13,3)="247","Base",IF(OR(LEFT(B13,3)="310",LEFT(B13,3)="316",LEFT(B13,3)="340",LEFT(B13,3)="341",LEFT(B13,3)="344",LEFT(B13,3)="354",LEFT(B13,4)="3076",LEFT(B13,4)="3077",LEFT(B13,4)="3080"),"Paving",IF(OR(LEFT(B13,3)="400",LEFT(B13,3)="416",LEFT(B13,3)="420",LEFT(B13,3)="422",LEFT(B13,3)="432",LEFT(B13,3)="450",LEFT(B13,3)="462",LEFT(B13,3)="464",LEFT(B13,3)="465",LEFT(B13,3)="466",LEFT(B13,3)="467",LEFT(B13,3)="496"),"Drainage",IF(OR(LEFT(B13,3)="164",LEFT(B13,3)="168",LEFT(B13,3)="169",LEFT(B13,3)="529",LEFT(B13,3)="530",LEFT(B13,3)="531"),"Roadside",IF(OR(LEFT(B13,3)="540",LEFT(B13,3)="542",LEFT(B13,3)="544",LEFT(B13,3)="545"),"Safety",IF(OR(LEFT(B13,3)="644",LEFT(B13,3)="636",LEFT(B13,3)="658"),"Signing",IF(OR(LEFT(B13,3)="666",LEFT(B13,3)="668",LEFT(B13,3)="672",LEFT(B13,3)="677",LEFT(B13,3)="678"),"Markings","Other"))))))))))))) -> Earthwork | E13: =IF(B13="","",'WS Import'!D23) -> STA | F13: =IF(B13="","",'WS Import'!E23) -> 18 | G13: 1400 | H13: =IF(B13="","",IFERROR(INDEX('Unit Cost'!$N$6:$N$21,MATCH(B13,'Unit Cost'!$B$6:$B$21,0)),0)) -> 0 | I13: =IF(B13="","",F13*IF(H13>0,H13,G13)) -> 25200 | J13: =IF(B13="","",IF(B13="500-7001",1,MarkupFactor)) -> 1.4163822 | K13: =IF(B13="","",IF(B13="500-7001",Mobilization!C11,IF(F13=0,0,IF(H13>0,H13,G13)*J13))) -> 1982.9351 | M13: =IF(B13="","",IF(L13="",K13,L13)) -> 1982.9351 | N13: =IF(B13="","",F13*M13) -> 35692.833 | O13: =IF(OR(B13="",$N$156=""),"",N13/$N$156) -> 0.013880756 | P13: 800 | Q13: 1500 | R13: 2800 | S13: =IF(OR(B13="",F13=""),"",IF(M13=0,"ZERO PRICE",IF(AND(M13>0,M13<=0.05,Q13>1),"TOKEN PRICE",IF(AND(Q13>0,M13<P13*0.5),"UNDER BAND",IF(AND(R13>0,M13>R13*1.5),"OVER BAND",IF(AND(B13="500-7001",$N$156>0,N13/$N$156>0.1),"MOB > 10%","OK")))))) -> OK
A14: =IF('WS Import'!H24="","",ROW()-5) -> 9 | B14: =IF('WS Import'!H24="","",'WS Import'!H24) -> 104-7006 | C14: =IF('WS Import'!H24="","",'WS Import'!C24) -> Removing conc (pav) | D14: =IF(B14="","",IF('WS Import'!F24<>"",'WS Import'!F24,IF(LEFT(B14,3)="500","Mobilization",IF(OR(LEFT(B14,3)="502",LEFT(B14,3)="503",LEFT(B14,3)="505",LEFT(B14,3)="512"),"Traffic control",IF(LEFT(B14,3)="506","SW3P",IF(OR(LEFT(B14,3)="100",LEFT(B14,3)="104",LEFT(B14,3)="105",LEFT(B14,3)="110",LEFT(B14,3)="132"),"Earthwork",IF(LEFT(B14,3)="247","Base",IF(OR(LEFT(B14,3)="310",LEFT(B14,3)="316",LEFT(B14,3)="340",LEFT(B14,3)="341",LEFT(B14,3)="344",LEFT(B14,3)="354",LEFT(B14,4)="3076",LEFT(B14,4)="3077",LEFT(B14,4)="3080"),"Paving",IF(OR(LEFT(B14,3)="400",LEFT(B14,3)="416",LEFT(B14,3)="420",LEFT(B14,3)="422",LEFT(B14,3)="432",LEFT(B14,3)="450",LEFT(B14,3)="462",LEFT(B14,3)="464",LEFT(B14,3)="465",LEFT(B14,3)="466",LEFT(B14,3)="467",LEFT(B14,3)="496"),"Drainage",IF(OR(LEFT(B14,3)="164",LEFT(B14,3)="168",LEFT(B14,3)="169",LEFT(B14,3)="529",LEFT(B14,3)="530",LEFT(B14,3)="531"),"Roadside",IF(OR(LEFT(B14,3)="540",LEFT(B14,3)="542",LEFT(B14,3)="544",LEFT(B14,3)="545"),"Safety",IF(OR(LEFT(B14,3)="644",LEFT(B14,3)="636",LEFT(B14,3)="658"),"Signing",IF(OR(LEFT(B14,3)="666",LEFT(B14,3)="668",LEFT(B14,3)="672",LEFT(B14,3)="677",LEFT(B14,3)="678"),"Markings","Other"))))))))))))) -> Earthwork | E14: =IF(B14="","",'WS Import'!D24) -> SY | F14: =IF(B14="","",'WS Import'!E24) -> 2800 | G14: 12.5 | H14: =IF(B14="","",IFERROR(INDEX('Unit Cost'!$N$6:$N$21,MATCH(B14,'Unit Cost'!$B$6:$B$21,0)),0)) -> 0 | I14: =IF(B14="","",F14*IF(H14>0,H14,G14)) -> 35000 | J14: =IF(B14="","",IF(B14="500-7001",1,MarkupFactor)) -> 1.4163822 | K14: =IF(B14="","",IF(B14="500-7001",Mobilization!C11,IF(F14=0,0,IF(H14>0,H14,G14)*J14))) -> 17.704778 | M14: =IF(B14="","",IF(L14="",K14,L14)) -> 17.704778 | N14: =IF(B14="","",F14*M14) -> 49573.379 | O14: =IF(OR(B14="",$N$156=""),"",N14/$N$156) -> 0.019278828 | P14: 8 | Q14: 14 | R14: 22 | S14: =IF(OR(B14="",F14=""),"",IF(M14=0,"ZERO PRICE",IF(AND(M14>0,M14<=0.05,Q14>1),"TOKEN PRICE",IF(AND(Q14>0,M14<P14*0.5),"UNDER BAND",IF(AND(R14>0,M14>R14*1.5),"OVER BAND",IF(AND(B14="500-7001",$N$156>0,N14/$N$156>0.1),"MOB > 10%","OK")))))) -> OK
A15: =IF('WS Import'!H25="","",ROW()-5) -> 10 | B15: =IF('WS Import'!H25="","",'WS Import'!H25) -> 110-7001 | C15: =IF('WS Import'!H25="","",'WS Import'!C25) -> Excavation (roadway) | D15: =IF(B15="","",IF('WS Import'!F25<>"",'WS Import'!F25,IF(LEFT(B15,3)="500","Mobilization",IF(OR(LEFT(B15,3)="502",LEFT(B15,3)="503",LEFT(B15,3)="505",LEFT(B15,3)="512"),"Traffic control",IF(LEFT(B15,3)="506","SW3P",IF(OR(LEFT(B15,3)="100",LEFT(B15,3)="104",LEFT(B15,3)="105",LEFT(B15,3)="110",LEFT(B15,3)="132"),"Earthwork",IF(LEFT(B15,3)="247","Base",IF(OR(LEFT(B15,3)="310",LEFT(B15,3)="316",LEFT(B15,3)="340",LEFT(B15,3)="341",LEFT(B15,3)="344",LEFT(B15,3)="354",LEFT(B15,4)="3076",LEFT(B15,4)="3077",LEFT(B15,4)="3080"),"Paving",IF(OR(LEFT(B15,3)="400",LEFT(B15,3)="416",LEFT(B15,3)="420",LEFT(B15,3)="422",LEFT(B15,3)="432",LEFT(B15,3)="450",LEFT(B15,3)="462",LEFT(B15,3)="464",LEFT(B15,3)="465",LEFT(B15,3)="466",LEFT(B15,3)="467",LEFT(B15,3)="496"),"Drainage",IF(OR(LEFT(B15,3)="164",LEFT(B15,3)="168",LEFT(B15,3)="169",LEFT(B15,3)="529",LEFT(B15,3)="530",LEFT(B15,3)="531"),"Roadside",IF(OR(LEFT(B15,3)="540",LEFT(B15,3)="542",LEFT(B15,3)="544",LEFT(B15,3)="545"),"Safety",IF(OR(LEFT(B15,3)="644",LEFT(B15,3)="636",LEFT(B15,3)="658"),"Signing",IF(OR(LEFT(B15,3)="666",LEFT(B15,3)="668",LEFT(B15,3)="672",LEFT(B15,3)="677",LEFT(B15,3)="678"),"Markings","Other"))))))))))))) -> Earthwork | E15: =IF(B15="","",'WS Import'!D25) -> CY | F15: =IF(B15="","",'WS Import'!E25) -> 8600 | G15: 0 | H15: =IF(B15="","",IFERROR(INDEX('Unit Cost'!$N$6:$N$21,MATCH(B15,'Unit Cost'!$B$6:$B$21,0)),0)) -> 6.1111111 | I15: =IF(B15="","",F15*IF(H15>0,H15,G15)) -> 52555.556 | J15: =IF(B15="","",IF(B15="500-7001",1,MarkupFactor)) -> 1.4163822 | K15: =IF(B15="","",IF(B15="500-7001",Mobilization!C11,IF(F15=0,0,IF(H15>0,H15,G15)*J15))) -> 8.6556693 | M15: =IF(B15="","",IF(L15="",K15,L15)) -> 8.6556693 | N15: =IF(B15="","",F15*M15) -> 74438.756 | O15: =IF(OR(B15="",$N$156=""),"",N15/$N$156) -> 0.028948843 | P15: 8 | Q15: 12 | R15: 18 | S15: =IF(OR(B15="",F15=""),"",IF(M15=0,"ZERO PRICE",IF(AND(M15>0,M15<=0.05,Q15>1),"TOKEN PRICE",IF(AND(Q15>0,M15<P15*0.5),"UNDER BAND",IF(AND(R15>0,M15>R15*1.5),"OVER BAND",IF(AND(B15="500-7001",$N$156>0,N15/$N$156>0.1),"MOB > 10%","OK")))))) -> OK
A16: =IF('WS Import'!H26="","",ROW()-5) -> 11 | B16: =IF('WS Import'!H26="","",'WS Import'!H26) -> 132-7005 | C16: =IF('WS Import'!H26="","",'WS Import'!C26) -> Embankment (final)(ord comp)(ty C) | D16: =IF(B16="","",IF('WS Import'!F26<>"",'WS Import'!F26,IF(LEFT(B16,3)="500","Mobilization",IF(OR(LEFT(B16,3)="502",LEFT(B16,3)="503",LEFT(B16,3)="505",LEFT(B16,3)="512"),"Traffic control",IF(LEFT(B16,3)="506","SW3P",IF(OR(LEFT(B16,3)="100",LEFT(B16,3)="104",LEFT(B16,3)="105",LEFT(B16,3)="110",LEFT(B16,3)="132"),"Earthwork",IF(LEFT(B16,3)="247","Base",IF(OR(LEFT(B16,3)="310",LEFT(B16,3)="316",LEFT(B16,3)="340",LEFT(B16,3)="341",LEFT(B16,3)="344",LEFT(B16,3)="354",LEFT(B16,4)="3076",LEFT(B16,4)="3077",LEFT(B16,4)="3080"),"Paving",IF(OR(LEFT(B16,3)="400",LEFT(B16,3)="416",LEFT(B16,3)="420",LEFT(B16,3)="422",LEFT(B16,3)="432",LEFT(B16,3)="450",LEFT(B16,3)="462",LEFT(B16,3)="464",LEFT(B16,3)="465",LEFT(B16,3)="466",LEFT(B16,3)="467",LEFT(B16,3)="496"),"Drainage",IF(OR(LEFT(B16,3)="164",LEFT(B16,3)="168",LEFT(B16,3)="169",LEFT(B16,3)="529",LEFT(B16,3)="530",LEFT(B16,3)="531"),"Roadside",IF(OR(LEFT(B16,3)="540",LEFT(B16,3)="542",LEFT(B16,3)="544",LEFT(B16,3)="545"),"Safety",IF(OR(LEFT(B16,3)="644",LEFT(B16,3)="636",LEFT(B16,3)="658"),"Signing",IF(OR(LEFT(B16,3)="666",LEFT(B16,3)="668",LEFT(B16,3)="672",LEFT(B16,3)="677",LEFT(B16,3)="678"),"Markings","Other"))))))))))))) -> Earthwork | E16: =IF(B16="","",'WS Import'!D26) -> CY | F16: =IF(B16="","",'WS Import'!E26) -> 4100 | G16: 0 | H16: =IF(B16="","",IFERROR(INDEX('Unit Cost'!$N$6:$N$21,MATCH(B16,'Unit Cost'!$B$6:$B$21,0)),0)) -> 13.686667 | I16: =IF(B16="","",F16*IF(H16>0,H16,G16)) -> 56115.333 | J16: =IF(B16="","",IF(B16="500-7001",1,MarkupFactor)) -> 1.4163822 | K16: =IF(B16="","",IF(B16="500-7001",Mobilization!C11,IF(F16=0,0,IF(H16>0,H16,G16)*J16))) -> 19.385552 | M16: =IF(B16="","",IF(L16="",K16,L16)) -> 19.385552 | N16: =IF(B16="","",F16*M16) -> 79480.762 | O16: =IF(OR(B16="",$N$156=""),"",N16/$N$156) -> 0.030909653 | P16: 8 | Q16: 14 | R16: 22 | S16: =IF(OR(B16="",F16=""),"",IF(M16=0,"ZERO PRICE",IF(AND(M16>0,M16<=0.05,Q16>1),"TOKEN PRICE",IF(AND(Q16>0,M16<P16*0.5),"UNDER BAND",IF(AND(R16>0,M16>R16*1.5),"OVER BAND",IF(AND(B16="500-7001",$N$156>0,N16/$N$156>0.1),"MOB > 10%","OK")))))) -> OK
A17: =IF('WS Import'!H27="","",ROW()-5) -> 12 | B17: =IF('WS Import'!H27="","",'WS Import'!H27) -> 164-7002 | C17: =IF('WS Import'!H27="","",'WS Import'!C27) -> Broadcast seed (perm)(rural)(clay) | D17: =IF(B17="","",IF('WS Import'!F27<>"",'WS Import'!F27,IF(LEFT(B17,3)="500","Mobilization",IF(OR(LEFT(B17,3)="502",LEFT(B17,3)="503",LEFT(B17,3)="505",LEFT(B17,3)="512"),"Traffic control",IF(LEFT(B17,3)="506","SW3P",IF(OR(LEFT(B17,3)="100",LEFT(B17,3)="104",LEFT(B17,3)="105",LEFT(B17,3)="110",LEFT(B17,3)="132"),"Earthwork",IF(LEFT(B17,3)="247","Base",IF(OR(LEFT(B17,3)="310",LEFT(B17,3)="316",LEFT(B17,3)="340",LEFT(B17,3)="341",LEFT(B17,3)="344",LEFT(B17,3)="354",LEFT(B17,4)="3076",LEFT(B17,4)="3077",LEFT(B17,4)="3080"),"Paving",IF(OR(LEFT(B17,3)="400",LEFT(B17,3)="416",LEFT(B17,3)="420",LEFT(B17,3)="422",LEFT(B17,3)="432",LEFT(B17,3)="450",LEFT(B17,3)="462",LEFT(B17,3)="464",LEFT(B17,3)="465",LEFT(B17,3)="466",LEFT(B17,3)="467",LEFT(B17,3)="496"),"Drainage",IF(OR(LEFT(B17,3)="164",LEFT(B17,3)="168",LEFT(B17,3)="169",LEFT(B17,3)="529",LEFT(B17,3)="530",LEFT(B17,3)="531"),"Roadside",IF(OR(LEFT(B17,3)="540",LEFT(B17,3)="542",LEFT(B17,3)="544",LEFT(B17,3)="545"),"Safety",IF(OR(LEFT(B17,3)="644",LEFT(B17,3)="636",LEFT(B17,3)="658"),"Signing",IF(OR(LEFT(B17,3)="666",LEFT(B17,3)="668",LEFT(B17,3)="672",LEFT(B17,3)="677",LEFT(B17,3)="678"),"Markings","Other"))))))))))))) -> Roadside | E17: =IF(B17="","",'WS Import'!D27) -> SY | F17: =IF(B17="","",'WS Import'!E27) -> 18000 | G17: 0 | H17: =IF(B17="","",IFERROR(INDEX('Unit Cost'!$N$6:$N$21,MATCH(B17,'Unit Cost'!$B$6:$B$21,0)),0)) -> 0.4765 | I17: =IF(B17="","",F17*IF(H17>0,H17,G17)) -> 8577 | J17: =IF(B17="","",IF(B17="500-7001",1,MarkupFactor)) -> 1.4163822 | K17: =IF(B17="","",IF(B17="500-7001",Mobilization!C11,IF(F17=0,0,IF(H17>0,H17,G17)*J17))) -> 0.67490614 | M17: =IF(B17="","",IF(L17="",K17,L17)) -> 0.67490614 | N17: =IF(B17="","",F17*M17) -> 12148.311 | O17: =IF(OR(B17="",$N$156=""),"",N17/$N$156) -> 0.0047244144 | P17: 0.35 | Q17: 0.65 | R17: 1.1 | S17: =IF(OR(B17="",F17=""),"",IF(M17=0,"ZERO PRICE",IF(AND(M17>0,M17<=0.05,Q17>1),"TOKEN PRICE",IF(AND(Q17>0,M17<P17*0.5),"UNDER BAND",IF(AND(R17>0,M17>R17*1.5),"OVER BAND",IF(AND(B17="500-7001",$N$156>0,N17/$N$156>0.1),"MOB > 10%","OK")))))) -> OK
A18: =IF('WS Import'!H28="","",ROW()-5) -> 13 | B18: =IF('WS Import'!H28="","",'WS Import'!H28) -> 168-7001 | C18: =IF('WS Import'!H28="","",'WS Import'!C28) -> Vegetative watering | D18: =IF(B18="","",IF('WS Import'!F28<>"",'WS Import'!F28,IF(LEFT(B18,3)="500","Mobilization",IF(OR(LEFT(B18,3)="502",LEFT(B18,3)="503",LEFT(B18,3)="505",LEFT(B18,3)="512"),"Traffic control",IF(LEFT(B18,3)="506","SW3P",IF(OR(LEFT(B18,3)="100",LEFT(B18,3)="104",LEFT(B18,3)="105",LEFT(B18,3)="110",LEFT(B18,3)="132"),"Earthwork",IF(LEFT(B18,3)="247","Base",IF(OR(LEFT(B18,3)="310",LEFT(B18,3)="316",LEFT(B18,3)="340",LEFT(B18,3)="341",LEFT(B18,3)="344",LEFT(B18,3)="354",LEFT(B18,4)="3076",LEFT(B18,4)="3077",LEFT(B18,4)="3080"),"Paving",IF(OR(LEFT(B18,3)="400",LEFT(B18,3)="416",LEFT(B18,3)="420",LEFT(B18,3)="422",LEFT(B18,3)="432",LEFT(B18,3)="450",LEFT(B18,3)="462",LEFT(B18,3)="464",LEFT(B18,3)="465",LEFT(B18,3)="466",LEFT(B18,3)="467",LEFT(B18,3)="496"),"Drainage",IF(OR(LEFT(B18,3)="164",LEFT(B18,3)="168",LEFT(B18,3)="169",LEFT(B18,3)="529",LEFT(B18,3)="530",LEFT(B18,3)="531"),"Roadside",IF(OR(LEFT(B18,3)="540",LEFT(B18,3)="542",LEFT(B18,3)="544",LEFT(B18,3)="545"),"Safety",IF(OR(LEFT(B18,3)="644",LEFT(B18,3)="636",LEFT(B18,3)="658"),"Signing",IF(OR(LEFT(B18,3)="666",LEFT(B18,3)="668",LEFT(B18,3)="672",LEFT(B18,3)="677",LEFT(B18,3)="678"),"Markings","Other"))))))))))))) -> Roadside | E18: =IF(B18="","",'WS Import'!D28) -> TGL | F18: =IF(B18="","",'WS Import'!E28) -> 380 | G18: 22 | H18: =IF(B18="","",IFERROR(INDEX('Unit Cost'!$N$6:$N$21,MATCH(B18,'Unit Cost'!$B$6:$B$21,0)),0)) -> 0 | I18: =IF(B18="","",F18*IF(H18>0,H18,G18)) -> 8360 | J18: =IF(B18="","",IF(B18="500-7001",1,MarkupFactor)) -> 1.4163822 | K18: =IF(B18="","",IF(B18="500-7001",Mobilization!C11,IF(F18=0,0,IF(H18>0,H18,G18)*J18))) -> 31.160409 | M18: =IF(B18="","",IF(L18="",K18,L18)) -> 31.160409 | N18: =IF(B18="","",F18*M18) -> 11840.956 | O18: =IF(OR(B18="",$N$156=""),"",N18/$N$156) -> 0.0046048857 | P18: 12 | Q18: 26 | R18: 50 | S18: =IF(OR(B18="",F18=""),"",IF(M18=0,"ZERO PRICE",IF(AND(M18>0,M18<=0.05,Q18>1),"TOKEN PRICE",IF(AND(Q18>0,M18<P18*0.5),"UNDER BAND",IF(AND(R18>0,M18>R18*1.5),"OVER BAND",IF(AND(B18="500-7001",$N$156>0,N18/$N$156>0.1),"MOB > 10%","OK")))))) -> OK
A19: =IF('WS Import'!H29="","",ROW()-5) -> 14 | B19: =IF('WS Import'!H29="","",'WS Import'!H29) -> 247-7194 | C19: =IF('WS Import'!H29="","",'WS Import'!C29) -> Flex base (compl in place)(ty A gr 4) | D19: =IF(B19="","",IF('WS Import'!F29<>"",'WS Import'!F29,IF(LEFT(B19,3)="500","Mobilization",IF(OR(LEFT(B19,3)="502",LEFT(B19,3)="503",LEFT(B19,3)="505",LEFT(B19,3)="512"),"Traffic control",IF(LEFT(B19,3)="506","SW3P",IF(OR(LEFT(B19,3)="100",LEFT(B19,3)="104",LEFT(B19,3)="105",LEFT(B19,3)="110",LEFT(B19,3)="132"),"Earthwork",IF(LEFT(B19,3)="247","Base",IF(OR(LEFT(B19,3)="310",LEFT(B19,3)="316",LEFT(B19,3)="340",LEFT(B19,3)="341",LEFT(B19,3)="344",LEFT(B19,3)="354",LEFT(B19,4)="3076",LEFT(B19,4)="3077",LEFT(B19,4)="3080"),"Paving",IF(OR(LEFT(B19,3)="400",LEFT(B19,3)="416",LEFT(B19,3)="420",LEFT(B19,3)="422",LEFT(B19,3)="432",LEFT(B19,3)="450",LEFT(B19,3)="462",LEFT(B19,3)="464",LEFT(B19,3)="465",LEFT(B19,3)="466",LEFT(B19,3)="467",LEFT(B19,3)="496"),"Drainage",IF(OR(LEFT(B19,3)="164",LEFT(B19,3)="168",LEFT(B19,3)="169",LEFT(B19,3)="529",LEFT(B19,3)="530",LEFT(B19,3)="531"),"Roadside",IF(OR(LEFT(B19,3)="540",LEFT(B19,3)="542",LEFT(B19,3)="544",LEFT(B19,3)="545"),"Safety",IF(OR(LEFT(B19,3)="644",LEFT(B19,3)="636",LEFT(B19,3)="658"),"Signing",IF(OR(LEFT(B19,3)="666",LEFT(B19,3)="668",LEFT(B19,3)="672",LEFT(B19,3)="677",LEFT(B19,3)="678"),"Markings","Other"))))))))))))) -> Base | E19: =IF(B19="","",'WS Import'!D29) -> CY | F19: =IF(B19="","",'WS Import'!E29) -> 3400 | G19: 0 | H19: =IF(B19="","",IFERROR(INDEX('Unit Cost'!$N$6:$N$21,MATCH(B19,'Unit Cost'!$B$6:$B$21,0)),0)) -> 36.653333 | I19: =IF(B19="","",F19*IF(H19>0,H19,G19)) -> 124621.33 | J19: =IF(B19="","",IF(B19="500-7001",1,MarkupFactor)) -> 1.4163822 | K19: =IF(B19="","",IF(B19="500-7001",Mobilization!C11,IF(F19=0,0,IF(H19>0,H19,G19)*J19))) -> 51.915131 | M19: =IF(B19="","",IF(L19="",K19,L19)) -> 51.915131 | N19: =IF(B19="","",F19*M19) -> 176511.44 | O19: =IF(OR(B19="",$N$156=""),"",N19/$N$156) -> 0.068644377 | P19: 32 | Q19: 45 | R19: 62 | S19: =IF(OR(B19="",F19=""),"",IF(M19=0,"ZERO PRICE",IF(AND(M19>0,M19<=0.05,Q19>1),"TOKEN PRICE",IF(AND(Q19>0,M19<P19*0.5),"UNDER BAND",IF(AND(R19>0,M19>R19*1.5),"OVER BAND",IF(AND(B19="500-7001",$N$156>0,N19/$N$156>0.1),"MOB > 10%","OK")))))) -> OK
A20: =IF('WS Import'!H30="","",ROW()-5) -> 15 | B20: =IF('WS Import'!H30="","",'WS Import'!H30) -> 310-7004 | C20: =IF('WS Import'!H30="","",'WS Import'!C30) -> Prime coat | D20: =IF(B20="","",IF('WS Import'!F30<>"",'WS Import'!F30,IF(LEFT(B20,3)="500","Mobilization",IF(OR(LEFT(B20,3)="502",LEFT(B20,3)="503",LEFT(B20,3)="505",LEFT(B20,3)="512"),"Traffic control",IF(LEFT(B20,3)="506","SW3P",IF(OR(LEFT(B20,3)="100",LEFT(B20,3)="104",LEFT(B20,3)="105",LEFT(B20,3)="110",LEFT(B20,3)="132"),"Earthwork",IF(LEFT(B20,3)="247","Base",IF(OR(LEFT(B20,3)="310",LEFT(B20,3)="316",LEFT(B20,3)="340",LEFT(B20,3)="341",LEFT(B20,3)="344",LEFT(B20,3)="354",LEFT(B20,4)="3076",LEFT(B20,4)="3077",LEFT(B20,4)="3080"),"Paving",IF(OR(LEFT(B20,3)="400",LEFT(B20,3)="416",LEFT(B20,3)="420",LEFT(B20,3)="422",LEFT(B20,3)="432",LEFT(B20,3)="450",LEFT(B20,3)="462",LEFT(B20,3)="464",LEFT(B20,3)="465",LEFT(B20,3)="466",LEFT(B20,3)="467",LEFT(B20,3)="496"),"Drainage",IF(OR(LEFT(B20,3)="164",LEFT(B20,3)="168",LEFT(B20,3)="169",LEFT(B20,3)="529",LEFT(B20,3)="530",LEFT(B20,3)="531"),"Roadside",IF(OR(LEFT(B20,3)="540",LEFT(B20,3)="542",LEFT(B20,3)="544",LEFT(B20,3)="545"),"Safety",IF(OR(LEFT(B20,3)="644",LEFT(B20,3)="636",LEFT(B20,3)="658"),"Signing",IF(OR(LEFT(B20,3)="666",LEFT(B20,3)="668",LEFT(B20,3)="672",LEFT(B20,3)="677",LEFT(B20,3)="678"),"Markings","Other"))))))))))))) -> Paving | E20: =IF(B20="","",'WS Import'!D30) -> GAL | F20: =IF(B20="","",'WS Import'!E30) -> 14000 | G20: 0 | H20: =IF(B20="","",IFERROR(INDEX('Unit Cost'!$N$6:$N$21,MATCH(B20,'Unit Cost'!$B$6:$B$21,0)),0)) -> 3.0386667 | I20: =IF(B20="","",F20*IF(H20>0,H20,G20)) -> 42541.333 | J20: =IF(B20="","",IF(B20="500-7001",1,MarkupFactor)) -> 1.4163822 | K20: =IF(B20="","",IF(B20="500-7001",Mobilization!C11,IF(F20=0,0,IF(H20>0,H20,G20)*J20))) -> 4.3039135 | M20: =IF(B20="","",IF(L20="",K20,L20)) -> 4.3039135 | N20: =IF(B20="","",F20*M20) -> 60254.789 | O20: =IF(OR(B20="",$N$156=""),"",N20/$N$156) -> 0.023432772 | P20: 3 | Q20: 4.5 | R20: 6.5 | S20: =IF(OR(B20="",F20=""),"",IF(M20=0,"ZERO PRICE",IF(AND(M20>0,M20<=0.05,Q20>1),"TOKEN PRICE",IF(AND(Q20>0,M20<P20*0.5),"UNDER BAND",IF(AND(R20>0,M20>R20*1.5),"OVER BAND",IF(AND(B20="500-7001",$N$156>0,N20/$N$156>0.1),"MOB > 10%","OK")))))) -> OK
A21: =IF('WS Import'!H31="","",ROW()-5) -> 16 | B21: =IF('WS Import'!H31="","",'WS Import'!H31) -> 354-7051 | C21: =IF('WS Import'!H31="","",'WS Import'!C31) -> Plane asph conc pav (2 in) | D21: =IF(B21="","",IF('WS Import'!F31<>"",'WS Import'!F31,IF(LEFT(B21,3)="500","Mobilization",IF(OR(LEFT(B21,3)="502",LEFT(B21,3)="503",LEFT(B21,3)="505",LEFT(B21,3)="512"),"Traffic control",IF(LEFT(B21,3)="506","SW3P",IF(OR(LEFT(B21,3)="100",LEFT(B21,3)="104",LEFT(B21,3)="105",LEFT(B21,3)="110",LEFT(B21,3)="132"),"Earthwork",IF(LEFT(B21,3)="247","Base",IF(OR(LEFT(B21,3)="310",LEFT(B21,3)="316",LEFT(B21,3)="340",LEFT(B21,3)="341",LEFT(B21,3)="344",LEFT(B21,3)="354",LEFT(B21,4)="3076",LEFT(B21,4)="3077",LEFT(B21,4)="3080"),"Paving",IF(OR(LEFT(B21,3)="400",LEFT(B21,3)="416",LEFT(B21,3)="420",LEFT(B21,3)="422",LEFT(B21,3)="432",LEFT(B21,3)="450",LEFT(B21,3)="462",LEFT(B21,3)="464",LEFT(B21,3)="465",LEFT(B21,3)="466",LEFT(B21,3)="467",LEFT(B21,3)="496"),"Drainage",IF(OR(LEFT(B21,3)="164",LEFT(B21,3)="168",LEFT(B21,3)="169",LEFT(B21,3)="529",LEFT(B21,3)="530",LEFT(B21,3)="531"),"Roadside",IF(OR(LEFT(B21,3)="540",LEFT(B21,3)="542",LEFT(B21,3)="544",LEFT(B21,3)="545"),"Safety",IF(OR(LEFT(B21,3)="644",LEFT(B21,3)="636",LEFT(B21,3)="658"),"Signing",IF(OR(LEFT(B21,3)="666",LEFT(B21,3)="668",LEFT(B21,3)="672",LEFT(B21,3)="677",LEFT(B21,3)="678"),"Markings","Other"))))))))))))) -> Paving | E21: =IF(B21="","",'WS Import'!D31) -> SY | F21: =IF(B21="","",'WS Import'!E31) -> 64000 | G21: 0 | H21: =IF(B21="","",IFERROR(INDEX('Unit Cost'!$N$6:$N$21,MATCH(B21,'Unit Cost'!$B$6:$B$21,0)),0)) -> 0.74444444 | I21: =IF(B21="","",F21*IF(H21>0,H21,G21)) -> 47644.444 | J21: =IF(B21="","",IF(B21="500-7001",1,MarkupFactor)) -> 1.4163822 | K21: =IF(B21="","",IF(B21="500-7001",Mobilization!C11,IF(F21=0,0,IF(H21>0,H21,G21)*J21))) -> 1.0544179 | M21: =IF(B21="","",IF(L21="",K21,L21)) -> 1.0544179 | N21: =IF(B21="","",F21*M21) -> 67482.745 | O21: =IF(OR(B21="",$N$156=""),"",N21/$N$156) -> 0.026243687 | P21: 1.4 | Q21: 2.4 | R21: 3.8 | S21: =IF(OR(B21="",F21=""),"",IF(M21=0,"ZERO PRICE",IF(AND(M21>0,M21<=0.05,Q21>1),"TOKEN PRICE",IF(AND(Q21>0,M21<P21*0.5),"UNDER BAND",IF(AND(R21>0,M21>R21*1.5),"OVER BAND",IF(AND(B21="500-7001",$N$156>0,N21/$N$156>0.1),"MOB > 10%","OK")))))) -> OK
A22: =IF('WS Import'!H32="","",ROW()-5) -> 17 | B22: =IF('WS Import'!H32="","",'WS Import'!H32) -> 3076-7008 | C22: =IF('WS Import'!H32="","",'WS Import'!C32) -> D-GR HMA ty B PG64-22 | D22: =IF(B22="","",IF('WS Import'!F32<>"",'WS Import'!F32,IF(LEFT(B22,3)="500","Mobilization",IF(OR(LEFT(B22,3)="502",LEFT(B22,3)="503",LEFT(B22,3)="505",LEFT(B22,3)="512"),"Traffic control",IF(LEFT(B22,3)="506","SW3P",IF(OR(LEFT(B22,3)="100",LEFT(B22,3)="104",LEFT(B22,3)="105",LEFT(B22,3)="110",LEFT(B22,3)="132"),"Earthwork",IF(LEFT(B22,3)="247","Base",IF(OR(LEFT(B22,3)="310",LEFT(B22,3)="316",LEFT(B22,3)="340",LEFT(B22,3)="341",LEFT(B22,3)="344",LEFT(B22,3)="354",LEFT(B22,4)="3076",LEFT(B22,4)="3077",LEFT(B22,4)="3080"),"Paving",IF(OR(LEFT(B22,3)="400",LEFT(B22,3)="416",LEFT(B22,3)="420",LEFT(B22,3)="422",LEFT(B22,3)="432",LEFT(B22,3)="450",LEFT(B22,3)="462",LEFT(B22,3)="464",LEFT(B22,3)="465",LEFT(B22,3)="466",LEFT(B22,3)="467",LEFT(B22,3)="496"),"Drainage",IF(OR(LEFT(B22,3)="164",LEFT(B22,3)="168",LEFT(B22,3)="169",LEFT(B22,3)="529",LEFT(B22,3)="530",LEFT(B22,3)="531"),"Roadside",IF(OR(LEFT(B22,3)="540",LEFT(B22,3)="542",LEFT(B22,3)="544",LEFT(B22,3)="545"),"Safety",IF(OR(LEFT(B22,3)="644",LEFT(B22,3)="636",LEFT(B22,3)="658"),"Signing",IF(OR(LEFT(B22,3)="666",LEFT(B22,3)="668",LEFT(B22,3)="672",LEFT(B22,3)="677",LEFT(B22,3)="678"),"Markings","Other"))))))))))))) -> Paving | E22: =IF(B22="","",'WS Import'!D32) -> TON | F22: =IF(B22="","",'WS Import'!E32) -> 2600 | G22: 0 | H22: =IF(B22="","",IFERROR(INDEX('Unit Cost'!$N$6:$N$21,MATCH(B22,'Unit Cost'!$B$6:$B$21,0)),0)) -> 76.986667 | I22: =IF(B22="","",F22*IF(H22>0,H22,G22)) -> 200165.33 | J22: =IF(B22="","",IF(B22="500-7001",1,MarkupFactor)) -> 1.4163822 | K22: =IF(B22="","",IF(B22="500-7001",Mobilization!C11,IF(F22=0,0,IF(H22>0,H22,G22)*J22))) -> 109.04255 | M22: =IF(B22="","",IF(L22="",K22,L22)) -> 109.04255 | N22: =IF(B22="","",F22*M22) -> 283510.62 | O22: =IF(OR(B22="",$N$156=""),"",N22/$N$156) -> 0.1102558 | P22: 85 | Q22: 105 | R22: 130 | S22: =IF(OR(B22="",F22=""),"",IF(M22=0,"ZERO PRICE",IF(AND(M22>0,M22<=0.05,Q22>1),"TOKEN PRICE",IF(AND(Q22>0,M22<P22*0.5),"UNDER BAND",IF(AND(R22>0,M22>R22*1.5),"OVER BAND",IF(AND(B22="500-7001",$N$156>0,N22/$N$156>0.1),"MOB > 10%","OK")))))) -> OK
A23: =IF('WS Import'!H33="","",ROW()-5) -> 18 | B23: =IF('WS Import'!H33="","",'WS Import'!H33) -> 3076-7022 | C23: =IF('WS Import'!H33="","",'WS Import'!C33) -> D-GR HMA ty D SAC-B PG70-22 | D23: =IF(B23="","",IF('WS Import'!F33<>"",'WS Import'!F33,IF(LEFT(B23,3)="500","Mobilization",IF(OR(LEFT(B23,3)="502",LEFT(B23,3)="503",LEFT(B23,3)="505",LEFT(B23,3)="512"),"Traffic control",IF(LEFT(B23,3)="506","SW3P",IF(OR(LEFT(B23,3)="100",LEFT(B23,3)="104",LEFT(B23,3)="105",LEFT(B23,3)="110",LEFT(B23,3)="132"),"Earthwork",IF(LEFT(B23,3)="247","Base",IF(OR(LEFT(B23,3)="310",LEFT(B23,3)="316",LEFT(B23,3)="340",LEFT(B23,3)="341",LEFT(B23,3)="344",LEFT(B23,3)="354",LEFT(B23,4)="3076",LEFT(B23,4)="3077",LEFT(B23,4)="3080"),"Paving",IF(OR(LEFT(B23,3)="400",LEFT(B23,3)="416",LEFT(B23,3)="420",LEFT(B23,3)="422",LEFT(B23,3)="432",LEFT(B23,3)="450",LEFT(B23,3)="462",LEFT(B23,3)="464",LEFT(B23,3)="465",LEFT(B23,3)="466",LEFT(B23,3)="467",LEFT(B23,3)="496"),"Drainage",IF(OR(LEFT(B23,3)="164",LEFT(B23,3)="168",LEFT(B23,3)="169",LEFT(B23,3)="529",LEFT(B23,3)="530",LEFT(B23,3)="531"),"Roadside",IF(OR(LEFT(B23,3)="540",LEFT(B23,3)="542",LEFT(B23,3)="544",LEFT(B23,3)="545"),"Safety",IF(OR(LEFT(B23,3)="644",LEFT(B23,3)="636",LEFT(B23,3)="658"),"Signing",IF(OR(LEFT(B23,3)="666",LEFT(B23,3)="668",LEFT(B23,3)="672",LEFT(B23,3)="677",LEFT(B23,3)="678"),"Markings","Other"))))))))))))) -> Paving | E23: =IF(B23="","",'WS Import'!D33) -> TON | F23: =IF(B23="","",'WS Import'!E33) -> 7400 | G23: 0 | H23: =IF(B23="","",IFERROR(INDEX('Unit Cost'!$N$6:$N$21,MATCH(B23,'Unit Cost'!$B$6:$B$21,0)),0)) -> 88.262857 | I23: =IF(B23="","",F23*IF(H23>0,H23,G23)) -> 653145.14 | J23: =IF(B23="","",IF(B23="500-7001",1,MarkupFactor)) -> 1.4163822 | K23: =IF(B23="","",IF(B23="500-7001",Mobilization!C11,IF(F23=0,0,IF(H23>0,H23,G23)*J23))) -> 125.01394 | M23: =IF(B23="","",IF(L23="",K23,L23)) -> 125.01394 | N23: =IF(B23="","",F23*M23) -> 925103.18 | O23: =IF(OR(B23="",$N$156=""),"",N23/$N$156) -> 0.35976779 | P23: 95 | Q23: 118 | R23: 145 | S23: =IF(OR(B23="",F23=""),"",IF(M23=0,"ZERO PRICE",IF(AND(M23>0,M23<=0.05,Q23>1),"TOKEN PRICE",IF(AND(Q23>0,M23<P23*0.5),"UNDER BAND",IF(AND(R23>0,M23>R23*1.5),"OVER BAND",IF(AND(B23="500-7001",$N$156>0,N23/$N$156>0.1),"MOB > 10%","OK")))))) -> OK
A24: =IF('WS Import'!H34="","",ROW()-5) -> 19 | B24: =IF('WS Import'!H34="","",'WS Import'!H34) -> 432-7001 | C24: =IF('WS Import'!H34="","",'WS Import'!C34) -> Riprap (conc)(4 in) | D24: =IF(B24="","",IF('WS Import'!F34<>"",'WS Import'!F34,IF(LEFT(B24,3)="500","Mobilization",IF(OR(LEFT(B24,3)="502",LEFT(B24,3)="503",LEFT(B24,3)="505",LEFT(B24,3)="512"),"Traffic control",IF(LEFT(B24,3)="506","SW3P",IF(OR(LEFT(B24,3)="100",LEFT(B24,3)="104",LEFT(B24,3)="105",LEFT(B24,3)="110",LEFT(B24,3)="132"),"Earthwork",IF(LEFT(B24,3)="247","Base",IF(OR(LEFT(B24,3)="310",LEFT(B24,3)="316",LEFT(B24,3)="340",LEFT(B24,3)="341",LEFT(B24,3)="344",LEFT(B24,3)="354",LEFT(B24,4)="3076",LEFT(B24,4)="3077",LEFT(B24,4)="3080"),"Paving",IF(OR(LEFT(B24,3)="400",LEFT(B24,3)="416",LEFT(B24,3)="420",LEFT(B24,3)="422",LEFT(B24,3)="432",LEFT(B24,3)="450",LEFT(B24,3)="462",LEFT(B24,3)="464",LEFT(B24,3)="465",LEFT(B24,3)="466",LEFT(B24,3)="467",LEFT(B24,3)="496"),"Drainage",IF(OR(LEFT(B24,3)="164",LEFT(B24,3)="168",LEFT(B24,3)="169",LEFT(B24,3)="529",LEFT(B24,3)="530",LEFT(B24,3)="531"),"Roadside",IF(OR(LEFT(B24,3)="540",LEFT(B24,3)="542",LEFT(B24,3)="544",LEFT(B24,3)="545"),"Safety",IF(OR(LEFT(B24,3)="644",LEFT(B24,3)="636",LEFT(B24,3)="658"),"Signing",IF(OR(LEFT(B24,3)="666",LEFT(B24,3)="668",LEFT(B24,3)="672",LEFT(B24,3)="677",LEFT(B24,3)="678"),"Markings","Other"))))))))))))) -> Drainage | E24: =IF(B24="","",'WS Import'!D34) -> CY | F24: =IF(B24="","",'WS Import'!E34) -> 160 | G24: 145 | H24: =IF(B24="","",IFERROR(INDEX('Unit Cost'!$N$6:$N$21,MATCH(B24,'Unit Cost'!$B$6:$B$21,0)),0)) -> 0 | I24: =IF(B24="","",F24*IF(H24>0,H24,G24)) -> 23200 | J24: =IF(B24="","",IF(B24="500-7001",1,MarkupFactor)) -> 1.4163822 | K24: =IF(B24="","",IF(B24="500-7001",Mobilization!C11,IF(F24=0,0,IF(H24>0,H24,G24)*J24))) -> 205.37543 | M24: =IF(B24="","",IF(L24="",K24,L24)) -> 205.37543 | N24: =IF(B24="","",F24*M24) -> 32860.068 | O24: =IF(OR(B24="",$N$156=""),"",N24/$N$156) -> 0.012779109 | P24: 110 | Q24: 165 | R24: 220 | S24: =IF(OR(B24="",F24=""),"",IF(M24=0,"ZERO PRICE",IF(AND(M24>0,M24<=0.05,Q24>1),"TOKEN PRICE",IF(AND(Q24>0,M24<P24*0.5),"UNDER BAND",IF(AND(R24>0,M24>R24*1.5),"OVER BAND",IF(AND(B24="500-7001",$N$156>0,N24/$N$156>0.1),"MOB > 10%","OK")))))) -> OK
A25: =IF('WS Import'!H35="","",ROW()-5) -> 20 | B25: =IF('WS Import'!H35="","",'WS Import'!H35) -> 464-7005 | C25: =IF('WS Import'!H35="","",'WS Import'!C35) -> RC pipe (cl III)(24 in) | D25: =IF(B25="","",IF('WS Import'!F35<>"",'WS Import'!F35,IF(LEFT(B25,3)="500","Mobilization",IF(OR(LEFT(B25,3)="502",LEFT(B25,3)="503",LEFT(B25,3)="505",LEFT(B25,3)="512"),"Traffic control",IF(LEFT(B25,3)="506","SW3P",IF(OR(LEFT(B25,3)="100",LEFT(B25,3)="104",LEFT(B25,3)="105",LEFT(B25,3)="110",LEFT(B25,3)="132"),"Earthwork",IF(LEFT(B25,3)="247","Base",IF(OR(LEFT(B25,3)="310",LEFT(B25,3)="316",LEFT(B25,3)="340",LEFT(B25,3)="341",LEFT(B25,3)="344",LEFT(B25,3)="354",LEFT(B25,4)="3076",LEFT(B25,4)="3077",LEFT(B25,4)="3080"),"Paving",IF(OR(LEFT(B25,3)="400",LEFT(B25,3)="416",LEFT(B25,3)="420",LEFT(B25,3)="422",LEFT(B25,3)="432",LEFT(B25,3)="450",LEFT(B25,3)="462",LEFT(B25,3)="464",LEFT(B25,3)="465",LEFT(B25,3)="466",LEFT(B25,3)="467",LEFT(B25,3)="496"),"Drainage",IF(OR(LEFT(B25,3)="164",LEFT(B25,3)="168",LEFT(B25,3)="169",LEFT(B25,3)="529",LEFT(B25,3)="530",LEFT(B25,3)="531"),"Roadside",IF(OR(LEFT(B25,3)="540",LEFT(B25,3)="542",LEFT(B25,3)="544",LEFT(B25,3)="545"),"Safety",IF(OR(LEFT(B25,3)="644",LEFT(B25,3)="636",LEFT(B25,3)="658"),"Signing",IF(OR(LEFT(B25,3)="666",LEFT(B25,3)="668",LEFT(B25,3)="672",LEFT(B25,3)="677",LEFT(B25,3)="678"),"Markings","Other"))))))))))))) -> Drainage | E25: =IF(B25="","",'WS Import'!D35) -> LF | F25: =IF(B25="","",'WS Import'!E35) -> 720 | G25: 0 | H25: =IF(B25="","",IFERROR(INDEX('Unit Cost'!$N$6:$N$21,MATCH(B25,'Unit Cost'!$B$6:$B$21,0)),0)) -> 96.29 | I25: =IF(B25="","",F25*IF(H25>0,H25,G25)) -> 69328.8 | J25: =IF(B25="","",IF(B25="500-7001",1,MarkupFactor)) -> 1.4163822 | K25: =IF(B25="","",IF(B25="500-7001",Mobilization!C11,IF(F25=0,0,IF(H25>0,H25,G25)*J25))) -> 136.38345 | M25: =IF(B25="","",IF(L25="",K25,L25)) -> 136.38345 | N25: =IF(B25="","",F25*M25) -> 98196.081 | O25: =IF(OR(B25="",$N$156=""),"",N25/$N$156) -> 0.038187943 | P25: 95 | Q25: 125 | R25: 155 | S25: =IF(OR(B25="",F25=""),"",IF(M25=0,"ZERO PRICE",IF(AND(M25>0,M25<=0.05,Q25>1),"TOKEN PRICE",IF(AND(Q25>0,M25<P25*0.5),"UNDER BAND",IF(AND(R25>0,M25>R25*1.5),"OVER BAND",IF(AND(B25="500-7001",$N$156>0,N25/$N$156>0.1),"MOB > 10%","OK")))))) -> OK
A26: =IF('WS Import'!H36="","",ROW()-5) -> 21 | B26: =IF('WS Import'!H36="","",'WS Import'!H36) -> 465-7127 | C26: =IF('WS Import'!H36="","",'WS Import'!C36) -> Inlet (compl)(ty C) | D26: =IF(B26="","",IF('WS Import'!F36<>"",'WS Import'!F36,IF(LEFT(B26,3)="500","Mobilization",IF(OR(LEFT(B26,3)="502",LEFT(B26,3)="503",LEFT(B26,3)="505",LEFT(B26,3)="512"),"Traffic control",IF(LEFT(B26,3)="506","SW3P",IF(OR(LEFT(B26,3)="100",LEFT(B26,3)="104",LEFT(B26,3)="105",LEFT(B26,3)="110",LEFT(B26,3)="132"),"Earthwork",IF(LEFT(B26,3)="247","Base",IF(OR(LEFT(B26,3)="310",LEFT(B26,3)="316",LEFT(B26,3)="340",LEFT(B26,3)="341",LEFT(B26,3)="344",LEFT(B26,3)="354",LEFT(B26,4)="3076",LEFT(B26,4)="3077",LEFT(B26,4)="3080"),"Paving",IF(OR(LEFT(B26,3)="400",LEFT(B26,3)="416",LEFT(B26,3)="420",LEFT(B26,3)="422",LEFT(B26,3)="432",LEFT(B26,3)="450",LEFT(B26,3)="462",LEFT(B26,3)="464",LEFT(B26,3)="465",LEFT(B26,3)="466",LEFT(B26,3)="467",LEFT(B26,3)="496"),"Drainage",IF(OR(LEFT(B26,3)="164",LEFT(B26,3)="168",LEFT(B26,3)="169",LEFT(B26,3)="529",LEFT(B26,3)="530",LEFT(B26,3)="531"),"Roadside",IF(OR(LEFT(B26,3)="540",LEFT(B26,3)="542",LEFT(B26,3)="544",LEFT(B26,3)="545"),"Safety",IF(OR(LEFT(B26,3)="644",LEFT(B26,3)="636",LEFT(B26,3)="658"),"Signing",IF(OR(LEFT(B26,3)="666",LEFT(B26,3)="668",LEFT(B26,3)="672",LEFT(B26,3)="677",LEFT(B26,3)="678"),"Markings","Other"))))))))))))) -> Drainage | E26: =IF(B26="","",'WS Import'!D36) -> EA | F26: =IF(B26="","",'WS Import'!E36) -> 6 | G26: 4200 | H26: =IF(B26="","",IFERROR(INDEX('Unit Cost'!$N$6:$N$21,MATCH(B26,'Unit Cost'!$B$6:$B$21,0)),0)) -> 0 | I26: =IF(B26="","",F26*IF(H26>0,H26,G26)) -> 25200 | J26: =IF(B26="","",IF(B26="500-7001",1,MarkupFactor)) -> 1.4163822 | K26: =IF(B26="","",IF(B26="500-7001",Mobilization!C11,IF(F26=0,0,IF(H26>0,H26,G26)*J26))) -> 5948.8054 | M26: =IF(B26="","",IF(L26="",K26,L26)) -> 5948.8054 | N26: =IF(B26="","",F26*M26) -> 35692.833 | O26: =IF(OR(B26="",$N$156=""),"",N26/$N$156) -> 0.013880756 | P26: 3200 | Q26: 4800 | R26: 6500 | S26: =IF(OR(B26="",F26=""),"",IF(M26=0,"ZERO PRICE",IF(AND(M26>0,M26<=0.05,Q26>1),"TOKEN PRICE",IF(AND(Q26>0,M26<P26*0.5),"UNDER BAND",IF(AND(R26>0,M26>R26*1.5),"OVER BAND",IF(AND(B26="500-7001",$N$156>0,N26/$N$156>0.1),"MOB > 10%","OK")))))) -> OK
A27: =IF('WS Import'!H37="","",ROW()-5) -> 22 | B27: =IF('WS Import'!H37="","",'WS Import'!H37) -> 467-7308 | C27: =IF('WS Import'!H37="","",'WS Import'!C37) -> SET (ty II)(24 in)(RCP)(6:1)(P) | D27: =IF(B27="","",IF('WS Import'!F37<>"",'WS Import'!F37,IF(LEFT(B27,3)="500","Mobilization",IF(OR(LEFT(B27,3)="502",LEFT(B27,3)="503",LEFT(B27,3)="505",LEFT(B27,3)="512"),"Traffic control",IF(LEFT(B27,3)="506","SW3P",IF(OR(LEFT(B27,3)="100",LEFT(B27,3)="104",LEFT(B27,3)="105",LEFT(B27,3)="110",LEFT(B27,3)="132"),"Earthwork",IF(LEFT(B27,3)="247","Base",IF(OR(LEFT(B27,3)="310",LEFT(B27,3)="316",LEFT(B27,3)="340",LEFT(B27,3)="341",LEFT(B27,3)="344",LEFT(B27,3)="354",LEFT(B27,4)="3076",LEFT(B27,4)="3077",LEFT(B27,4)="3080"),"Paving",IF(OR(LEFT(B27,3)="400",LEFT(B27,3)="416",LEFT(B27,3)="420",LEFT(B27,3)="422",LEFT(B27,3)="432",LEFT(B27,3)="450",LEFT(B27,3)="462",LEFT(B27,3)="464",LEFT(B27,3)="465",LEFT(B27,3)="466",LEFT(B27,3)="467",LEFT(B27,3)="496"),"Drainage",IF(OR(LEFT(B27,3)="164",LEFT(B27,3)="168",LEFT(B27,3)="169",LEFT(B27,3)="529",LEFT(B27,3)="530",LEFT(B27,3)="531"),"Roadside",IF(OR(LEFT(B27,3)="540",LEFT(B27,3)="542",LEFT(B27,3)="544",LEFT(B27,3)="545"),"Safety",IF(OR(LEFT(B27,3)="644",LEFT(B27,3)="636",LEFT(B27,3)="658"),"Signing",IF(OR(LEFT(B27,3)="666",LEFT(B27,3)="668",LEFT(B27,3)="672",LEFT(B27,3)="677",LEFT(B27,3)="678"),"Markings","Other"))))))))))))) -> Drainage | E27: =IF(B27="","",'WS Import'!D37) -> EA | F27: =IF(B27="","",'WS Import'!E37) -> 4 | G27: 2100 | H27: =IF(B27="","",IFERROR(INDEX('Unit Cost'!$N$6:$N$21,MATCH(B27,'Unit Cost'!$B$6:$B$21,0)),0)) -> 0 | I27: =IF(B27="","",F27*IF(H27>0,H27,G27)) -> 8400 | J27: =IF(B27="","",IF(B27="500-7001",1,MarkupFactor)) -> 1.4163822 | K27: =IF(B27="","",IF(B27="500-7001",Mobilization!C11,IF(F27=0,0,IF(H27>0,H27,G27)*J27))) -> 2974.4027 | M27: =IF(B27="","",IF(L27="",K27,L27)) -> 2974.4027 | N27: =IF(B27="","",F27*M27) -> 11897.611 | O27: =IF(OR(B27="",$N$156=""),"",N27/$N$156) -> 0.0046269186 | P27: 1400 | Q27: 2400 | R27: 3600 | S27: =IF(OR(B27="",F27=""),"",IF(M27=0,"ZERO PRICE",IF(AND(M27>0,M27<=0.05,Q27>1),"TOKEN PRICE",IF(AND(Q27>0,M27<P27*0.5),"UNDER BAND",IF(AND(R27>0,M27>R27*1.5),"OVER BAND",IF(AND(B27="500-7001",$N$156>0,N27/$N$156>0.1),"MOB > 10%","OK")))))) -> OK
A28: =IF('WS Import'!H38="","",ROW()-5) -> 23 | B28: =IF('WS Import'!H38="","",'WS Import'!H38) -> 529-7009 | C28: =IF('WS Import'!H38="","",'WS Import'!C38) -> Curb and gutter (ty II) | D28: =IF(B28="","",IF('WS Import'!F38<>"",'WS Import'!F38,IF(LEFT(B28,3)="500","Mobilization",IF(OR(LEFT(B28,3)="502",LEFT(B28,3)="503",LEFT(B28,3)="505",LEFT(B28,3)="512"),"Traffic control",IF(LEFT(B28,3)="506","SW3P",IF(OR(LEFT(B28,3)="100",LEFT(B28,3)="104",LEFT(B28,3)="105",LEFT(B28,3)="110",LEFT(B28,3)="132"),"Earthwork",IF(LEFT(B28,3)="247","Base",IF(OR(LEFT(B28,3)="310",LEFT(B28,3)="316",LEFT(B28,3)="340",LEFT(B28,3)="341",LEFT(B28,3)="344",LEFT(B28,3)="354",LEFT(B28,4)="3076",LEFT(B28,4)="3077",LEFT(B28,4)="3080"),"Paving",IF(OR(LEFT(B28,3)="400",LEFT(B28,3)="416",LEFT(B28,3)="420",LEFT(B28,3)="422",LEFT(B28,3)="432",LEFT(B28,3)="450",LEFT(B28,3)="462",LEFT(B28,3)="464",LEFT(B28,3)="465",LEFT(B28,3)="466",LEFT(B28,3)="467",LEFT(B28,3)="496"),"Drainage",IF(OR(LEFT(B28,3)="164",LEFT(B28,3)="168",LEFT(B28,3)="169",LEFT(B28,3)="529",LEFT(B28,3)="530",LEFT(B28,3)="531"),"Roadside",IF(OR(LEFT(B28,3)="540",LEFT(B28,3)="542",LEFT(B28,3)="544",LEFT(B28,3)="545"),"Safety",IF(OR(LEFT(B28,3)="644",LEFT(B28,3)="636",LEFT(B28,3)="658"),"Signing",IF(OR(LEFT(B28,3)="666",LEFT(B28,3)="668",LEFT(B28,3)="672",LEFT(B28,3)="677",LEFT(B28,3)="678"),"Markings","Other"))))))))))))) -> Roadside | E28: =IF(B28="","",'WS Import'!D38) -> LF | F28: =IF(B28="","",'WS Import'!E38) -> 3200 | G28: 0 | H28: =IF(B28="","",IFERROR(INDEX('Unit Cost'!$N$6:$N$21,MATCH(B28,'Unit Cost'!$B$6:$B$21,0)),0)) -> 23.796429 | I28: =IF(B28="","",F28*IF(H28>0,H28,G28)) -> 76148.571 | J28: =IF(B28="","",IF(B28="500-7001",1,MarkupFactor)) -> 1.4163822 | K28: =IF(B28="","",IF(B28="500-7001",Mobilization!C11,IF(F28=0,0,IF(H28>0,H28,G28)*J28))) -> 33.704839 | M28: =IF(B28="","",IF(L28="",K28,L28)) -> 33.704839 | N28: =IF(B28="","",F28*M28) -> 107855.48 | O28: =IF(OR(B28="",$N$156=""),"",N28/$N$156) -> 0.041944434 | P28: 28 | Q28: 36 | R28: 48 | S28: =IF(OR(B28="",F28=""),"",IF(M28=0,"ZERO PRICE",IF(AND(M28>0,M28<=0.05,Q28>1),"TOKEN PRICE",IF(AND(Q28>0,M28<P28*0.5),"UNDER BAND",IF(AND(R28>0,M28>R28*1.5),"OVER BAND",IF(AND(B28="500-7001",$N$156>0,N28/$N$156>0.1),"MOB > 10%","OK")))))) -> OK
A29: =IF('WS Import'!H39="","",ROW()-5) -> 24 | B29: =IF('WS Import'!H39="","",'WS Import'!H39) -> 531-7001 | C29: =IF('WS Import'!H39="","",'WS Import'!C39) -> Conc sidewalks (4 in) | D29: =IF(B29="","",IF('WS Import'!F39<>"",'WS Import'!F39,IF(LEFT(B29,3)="500","Mobilization",IF(OR(LEFT(B29,3)="502",LEFT(B29,3)="503",LEFT(B29,3)="505",LEFT(B29,3)="512"),"Traffic control",IF(LEFT(B29,3)="506","SW3P",IF(OR(LEFT(B29,3)="100",LEFT(B29,3)="104",LEFT(B29,3)="105",LEFT(B29,3)="110",LEFT(B29,3)="132"),"Earthwork",IF(LEFT(B29,3)="247","Base",IF(OR(LEFT(B29,3)="310",LEFT(B29,3)="316",LEFT(B29,3)="340",LEFT(B29,3)="341",LEFT(B29,3)="344",LEFT(B29,3)="354",LEFT(B29,4)="3076",LEFT(B29,4)="3077",LEFT(B29,4)="3080"),"Paving",IF(OR(LEFT(B29,3)="400",LEFT(B29,3)="416",LEFT(B29,3)="420",LEFT(B29,3)="422",LEFT(B29,3)="432",LEFT(B29,3)="450",LEFT(B29,3)="462",LEFT(B29,3)="464",LEFT(B29,3)="465",LEFT(B29,3)="466",LEFT(B29,3)="467",LEFT(B29,3)="496"),"Drainage",IF(OR(LEFT(B29,3)="164",LEFT(B29,3)="168",LEFT(B29,3)="169",LEFT(B29,3)="529",LEFT(B29,3)="530",LEFT(B29,3)="531"),"Roadside",IF(OR(LEFT(B29,3)="540",LEFT(B29,3)="542",LEFT(B29,3)="544",LEFT(B29,3)="545"),"Safety",IF(OR(LEFT(B29,3)="644",LEFT(B29,3)="636",LEFT(B29,3)="658"),"Signing",IF(OR(LEFT(B29,3)="666",LEFT(B29,3)="668",LEFT(B29,3)="672",LEFT(B29,3)="677",LEFT(B29,3)="678"),"Markings","Other"))))))))))))) -> Roadside | E29: =IF(B29="","",'WS Import'!D39) -> SY | F29: =IF(B29="","",'WS Import'!E39) -> 1100 | G29: 0 | H29: =IF(B29="","",IFERROR(INDEX('Unit Cost'!$N$6:$N$21,MATCH(B29,'Unit Cost'!$B$6:$B$21,0)),0)) -> 53.788889 | I29: =IF(B29="","",F29*IF(H29>0,H29,G29)) -> 59167.778 | J29: =IF(B29="","",IF(B29="500-7001",1,MarkupFactor)) -> 1.4163822 | K29: =IF(B29="","",IF(B29="500-7001",Mobilization!C11,IF(F29=0,0,IF(H29>0,H29,G29)*J29))) -> 76.185627 | M29: =IF(B29="","",IF(L29="",K29,L29)) -> 76.185627 | N29: =IF(B29="","",F29*M29) -> 83804.19 | O29: =IF(OR(B29="",$N$156=""),"",N29/$N$156) -> 0.032591011 | P29: 55 | Q29: 72 | R29: 95 | S29: =IF(OR(B29="",F29=""),"",IF(M29=0,"ZERO PRICE",IF(AND(M29>0,M29<=0.05,Q29>1),"TOKEN PRICE",IF(AND(Q29>0,M29<P29*0.5),"UNDER BAND",IF(AND(R29>0,M29>R29*1.5),"OVER BAND",IF(AND(B29="500-7001",$N$156>0,N29/$N$156>0.1),"MOB > 10%","OK")))))) -> OK
A30: =IF('WS Import'!H40="","",ROW()-5) -> 25 | B30: =IF('WS Import'!H40="","",'WS Import'!H40) -> 540-7001 | C30: =IF('WS Import'!H40="","",'WS Import'!C40) -> MTL W-beam GD fen (tim post) | D30: =IF(B30="","",IF('WS Import'!F40<>"",'WS Import'!F40,IF(LEFT(B30,3)="500","Mobilization",IF(OR(LEFT(B30,3)="502",LEFT(B30,3)="503",LEFT(B30,3)="505",LEFT(B30,3)="512"),"Traffic control",IF(LEFT(B30,3)="506","SW3P",IF(OR(LEFT(B30,3)="100",LEFT(B30,3)="104",LEFT(B30,3)="105",LEFT(B30,3)="110",LEFT(B30,3)="132"),"Earthwork",IF(LEFT(B30,3)="247","Base",IF(OR(LEFT(B30,3)="310",LEFT(B30,3)="316",LEFT(B30,3)="340",LEFT(B30,3)="341",LEFT(B30,3)="344",LEFT(B30,3)="354",LEFT(B30,4)="3076",LEFT(B30,4)="3077",LEFT(B30,4)="3080"),"Paving",IF(OR(LEFT(B30,3)="400",LEFT(B30,3)="416",LEFT(B30,3)="420",LEFT(B30,3)="422",LEFT(B30,3)="432",LEFT(B30,3)="450",LEFT(B30,3)="462",LEFT(B30,3)="464",LEFT(B30,3)="465",LEFT(B30,3)="466",LEFT(B30,3)="467",LEFT(B30,3)="496"),"Drainage",IF(OR(LEFT(B30,3)="164",LEFT(B30,3)="168",LEFT(B30,3)="169",LEFT(B30,3)="529",LEFT(B30,3)="530",LEFT(B30,3)="531"),"Roadside",IF(OR(LEFT(B30,3)="540",LEFT(B30,3)="542",LEFT(B30,3)="544",LEFT(B30,3)="545"),"Safety",IF(OR(LEFT(B30,3)="644",LEFT(B30,3)="636",LEFT(B30,3)="658"),"Signing",IF(OR(LEFT(B30,3)="666",LEFT(B30,3)="668",LEFT(B30,3)="672",LEFT(B30,3)="677",LEFT(B30,3)="678"),"Markings","Other"))))))))))))) -> Safety | E30: =IF(B30="","",'WS Import'!D40) -> LF | F30: =IF(B30="","",'WS Import'!E40) -> 900 | G30: 0 | H30: =IF(B30="","",IFERROR(INDEX('Unit Cost'!$N$6:$N$21,MATCH(B30,'Unit Cost'!$B$6:$B$21,0)),0)) -> 27.96 | I30: =IF(B30="","",F30*IF(H30>0,H30,G30)) -> 25164 | J30: =IF(B30="","",IF(B30="500-7001",1,MarkupFactor)) -> 1.4163822 | K30: =IF(B30="","",IF(B30="500-7001",Mobilization!C11,IF(F30=0,0,IF(H30>0,H30,G30)*J30))) -> 39.602048 | M30: =IF(B30="","",IF(L30="",K30,L30)) -> 39.602048 | N30: =IF(B30="","",F30*M30) -> 35641.843 | O30: =IF(OR(B30="",$N$156=""),"",N30/$N$156) -> 0.013860926 | P30: 28 | Q30: 36 | R30: 48 | S30: =IF(OR(B30="",F30=""),"",IF(M30=0,"ZERO PRICE",IF(AND(M30>0,M30<=0.05,Q30>1),"TOKEN PRICE",IF(AND(Q30>0,M30<P30*0.5),"UNDER BAND",IF(AND(R30>0,M30>R30*1.5),"OVER BAND",IF(AND(B30="500-7001",$N$156>0,N30/$N$156>0.1),"MOB > 10%","OK")))))) -> OK
A31: =IF('WS Import'!H41="","",ROW()-5) -> 26 | B31: =IF('WS Import'!H41="","",'WS Import'!H41) -> 544-7001 | C31: =IF('WS Import'!H41="","",'WS Import'!C41) -> Guardrail end treatment (install) | D31: =IF(B31="","",IF('WS Import'!F41<>"",'WS Import'!F41,IF(LEFT(B31,3)="500","Mobilization",IF(OR(LEFT(B31,3)="502",LEFT(B31,3)="503",LEFT(B31,3)="505",LEFT(B31,3)="512"),"Traffic control",IF(LEFT(B31,3)="506","SW3P",IF(OR(LEFT(B31,3)="100",LEFT(B31,3)="104",LEFT(B31,3)="105",LEFT(B31,3)="110",LEFT(B31,3)="132"),"Earthwork",IF(LEFT(B31,3)="247","Base",IF(OR(LEFT(B31,3)="310",LEFT(B31,3)="316",LEFT(B31,3)="340",LEFT(B31,3)="341",LEFT(B31,3)="344",LEFT(B31,3)="354",LEFT(B31,4)="3076",LEFT(B31,4)="3077",LEFT(B31,4)="3080"),"Paving",IF(OR(LEFT(B31,3)="400",LEFT(B31,3)="416",LEFT(B31,3)="420",LEFT(B31,3)="422",LEFT(B31,3)="432",LEFT(B31,3)="450",LEFT(B31,3)="462",LEFT(B31,3)="464",LEFT(B31,3)="465",LEFT(B31,3)="466",LEFT(B31,3)="467",LEFT(B31,3)="496"),"Drainage",IF(OR(LEFT(B31,3)="164",LEFT(B31,3)="168",LEFT(B31,3)="169",LEFT(B31,3)="529",LEFT(B31,3)="530",LEFT(B31,3)="531"),"Roadside",IF(OR(LEFT(B31,3)="540",LEFT(B31,3)="542",LEFT(B31,3)="544",LEFT(B31,3)="545"),"Safety",IF(OR(LEFT(B31,3)="644",LEFT(B31,3)="636",LEFT(B31,3)="658"),"Signing",IF(OR(LEFT(B31,3)="666",LEFT(B31,3)="668",LEFT(B31,3)="672",LEFT(B31,3)="677",LEFT(B31,3)="678"),"Markings","Other"))))))))))))) -> Safety | E31: =IF(B31="","",'WS Import'!D41) -> EA | F31: =IF(B31="","",'WS Import'!E41) -> 6 | G31: 3100 | H31: =IF(B31="","",IFERROR(INDEX('Unit Cost'!$N$6:$N$21,MATCH(B31,'Unit Cost'!$B$6:$B$21,0)),0)) -> 0 | I31: =IF(B31="","",F31*IF(H31>0,H31,G31)) -> 18600 | J31: =IF(B31="","",IF(B31="500-7001",1,MarkupFactor)) -> 1.4163822 | K31: =IF(B31="","",IF(B31="500-7001",Mobilization!C11,IF(F31=0,0,IF(H31>0,H31,G31)*J31))) -> 4390.785 | M31: =IF(B31="","",IF(L31="",K31,L31)) -> 4390.785 | N31: =IF(B31="","",F31*M31) -> 26344.71 | O31: =IF(OR(B31="",$N$156=""),"",N31/$N$156) -> 0.01024532 | P31: 2800 | Q31: 3375 | R31: 4200 | S31: =IF(OR(B31="",F31=""),"",IF(M31=0,"ZERO PRICE",IF(AND(M31>0,M31<=0.05,Q31>1),"TOKEN PRICE",IF(AND(Q31>0,M31<P31*0.5),"UNDER BAND",IF(AND(R31>0,M31>R31*1.5),"OVER BAND",IF(AND(B31="500-7001",$N$156>0,N31/$N$156>0.1),"MOB > 10%","OK")))))) -> OK
A32: =IF('WS Import'!H42="","",ROW()-5) -> 27 | B32: =IF('WS Import'!H42="","",'WS Import'!H42) -> 644-7073 | C32: =IF('WS Import'!H42="","",'WS Import'!C42) -> Remove sm rd sn sup & am | D32: =IF(B32="","",IF('WS Import'!F42<>"",'WS Import'!F42,IF(LEFT(B32,3)="500","Mobilization",IF(OR(LEFT(B32,3)="502",LEFT(B32,3)="503",LEFT(B32,3)="505",LEFT(B32,3)="512"),"Traffic control",IF(LEFT(B32,3)="506","SW3P",IF(OR(LEFT(B32,3)="100",LEFT(B32,3)="104",LEFT(B32,3)="105",LEFT(B32,3)="110",LEFT(B32,3)="132"),"Earthwork",IF(LEFT(B32,3)="247","Base",IF(OR(LEFT(B32,3)="310",LEFT(B32,3)="316",LEFT(B32,3)="340",LEFT(B32,3)="341",LEFT(B32,3)="344",LEFT(B32,3)="354",LEFT(B32,4)="3076",LEFT(B32,4)="3077",LEFT(B32,4)="3080"),"Paving",IF(OR(LEFT(B32,3)="400",LEFT(B32,3)="416",LEFT(B32,3)="420",LEFT(B32,3)="422",LEFT(B32,3)="432",LEFT(B32,3)="450",LEFT(B32,3)="462",LEFT(B32,3)="464",LEFT(B32,3)="465",LEFT(B32,3)="466",LEFT(B32,3)="467",LEFT(B32,3)="496"),"Drainage",IF(OR(LEFT(B32,3)="164",LEFT(B32,3)="168",LEFT(B32,3)="169",LEFT(B32,3)="529",LEFT(B32,3)="530",LEFT(B32,3)="531"),"Roadside",IF(OR(LEFT(B32,3)="540",LEFT(B32,3)="542",LEFT(B32,3)="544",LEFT(B32,3)="545"),"Safety",IF(OR(LEFT(B32,3)="644",LEFT(B32,3)="636",LEFT(B32,3)="658"),"Signing",IF(OR(LEFT(B32,3)="666",LEFT(B32,3)="668",LEFT(B32,3)="672",LEFT(B32,3)="677",LEFT(B32,3)="678"),"Markings","Other"))))))))))))) -> Signing | E32: =IF(B32="","",'WS Import'!D42) -> EA | F32: =IF(B32="","",'WS Import'!E42) -> 22 | G32: 95 | H32: =IF(B32="","",IFERROR(INDEX('Unit Cost'!$N$6:$N$21,MATCH(B32,'Unit Cost'!$B$6:$B$21,0)),0)) -> 0 | I32: =IF(B32="","",F32*IF(H32>0,H32,G32)) -> 2090 | J32: =IF(B32="","",IF(B32="500-7001",1,MarkupFactor)) -> 1.4163822 | K32: =IF(B32="","",IF(B32="500-7001",Mobilization!C11,IF(F32=0,0,IF(H32>0,H32,G32)*J32))) -> 134.55631 | M32: =IF(B32="","",IF(L32="",K32,L32)) -> 134.55631 | N32: =IF(B32="","",F32*M32) -> 2960.2389 | O32: =IF(OR(B32="",$N$156=""),"",N32/$N$156) -> 0.0011512214 | P32: 80 | Q32: 110 | R32: 160 | S32: =IF(OR(B32="",F32=""),"",IF(M32=0,"ZERO PRICE",IF(AND(M32>0,M32<=0.05,Q32>1),"TOKEN PRICE",IF(AND(Q32>0,M32<P32*0.5),"UNDER BAND",IF(AND(R32>0,M32>R32*1.5),"OVER BAND",IF(AND(B32="500-7001",$N$156>0,N32/$N$156>0.1),"MOB > 10%","OK")))))) -> OK
A33: =IF('WS Import'!H43="","",ROW()-5) -> 28 | B33: =IF('WS Import'!H43="","",'WS Import'!H43) -> 644-7001 | C33: =IF('WS Import'!H43="","",'WS Import'!C43) -> Install sm rd sn sup & am | D33: =IF(B33="","",IF('WS Import'!F43<>"",'WS Import'!F43,IF(LEFT(B33,3)="500","Mobilization",IF(OR(LEFT(B33,3)="502",LEFT(B33,3)="503",LEFT(B33,3)="505",LEFT(B33,3)="512"),"Traffic control",IF(LEFT(B33,3)="506","SW3P",IF(OR(LEFT(B33,3)="100",LEFT(B33,3)="104",LEFT(B33,3)="105",LEFT(B33,3)="110",LEFT(B33,3)="132"),"Earthwork",IF(LEFT(B33,3)="247","Base",IF(OR(LEFT(B33,3)="310",LEFT(B33,3)="316",LEFT(B33,3)="340",LEFT(B33,3)="341",LEFT(B33,3)="344",LEFT(B33,3)="354",LEFT(B33,4)="3076",LEFT(B33,4)="3077",LEFT(B33,4)="3080"),"Paving",IF(OR(LEFT(B33,3)="400",LEFT(B33,3)="416",LEFT(B33,3)="420",LEFT(B33,3)="422",LEFT(B33,3)="432",LEFT(B33,3)="450",LEFT(B33,3)="462",LEFT(B33,3)="464",LEFT(B33,3)="465",LEFT(B33,3)="466",LEFT(B33,3)="467",LEFT(B33,3)="496"),"Drainage",IF(OR(LEFT(B33,3)="164",LEFT(B33,3)="168",LEFT(B33,3)="169",LEFT(B33,3)="529",LEFT(B33,3)="530",LEFT(B33,3)="531"),"Roadside",IF(OR(LEFT(B33,3)="540",LEFT(B33,3)="542",LEFT(B33,3)="544",LEFT(B33,3)="545"),"Safety",IF(OR(LEFT(B33,3)="644",LEFT(B33,3)="636",LEFT(B33,3)="658"),"Signing",IF(OR(LEFT(B33,3)="666",LEFT(B33,3)="668",LEFT(B33,3)="672",LEFT(B33,3)="677",LEFT(B33,3)="678"),"Markings","Other"))))))))))))) -> Signing | E33: =IF(B33="","",'WS Import'!D43) -> EA | F33: =IF(B33="","",'WS Import'!E43) -> 16 | G33: 650 | H33: =IF(B33="","",IFERROR(INDEX('Unit Cost'!$N$6:$N$21,MATCH(B33,'Unit Cost'!$B$6:$B$21,0)),0)) -> 0 | I33: =IF(B33="","",F33*IF(H33>0,H33,G33)) -> 10400 | J33: =IF(B33="","",IF(B33="500-7001",1,MarkupFactor)) -> 1.4163822 | K33: =IF(B33="","",IF(B33="500-7001",Mobilization!C11,IF(F33=0,0,IF(H33>0,H33,G33)*J33))) -> 920.64846 | M33: =IF(B33="","",IF(L33="",K33,L33)) -> 920.64846 | N33: =IF(B33="","",F33*M33) -> 14730.375 | O33: =IF(OR(B33="",$N$156=""),"",N33/$N$156) -> 0.0057285659 | P33: 450 | Q33: 780 | R33: 1200 | S33: =IF(OR(B33="",F33=""),"",IF(M33=0,"ZERO PRICE",IF(AND(M33>0,M33<=0.05,Q33>1),"TOKEN PRICE",IF(AND(Q33>0,M33<P33*0.5),"UNDER BAND",IF(AND(R33>0,M33>R33*1.5),"OVER BAND",IF(AND(B33="500-7001",$N$156>0,N33/$N$156>0.1),"MOB > 10%","OK")))))) -> OK
A34: =IF('WS Import'!H44="","",ROW()-5) -> 29 | B34: =IF('WS Import'!H44="","",'WS Import'!H44) -> 666-7172 | C34: =IF('WS Import'!H44="","",'WS Import'!C44) -> Refl pav mrk ty I (W) 4 in (sld)(100mil) | D34: =IF(B34="","",IF('WS Import'!F44<>"",'WS Import'!F44,IF(LEFT(B34,3)="500","Mobilization",IF(OR(LEFT(B34,3)="502",LEFT(B34,3)="503",LEFT(B34,3)="505",LEFT(B34,3)="512"),"Traffic control",IF(LEFT(B34,3)="506","SW3P",IF(OR(LEFT(B34,3)="100",LEFT(B34,3)="104",LEFT(B34,3)="105",LEFT(B34,3)="110",LEFT(B34,3)="132"),"Earthwork",IF(LEFT(B34,3)="247","Base",IF(OR(LEFT(B34,3)="310",LEFT(B34,3)="316",LEFT(B34,3)="340",LEFT(B34,3)="341",LEFT(B34,3)="344",LEFT(B34,3)="354",LEFT(B34,4)="3076",LEFT(B34,4)="3077",LEFT(B34,4)="3080"),"Paving",IF(OR(LEFT(B34,3)="400",LEFT(B34,3)="416",LEFT(B34,3)="420",LEFT(B34,3)="422",LEFT(B34,3)="432",LEFT(B34,3)="450",LEFT(B34,3)="462",LEFT(B34,3)="464",LEFT(B34,3)="465",LEFT(B34,3)="466",LEFT(B34,3)="467",LEFT(B34,3)="496"),"Drainage",IF(OR(LEFT(B34,3)="164",LEFT(B34,3)="168",LEFT(B34,3)="169",LEFT(B34,3)="529",LEFT(B34,3)="530",LEFT(B34,3)="531"),"Roadside",IF(OR(LEFT(B34,3)="540",LEFT(B34,3)="542",LEFT(B34,3)="544",LEFT(B34,3)="545"),"Safety",IF(OR(LEFT(B34,3)="644",LEFT(B34,3)="636",LEFT(B34,3)="658"),"Signing",IF(OR(LEFT(B34,3)="666",LEFT(B34,3)="668",LEFT(B34,3)="672",LEFT(B34,3)="677",LEFT(B34,3)="678"),"Markings","Other"))))))))))))) -> Markings | E34: =IF(B34="","",'WS Import'!D44) -> LF | F34: =IF(B34="","",'WS Import'!E44) -> 48000 | G34: 0 | H34: =IF(B34="","",IFERROR(INDEX('Unit Cost'!$N$6:$N$21,MATCH(B34,'Unit Cost'!$B$6:$B$21,0)),0)) -> 0.39193333 | I34: =IF(B34="","",F34*IF(H34>0,H34,G34)) -> 18812.8 | J34: =IF(B34="","",IF(B34="500-7001",1,MarkupFactor)) -> 1.4163822 | K34: =IF(B34="","",IF(B34="500-7001",Mobilization!C11,IF(F34=0,0,IF(H34>0,H34,G34)*J34))) -> 0.55512741 | M34: =IF(B34="","",IF(L34="",K34,L34)) -> 0.55512741 | N34: =IF(B34="","",F34*M34) -> 26646.116 | O34: =IF(OR(B34="",$N$156=""),"",N34/$N$156) -> 0.010362535 | P34: 0.45 | Q34: 0.75 | R34: 1.15 | S34: =IF(OR(B34="",F34=""),"",IF(M34=0,"ZERO PRICE",IF(AND(M34>0,M34<=0.05,Q34>1),"TOKEN PRICE",IF(AND(Q34>0,M34<P34*0.5),"UNDER BAND",IF(AND(R34>0,M34>R34*1.5),"OVER BAND",IF(AND(B34="500-7001",$N$156>0,N34/$N$156>0.1),"MOB > 10%","OK")))))) -> OK
A35: =IF('WS Import'!H45="","",ROW()-5) -> 30 | B35: =IF('WS Import'!H45="","",'WS Import'!H45) -> 666-7175 | C35: =IF('WS Import'!H45="","",'WS Import'!C45) -> Refl pav mrk ty I (Y) 4 in (sld)(100mil) | D35: =IF(B35="","",IF('WS Import'!F45<>"",'WS Import'!F45,IF(LEFT(B35,3)="500","Mobilization",IF(OR(LEFT(B35,3)="502",LEFT(B35,3)="503",LEFT(B35,3)="505",LEFT(B35,3)="512"),"Traffic control",IF(LEFT(B35,3)="506","SW3P",IF(OR(LEFT(B35,3)="100",LEFT(B35,3)="104",LEFT(B35,3)="105",LEFT(B35,3)="110",LEFT(B35,3)="132"),"Earthwork",IF(LEFT(B35,3)="247","Base",IF(OR(LEFT(B35,3)="310",LEFT(B35,3)="316",LEFT(B35,3)="340",LEFT(B35,3)="341",LEFT(B35,3)="344",LEFT(B35,3)="354",LEFT(B35,4)="3076",LEFT(B35,4)="3077",LEFT(B35,4)="3080"),"Paving",IF(OR(LEFT(B35,3)="400",LEFT(B35,3)="416",LEFT(B35,3)="420",LEFT(B35,3)="422",LEFT(B35,3)="432",LEFT(B35,3)="450",LEFT(B35,3)="462",LEFT(B35,3)="464",LEFT(B35,3)="465",LEFT(B35,3)="466",LEFT(B35,3)="467",LEFT(B35,3)="496"),"Drainage",IF(OR(LEFT(B35,3)="164",LEFT(B35,3)="168",LEFT(B35,3)="169",LEFT(B35,3)="529",LEFT(B35,3)="530",LEFT(B35,3)="531"),"Roadside",IF(OR(LEFT(B35,3)="540",LEFT(B35,3)="542",LEFT(B35,3)="544",LEFT(B35,3)="545"),"Safety",IF(OR(LEFT(B35,3)="644",LEFT(B35,3)="636",LEFT(B35,3)="658"),"Signing",IF(OR(LEFT(B35,3)="666",LEFT(B35,3)="668",LEFT(B35,3)="672",LEFT(B35,3)="677",LEFT(B35,3)="678"),"Markings","Other"))))))))))))) -> Markings | E35: =IF(B35="","",'WS Import'!D45) -> LF | F35: =IF(B35="","",'WS Import'!E45) -> 26000 | G35: 0 | H35: =IF(B35="","",IFERROR(INDEX('Unit Cost'!$N$6:$N$21,MATCH(B35,'Unit Cost'!$B$6:$B$21,0)),0)) -> 0.39193333 | I35: =IF(B35="","",F35*IF(H35>0,H35,G35)) -> 10190.267 | J35: =IF(B35="","",IF(B35="500-7001",1,MarkupFactor)) -> 1.4163822 | K35: =IF(B35="","",IF(B35="500-7001",Mobilization!C11,IF(F35=0,0,IF(H35>0,H35,G35)*J35))) -> 0.55512741 | M35: =IF(B35="","",IF(L35="",K35,L35)) -> 0.55512741 | N35: =IF(B35="","",F35*M35) -> 14433.313 | O35: =IF(OR(B35="",$N$156=""),"",N35/$N$156) -> 0.0056130399 | P35: 0.45 | Q35: 0.75 | R35: 1.15 | S35: =IF(OR(B35="",F35=""),"",IF(M35=0,"ZERO PRICE",IF(AND(M35>0,M35<=0.05,Q35>1),"TOKEN PRICE",IF(AND(Q35>0,M35<P35*0.5),"UNDER BAND",IF(AND(R35>0,M35>R35*1.5),"OVER BAND",IF(AND(B35="500-7001",$N$156>0,N35/$N$156>0.1),"MOB > 10%","OK")))))) -> OK
A36: =IF('WS Import'!H46="","",ROW()-5) -> 31 | B36: =IF('WS Import'!H46="","",'WS Import'!H46) -> 672-7004 | C36: =IF('WS Import'!H46="","",'WS Import'!C46) -> Refl pav mrkr ty II-A-A | D36: =IF(B36="","",IF('WS Import'!F46<>"",'WS Import'!F46,IF(LEFT(B36,3)="500","Mobilization",IF(OR(LEFT(B36,3)="502",LEFT(B36,3)="503",LEFT(B36,3)="505",LEFT(B36,3)="512"),"Traffic control",IF(LEFT(B36,3)="506","SW3P",IF(OR(LEFT(B36,3)="100",LEFT(B36,3)="104",LEFT(B36,3)="105",LEFT(B36,3)="110",LEFT(B36,3)="132"),"Earthwork",IF(LEFT(B36,3)="247","Base",IF(OR(LEFT(B36,3)="310",LEFT(B36,3)="316",LEFT(B36,3)="340",LEFT(B36,3)="341",LEFT(B36,3)="344",LEFT(B36,3)="354",LEFT(B36,4)="3076",LEFT(B36,4)="3077",LEFT(B36,4)="3080"),"Paving",IF(OR(LEFT(B36,3)="400",LEFT(B36,3)="416",LEFT(B36,3)="420",LEFT(B36,3)="422",LEFT(B36,3)="432",LEFT(B36,3)="450",LEFT(B36,3)="462",LEFT(B36,3)="464",LEFT(B36,3)="465",LEFT(B36,3)="466",LEFT(B36,3)="467",LEFT(B36,3)="496"),"Drainage",IF(OR(LEFT(B36,3)="164",LEFT(B36,3)="168",LEFT(B36,3)="169",LEFT(B36,3)="529",LEFT(B36,3)="530",LEFT(B36,3)="531"),"Roadside",IF(OR(LEFT(B36,3)="540",LEFT(B36,3)="542",LEFT(B36,3)="544",LEFT(B36,3)="545"),"Safety",IF(OR(LEFT(B36,3)="644",LEFT(B36,3)="636",LEFT(B36,3)="658"),"Signing",IF(OR(LEFT(B36,3)="666",LEFT(B36,3)="668",LEFT(B36,3)="672",LEFT(B36,3)="677",LEFT(B36,3)="678"),"Markings","Other"))))))))))))) -> Markings | E36: =IF(B36="","",'WS Import'!D46) -> EA | F36: =IF(B36="","",'WS Import'!E46) -> 820 | G36: 4.4 | H36: =IF(B36="","",IFERROR(INDEX('Unit Cost'!$N$6:$N$21,MATCH(B36,'Unit Cost'!$B$6:$B$21,0)),0)) -> 0 | I36: =IF(B36="","",F36*IF(H36>0,H36,G36)) -> 3608 | J36: =IF(B36="","",IF(B36="500-7001",1,MarkupFactor)) -> 1.4163822 | K36: =IF(B36="","",IF(B36="500-7001",Mobilization!C11,IF(F36=0,0,IF(H36>0,H36,G36)*J36))) -> 6.2320819 | M36: =IF(B36="","",IF(L36="",K36,L36)) -> 6.2320819 | N36: =IF(B36="","",F36*M36) -> 5110.3071 | O36: =IF(OR(B36="",$N$156=""),"",N36/$N$156) -> 0.0019873717 | P36: 4 | Q36: 5.2 | R36: 7.5 | S36: =IF(OR(B36="",F36=""),"",IF(M36=0,"ZERO PRICE",IF(AND(M36>0,M36<=0.05,Q36>1),"TOKEN PRICE",IF(AND(Q36>0,M36<P36*0.5),"UNDER BAND",IF(AND(R36>0,M36>R36*1.5),"OVER BAND",IF(AND(B36="500-7001",$N$156>0,N36/$N$156>0.1),"MOB > 10%","OK")))))) -> OK
A37: =IF('WS Import'!H47="","",ROW()-5) -> 32 | B37: =IF('WS Import'!H47="","",'WS Import'!H47) -> 677-7001 | C37: =IF('WS Import'!H47="","",'WS Import'!C47) -> Elim ext pav mrk & mrks (4 in) | D37: =IF(B37="","",IF('WS Import'!F47<>"",'WS Import'!F47,IF(LEFT(B37,3)="500","Mobilization",IF(OR(LEFT(B37,3)="502",LEFT(B37,3)="503",LEFT(B37,3)="505",LEFT(B37,3)="512"),"Traffic control",IF(LEFT(B37,3)="506","SW3P",IF(OR(LEFT(B37,3)="100",LEFT(B37,3)="104",LEFT(B37,3)="105",LEFT(B37,3)="110",LEFT(B37,3)="132"),"Earthwork",IF(LEFT(B37,3)="247","Base",IF(OR(LEFT(B37,3)="310",LEFT(B37,3)="316",LEFT(B37,3)="340",LEFT(B37,3)="341",LEFT(B37,3)="344",LEFT(B37,3)="354",LEFT(B37,4)="3076",LEFT(B37,4)="3077",LEFT(B37,4)="3080"),"Paving",IF(OR(LEFT(B37,3)="400",LEFT(B37,3)="416",LEFT(B37,3)="420",LEFT(B37,3)="422",LEFT(B37,3)="432",LEFT(B37,3)="450",LEFT(B37,3)="462",LEFT(B37,3)="464",LEFT(B37,3)="465",LEFT(B37,3)="466",LEFT(B37,3)="467",LEFT(B37,3)="496"),"Drainage",IF(OR(LEFT(B37,3)="164",LEFT(B37,3)="168",LEFT(B37,3)="169",LEFT(B37,3)="529",LEFT(B37,3)="530",LEFT(B37,3)="531"),"Roadside",IF(OR(LEFT(B37,3)="540",LEFT(B37,3)="542",LEFT(B37,3)="544",LEFT(B37,3)="545"),"Safety",IF(OR(LEFT(B37,3)="644",LEFT(B37,3)="636",LEFT(B37,3)="658"),"Signing",IF(OR(LEFT(B37,3)="666",LEFT(B37,3)="668",LEFT(B37,3)="672",LEFT(B37,3)="677",LEFT(B37,3)="678"),"Markings","Other"))))))))))))) -> Markings | E37: =IF(B37="","",'WS Import'!D47) -> LF | F37: =IF(B37="","",'WS Import'!E47) -> 74000 | G37: 0.28 | H37: =IF(B37="","",IFERROR(INDEX('Unit Cost'!$N$6:$N$21,MATCH(B37,'Unit Cost'!$B$6:$B$21,0)),0)) -> 0 | I37: =IF(B37="","",F37*IF(H37>0,H37,G37)) -> 20720 | J37: =IF(B37="","",IF(B37="500-7001",1,MarkupFactor)) -> 1.4163822 | K37: =IF(B37="","",IF(B37="500-7001",Mobilization!C11,IF(F37=0,0,IF(H37>0,H37,G37)*J37))) -> 0.39658703 | M37: =IF(B37="","",IF(L37="",K37,L37)) -> 0.39658703 | N37: =IF(B37="","",F37*M37) -> 29347.44 | O37: =IF(OR(B37="",$N$156=""),"",N37/$N$156) -> 0.011413066 | P37: 0.18 | Q37: 0.35 | R37: 0.55 | S37: =IF(OR(B37="",F37=""),"",IF(M37=0,"ZERO PRICE",IF(AND(M37>0,M37<=0.05,Q37>1),"TOKEN PRICE",IF(AND(Q37>0,M37<P37*0.5),"UNDER BAND",IF(AND(R37>0,M37>R37*1.5),"OVER BAND",IF(AND(B37="500-7001",$N$156>0,N37/$N$156>0.1),"MOB > 10%","OK")))))) -> OK
A38: =IF('WS Import'!H48="","",ROW()-5) -> 33 | B38: =IF('WS Import'!H48="","",'WS Import'!H48) -> 512-7001 | C38: =IF('WS Import'!H48="","",'WS Import'!C48) -> Port CTB (furn & inst)(safety shaped) | D38: =IF(B38="","",IF('WS Import'!F48<>"",'WS Import'!F48,IF(LEFT(B38,3)="500","Mobilization",IF(OR(LEFT(B38,3)="502",LEFT(B38,3)="503",LEFT(B38,3)="505",LEFT(B38,3)="512"),"Traffic control",IF(LEFT(B38,3)="506","SW3P",IF(OR(LEFT(B38,3)="100",LEFT(B38,3)="104",LEFT(B38,3)="105",LEFT(B38,3)="110",LEFT(B38,3)="132"),"Earthwork",IF(LEFT(B38,3)="247","Base",IF(OR(LEFT(B38,3)="310",LEFT(B38,3)="316",LEFT(B38,3)="340",LEFT(B38,3)="341",LEFT(B38,3)="344",LEFT(B38,3)="354",LEFT(B38,4)="3076",LEFT(B38,4)="3077",LEFT(B38,4)="3080"),"Paving",IF(OR(LEFT(B38,3)="400",LEFT(B38,3)="416",LEFT(B38,3)="420",LEFT(B38,3)="422",LEFT(B38,3)="432",LEFT(B38,3)="450",LEFT(B38,3)="462",LEFT(B38,3)="464",LEFT(B38,3)="465",LEFT(B38,3)="466",LEFT(B38,3)="467",LEFT(B38,3)="496"),"Drainage",IF(OR(LEFT(B38,3)="164",LEFT(B38,3)="168",LEFT(B38,3)="169",LEFT(B38,3)="529",LEFT(B38,3)="530",LEFT(B38,3)="531"),"Roadside",IF(OR(LEFT(B38,3)="540",LEFT(B38,3)="542",LEFT(B38,3)="544",LEFT(B38,3)="545"),"Safety",IF(OR(LEFT(B38,3)="644",LEFT(B38,3)="636",LEFT(B38,3)="658"),"Signing",IF(OR(LEFT(B38,3)="666",LEFT(B38,3)="668",LEFT(B38,3)="672",LEFT(B38,3)="677",LEFT(B38,3)="678"),"Markings","Other"))))))))))))) -> Traffic control | E38: =IF(B38="","",'WS Import'!D48) -> LF | F38: =IF(B38="","",'WS Import'!E48) -> 400 | G38: 32 | H38: =IF(B38="","",IFERROR(INDEX('Unit Cost'!$N$6:$N$21,MATCH(B38,'Unit Cost'!$B$6:$B$21,0)),0)) -> 0 | I38: =IF(B38="","",F38*IF(H38>0,H38,G38)) -> 12800 | J38: =IF(B38="","",IF(B38="500-7001",1,MarkupFactor)) -> 1.4163822 | K38: =IF(B38="","",IF(B38="500-7001",Mobilization!C11,IF(F38=0,0,IF(H38>0,H38,G38)*J38))) -> 45.324232 | M38: =IF(B38="","",IF(L38="",K38,L38)) -> 45.324232 | N38: =IF(B38="","",F38*M38) -> 18129.693 | O38: =IF(OR(B38="",$N$156=""),"",N38/$N$156) -> 0.0070505427 | P38: 22 | Q38: 34 | R38: 48 | S38: =IF(OR(B38="",F38=""),"",IF(M38=0,"ZERO PRICE",IF(AND(M38>0,M38<=0.05,Q38>1),"TOKEN PRICE",IF(AND(Q38>0,M38<P38*0.5),"UNDER BAND",IF(AND(R38>0,M38>R38*1.5),"OVER BAND",IF(AND(B38="500-7001",$N$156>0,N38/$N$156>0.1),"MOB > 10%","OK")))))) -> OK
A39: =IF('WS Import'!H49="","",ROW()-5) | B39: =IF('WS Import'!H49="","",'WS Import'!H49) | C39: =IF('WS Import'!H49="","",'WS Import'!C49) | D39: =IF(B39="","",IF('WS Import'!F49<>"",'WS Import'!F49,IF(LEFT(B39,3)="500","Mobilization",IF(OR(LEFT(B39,3)="502",LEFT(B39,3)="503",LEFT(B39,3)="505",LEFT(B39,3)="512"),"Traffic control",IF(LEFT(B39,3)="506","SW3P",IF(OR(LEFT(B39,3)="100",LEFT(B39,3)="104",LEFT(B39,3)="105",LEFT(B39,3)="110",LEFT(B39,3)="132"),"Earthwork",IF(LEFT(B39,3)="247","Base",IF(OR(LEFT(B39,3)="310",LEFT(B39,3)="316",LEFT(B39,3)="340",LEFT(B39,3)="341",LEFT(B39,3)="344",LEFT(B39,3)="354",LEFT(B39,4)="3076",LEFT(B39,4)="3077",LEFT(B39,4)="3080"),"Paving",IF(OR(LEFT(B39,3)="400",LEFT(B39,3)="416",LEFT(B39,3)="420",LEFT(B39,3)="422",LEFT(B39,3)="432",LEFT(B39,3)="450",LEFT(B39,3)="462",LEFT(B39,3)="464",LEFT(B39,3)="465",LEFT(B39,3)="466",LEFT(B39,3)="467",LEFT(B39,3)="496"),"Drainage",IF(OR(LEFT(B39,3)="164",LEFT(B39,3)="168",LEFT(B39,3)="169",LEFT(B39,3)="529",LEFT(B39,3)="530",LEFT(B39,3)="531"),"Roadside",IF(OR(LEFT(B39,3)="540",LEFT(B39,3)="542",LEFT(B39,3)="544",LEFT(B39,3)="545"),"Safety",IF(OR(LEFT(B39,3)="644",LEFT(B39,3)="636",LEFT(B39,3)="658"),"Signing",IF(OR(LEFT(B39,3)="666",LEFT(B39,3)="668",LEFT(B39,3)="672",LEFT(B39,3)="677",LEFT(B39,3)="678"),"Markings","Other"))))))))))))) | E39: =IF(B39="","",'WS Import'!D49) | F39: =IF(B39="","",'WS Import'!E49) | H39: =IF(B39="","",IFERROR(INDEX('Unit Cost'!$N$6:$N$21,MATCH(B39,'Unit Cost'!$B$6:$B$21,0)),0)) | I39: =IF(B39="","",F39*IF(H39>0,H39,G39)) | J39: =IF(B39="","",IF(B39="500-7001",1,MarkupFactor)) | K39: =IF(B39="","",IF(B39="500-7001",Mobilization!C11,IF(F39=0,0,IF(H39>0,H39,G39)*J39))) | M39: =IF(B39="","",IF(L39="",K39,L39)) | N39: =IF(B39="","",F39*M39) | O39: =IF(OR(B39="",$N$156=""),"",N39/$N$156) | S39: =IF(OR(B39="",F39=""),"",IF(M39=0,"ZERO PRICE",IF(AND(M39>0,M39<=0.05,Q39>1),"TOKEN PRICE",IF(AND(Q39>0,M39<P39*0.5),"UNDER BAND",IF(AND(R39>0,M39>R39*1.5),"OVER BAND",IF(AND(B39="500-7001",$N$156>0,N39/$N$156>0.1),"MOB > 10%","OK"))))))
A40: =IF('WS Import'!H50="","",ROW()-5) | B40: =IF('WS Import'!H50="","",'WS Import'!H50) | C40: =IF('WS Import'!H50="","",'WS Import'!C50) | D40: =IF(B40="","",IF('WS Import'!F50<>"",'WS Import'!F50,IF(LEFT(B40,3)="500","Mobilization",IF(OR(LEFT(B40,3)="502",LEFT(B40,3)="503",LEFT(B40,3)="505",LEFT(B40,3)="512"),"Traffic control",IF(LEFT(B40,3)="506","SW3P",IF(OR(LEFT(B40,3)="100",LEFT(B40,3)="104",LEFT(B40,3)="105",LEFT(B40,3)="110",LEFT(B40,3)="132"),"Earthwork",IF(LEFT(B40,3)="247","Base",IF(OR(LEFT(B40,3)="310",LEFT(B40,3)="316",LEFT(B40,3)="340",LEFT(B40,3)="341",LEFT(B40,3)="344",LEFT(B40,3)="354",LEFT(B40,4)="3076",LEFT(B40,4)="3077",LEFT(B40,4)="3080"),"Paving",IF(OR(LEFT(B40,3)="400",LEFT(B40,3)="416",LEFT(B40,3)="420",LEFT(B40,3)="422",LEFT(B40,3)="432",LEFT(B40,3)="450",LEFT(B40,3)="462",LEFT(B40,3)="464",LEFT(B40,3)="465",LEFT(B40,3)="466",LEFT(B40,3)="467",LEFT(B40,3)="496"),"Drainage",IF(OR(LEFT(B40,3)="164",LEFT(B40,3)="168",LEFT(B40,3)="169",LEFT(B40,3)="529",LEFT(B40,3)="530",LEFT(B40,3)="531"),"Roadside",IF(OR(LEFT(B40,3)="540",LEFT(B40,3)="542",LEFT(B40,3)="544",LEFT(B40,3)="545"),"Safety",IF(OR(LEFT(B40,3)="644",LEFT(B40,3)="636",LEFT(B40,3)="658"),"Signing",IF(OR(LEFT(B40,3)="666",LEFT(B40,3)="668",LEFT(B40,3)="672",LEFT(B40,3)="677",LEFT(B40,3)="678"),"Markings","Other"))))))))))))) | E40: =IF(B40="","",'WS Import'!D50) | F40: =IF(B40="","",'WS Import'!E50) | H40: =IF(B40="","",IFERROR(INDEX('Unit Cost'!$N$6:$N$21,MATCH(B40,'Unit Cost'!$B$6:$B$21,0)),0)) | I40: =IF(B40="","",F40*IF(H40>0,H40,G40)) | J40: =IF(B40="","",IF(B40="500-7001",1,MarkupFactor)) | K40: =IF(B40="","",IF(B40="500-7001",Mobilization!C11,IF(F40=0,0,IF(H40>0,H40,G40)*J40))) | M40: =IF(B40="","",IF(L40="",K40,L40)) | N40: =IF(B40="","",F40*M40) | O40: =IF(OR(B40="",$N$156=""),"",N40/$N$156) | S40: =IF(OR(B40="",F40=""),"",IF(M40=0,"ZERO PRICE",IF(AND(M40>0,M40<=0.05,Q40>1),"TOKEN PRICE",IF(AND(Q40>0,M40<P40*0.5),"UNDER BAND",IF(AND(R40>0,M40>R40*1.5),"OVER BAND",IF(AND(B40="500-7001",$N$156>0,N40/$N$156>0.1),"MOB > 10%","OK"))))))
A41: =IF('WS Import'!H51="","",ROW()-5) | B41: =IF('WS Import'!H51="","",'WS Import'!H51) | C41: =IF('WS Import'!H51="","",'WS Import'!C51) | D41: =IF(B41="","",IF('WS Import'!F51<>"",'WS Import'!F51,IF(LEFT(B41,3)="500","Mobilization",IF(OR(LEFT(B41,3)="502",LEFT(B41,3)="503",LEFT(B41,3)="505",LEFT(B41,3)="512"),"Traffic control",IF(LEFT(B41,3)="506","SW3P",IF(OR(LEFT(B41,3)="100",LEFT(B41,3)="104",LEFT(B41,3)="105",LEFT(B41,3)="110",LEFT(B41,3)="132"),"Earthwork",IF(LEFT(B41,3)="247","Base",IF(OR(LEFT(B41,3)="310",LEFT(B41,3)="316",LEFT(B41,3)="340",LEFT(B41,3)="341",LEFT(B41,3)="344",LEFT(B41,3)="354",LEFT(B41,4)="3076",LEFT(B41,4)="3077",LEFT(B41,4)="3080"),"Paving",IF(OR(LEFT(B41,3)="400",LEFT(B41,3)="416",LEFT(B41,3)="420",LEFT(B41,3)="422",LEFT(B41,3)="432",LEFT(B41,3)="450",LEFT(B41,3)="462",LEFT(B41,3)="464",LEFT(B41,3)="465",LEFT(B41,3)="466",LEFT(B41,3)="467",LEFT(B41,3)="496"),"Drainage",IF(OR(LEFT(B41,3)="164",LEFT(B41,3)="168",LEFT(B41,3)="169",LEFT(B41,3)="529",LEFT(B41,3)="530",LEFT(B41,3)="531"),"Roadside",IF(OR(LEFT(B41,3)="540",LEFT(B41,3)="542",LEFT(B41,3)="544",LEFT(B41,3)="545"),"Safety",IF(OR(LEFT(B41,3)="644",LEFT(B41,3)="636",LEFT(B41,3)="658"),"Signing",IF(OR(LEFT(B41,3)="666",LEFT(B41,3)="668",LEFT(B41,3)="672",LEFT(B41,3)="677",LEFT(B41,3)="678"),"Markings","Other"))))))))))))) | E41: =IF(B41="","",'WS Import'!D51) | F41: =IF(B41="","",'WS Import'!E51) | H41: =IF(B41="","",IFERROR(INDEX('Unit Cost'!$N$6:$N$21,MATCH(B41,'Unit Cost'!$B$6:$B$21,0)),0)) | I41: =IF(B41="","",F41*IF(H41>0,H41,G41)) | J41: =IF(B41="","",IF(B41="500-7001",1,MarkupFactor)) | K41: =IF(B41="","",IF(B41="500-7001",Mobilization!C11,IF(F41=0,0,IF(H41>0,H41,G41)*J41))) | M41: =IF(B41="","",IF(L41="",K41,L41)) | N41: =IF(B41="","",F41*M41) | O41: =IF(OR(B41="",$N$156=""),"",N41/$N$156) | S41: =IF(OR(B41="",F41=""),"",IF(M41=0,"ZERO PRICE",IF(AND(M41>0,M41<=0.05,Q41>1),"TOKEN PRICE",IF(AND(Q41>0,M41<P41*0.5),"UNDER BAND",IF(AND(R41>0,M41>R41*1.5),"OVER BAND",IF(AND(B41="500-7001",$N$156>0,N41/$N$156>0.1),"MOB > 10%","OK"))))))
A42: =IF('WS Import'!H52="","",ROW()-5) | B42: =IF('WS Import'!H52="","",'WS Import'!H52) | C42: =IF('WS Import'!H52="","",'WS Import'!C52) | D42: =IF(B42="","",IF('WS Import'!F52<>"",'WS Import'!F52,IF(LEFT(B42,3)="500","Mobilization",IF(OR(LEFT(B42,3)="502",LEFT(B42,3)="503",LEFT(B42,3)="505",LEFT(B42,3)="512"),"Traffic control",IF(LEFT(B42,3)="506","SW3P",IF(OR(LEFT(B42,3)="100",LEFT(B42,3)="104",LEFT(B42,3)="105",LEFT(B42,3)="110",LEFT(B42,3)="132"),"Earthwork",IF(LEFT(B42,3)="247","Base",IF(OR(LEFT(B42,3)="310",LEFT(B42,3)="316",LEFT(B42,3)="340",LEFT(B42,3)="341",LEFT(B42,3)="344",LEFT(B42,3)="354",LEFT(B42,4)="3076",LEFT(B42,4)="3077",LEFT(B42,4)="3080"),"Paving",IF(OR(LEFT(B42,3)="400",LEFT(B42,3)="416",LEFT(B42,3)="420",LEFT(B42,3)="422",LEFT(B42,3)="432",LEFT(B42,3)="450",LEFT(B42,3)="462",LEFT(B42,3)="464",LEFT(B42,3)="465",LEFT(B42,3)="466",LEFT(B42,3)="467",LEFT(B42,3)="496"),"Drainage",IF(OR(LEFT(B42,3)="164",LEFT(B42,3)="168",LEFT(B42,3)="169",LEFT(B42,3)="529",LEFT(B42,3)="530",LEFT(B42,3)="531"),"Roadside",IF(OR(LEFT(B42,3)="540",LEFT(B42,3)="542",LEFT(B42,3)="544",LEFT(B42,3)="545"),"Safety",IF(OR(LEFT(B42,3)="644",LEFT(B42,3)="636",LEFT(B42,3)="658"),"Signing",IF(OR(LEFT(B42,3)="666",LEFT(B42,3)="668",LEFT(B42,3)="672",LEFT(B42,3)="677",LEFT(B42,3)="678"),"Markings","Other"))))))))))))) | E42: =IF(B42="","",'WS Import'!D52) | F42: =IF(B42="","",'WS Import'!E52) | H42: =IF(B42="","",IFERROR(INDEX('Unit Cost'!$N$6:$N$21,MATCH(B42,'Unit Cost'!$B$6:$B$21,0)),0)) | I42: =IF(B42="","",F42*IF(H42>0,H42,G42)) | J42: =IF(B42="","",IF(B42="500-7001",1,MarkupFactor)) | K42: =IF(B42="","",IF(B42="500-7001",Mobilization!C11,IF(F42=0,0,IF(H42>0,H42,G42)*J42))) | M42: =IF(B42="","",IF(L42="",K42,L42)) | N42: =IF(B42="","",F42*M42) | O42: =IF(OR(B42="",$N$156=""),"",N42/$N$156) | S42: =IF(OR(B42="",F42=""),"",IF(M42=0,"ZERO PRICE",IF(AND(M42>0,M42<=0.05,Q42>1),"TOKEN PRICE",IF(AND(Q42>0,M42<P42*0.5),"UNDER BAND",IF(AND(R42>0,M42>R42*1.5),"OVER BAND",IF(AND(B42="500-7001",$N$156>0,N42/$N$156>0.1),"MOB > 10%","OK"))))))
A43: =IF('WS Import'!H53="","",ROW()-5) | B43: =IF('WS Import'!H53="","",'WS Import'!H53) | C43: =IF('WS Import'!H53="","",'WS Import'!C53) | D43: =IF(B43="","",IF('WS Import'!F53<>"",'WS Import'!F53,IF(LEFT(B43,3)="500","Mobilization",IF(OR(LEFT(B43,3)="502",LEFT(B43,3)="503",LEFT(B43,3)="505",LEFT(B43,3)="512"),"Traffic control",IF(LEFT(B43,3)="506","SW3P",IF(OR(LEFT(B43,3)="100",LEFT(B43,3)="104",LEFT(B43,3)="105",LEFT(B43,3)="110",LEFT(B43,3)="132"),"Earthwork",IF(LEFT(B43,3)="247","Base",IF(OR(LEFT(B43,3)="310",LEFT(B43,3)="316",LEFT(B43,3)="340",LEFT(B43,3)="341",LEFT(B43,3)="344",LEFT(B43,3)="354",LEFT(B43,4)="3076",LEFT(B43,4)="3077",LEFT(B43,4)="3080"),"Paving",IF(OR(LEFT(B43,3)="400",LEFT(B43,3)="416",LEFT(B43,3)="420",LEFT(B43,3)="422",LEFT(B43,3)="432",LEFT(B43,3)="450",LEFT(B43,3)="462",LEFT(B43,3)="464",LEFT(B43,3)="465",LEFT(B43,3)="466",LEFT(B43,3)="467",LEFT(B43,3)="496"),"Drainage",IF(OR(LEFT(B43,3)="164",LEFT(B43,3)="168",LEFT(B43,3)="169",LEFT(B43,3)="529",LEFT(B43,3)="530",LEFT(B43,3)="531"),"Roadside",IF(OR(LEFT(B43,3)="540",LEFT(B43,3)="542",LEFT(B43,3)="544",LEFT(B43,3)="545"),"Safety",IF(OR(LEFT(B43,3)="644",LEFT(B43,3)="636",LEFT(B43,3)="658"),"Signing",IF(OR(LEFT(B43,3)="666",LEFT(B43,3)="668",LEFT(B43,3)="672",LEFT(B43,3)="677",LEFT(B43,3)="678"),"Markings","Other"))))))))))))) | E43: =IF(B43="","",'WS Import'!D53) | F43: =IF(B43="","",'WS Import'!E53) | H43: =IF(B43="","",IFERROR(INDEX('Unit Cost'!$N$6:$N$21,MATCH(B43,'Unit Cost'!$B$6:$B$21,0)),0)) | I43: =IF(B43="","",F43*IF(H43>0,H43,G43)) | J43: =IF(B43="","",IF(B43="500-7001",1,MarkupFactor)) | K43: =IF(B43="","",IF(B43="500-7001",Mobilization!C11,IF(F43=0,0,IF(H43>0,H43,G43)*J43))) | M43: =IF(B43="","",IF(L43="",K43,L43)) | N43: =IF(B43="","",F43*M43) | O43: =IF(OR(B43="",$N$156=""),"",N43/$N$156) | S43: =IF(OR(B43="",F43=""),"",IF(M43=0,"ZERO PRICE",IF(AND(M43>0,M43<=0.05,Q43>1),"TOKEN PRICE",IF(AND(Q43>0,M43<P43*0.5),"UNDER BAND",IF(AND(R43>0,M43>R43*1.5),"OVER BAND",IF(AND(B43="500-7001",$N$156>0,N43/$N$156>0.1),"MOB > 10%","OK"))))))
A44: =IF('WS Import'!H54="","",ROW()-5) | B44: =IF('WS Import'!H54="","",'WS Import'!H54) | C44: =IF('WS Import'!H54="","",'WS Import'!C54) | D44: =IF(B44="","",IF('WS Import'!F54<>"",'WS Import'!F54,IF(LEFT(B44,3)="500","Mobilization",IF(OR(LEFT(B44,3)="502",LEFT(B44,3)="503",LEFT(B44,3)="505",LEFT(B44,3)="512"),"Traffic control",IF(LEFT(B44,3)="506","SW3P",IF(OR(LEFT(B44,3)="100",LEFT(B44,3)="104",LEFT(B44,3)="105",LEFT(B44,3)="110",LEFT(B44,3)="132"),"Earthwork",IF(LEFT(B44,3)="247","Base",IF(OR(LEFT(B44,3)="310",LEFT(B44,3)="316",LEFT(B44,3)="340",LEFT(B44,3)="341",LEFT(B44,3)="344",LEFT(B44,3)="354",LEFT(B44,4)="3076",LEFT(B44,4)="3077",LEFT(B44,4)="3080"),"Paving",IF(OR(LEFT(B44,3)="400",LEFT(B44,3)="416",LEFT(B44,3)="420",LEFT(B44,3)="422",LEFT(B44,3)="432",LEFT(B44,3)="450",LEFT(B44,3)="462",LEFT(B44,3)="464",LEFT(B44,3)="465",LEFT(B44,3)="466",LEFT(B44,3)="467",LEFT(B44,3)="496"),"Drainage",IF(OR(LEFT(B44,3)="164",LEFT(B44,3)="168",LEFT(B44,3)="169",LEFT(B44,3)="529",LEFT(B44,3)="530",LEFT(B44,3)="531"),"Roadside",IF(OR(LEFT(B44,3)="540",LEFT(B44,3)="542",LEFT(B44,3)="544",LEFT(B44,3)="545"),"Safety",IF(OR(LEFT(B44,3)="644",LEFT(B44,3)="636",LEFT(B44,3)="658"),"Signing",IF(OR(LEFT(B44,3)="666",LEFT(B44,3)="668",LEFT(B44,3)="672",LEFT(B44,3)="677",LEFT(B44,3)="678"),"Markings","Other"))))))))))))) | E44: =IF(B44="","",'WS Import'!D54) | F44: =IF(B44="","",'WS Import'!E54) | H44: =IF(B44="","",IFERROR(INDEX('Unit Cost'!$N$6:$N$21,MATCH(B44,'Unit Cost'!$B$6:$B$21,0)),0)) | I44: =IF(B44="","",F44*IF(H44>0,H44,G44)) | J44: =IF(B44="","",IF(B44="500-7001",1,MarkupFactor)) | K44: =IF(B44="","",IF(B44="500-7001",Mobilization!C11,IF(F44=0,0,IF(H44>0,H44,G44)*J44))) | M44: =IF(B44="","",IF(L44="",K44,L44)) | N44: =IF(B44="","",F44*M44) | O44: =IF(OR(B44="",$N$156=""),"",N44/$N$156) | S44: =IF(OR(B44="",F44=""),"",IF(M44=0,"ZERO PRICE",IF(AND(M44>0,M44<=0.05,Q44>1),"TOKEN PRICE",IF(AND(Q44>0,M44<P44*0.5),"UNDER BAND",IF(AND(R44>0,M44>R44*1.5),"OVER BAND",IF(AND(B44="500-7001",$N$156>0,N44/$N$156>0.1),"MOB > 10%","OK"))))))
A45: =IF('WS Import'!H55="","",ROW()-5) | B45: =IF('WS Import'!H55="","",'WS Import'!H55) | C45: =IF('WS Import'!H55="","",'WS Import'!C55) | D45: =IF(B45="","",IF('WS Import'!F55<>"",'WS Import'!F55,IF(LEFT(B45,3)="500","Mobilization",IF(OR(LEFT(B45,3)="502",LEFT(B45,3)="503",LEFT(B45,3)="505",LEFT(B45,3)="512"),"Traffic control",IF(LEFT(B45,3)="506","SW3P",IF(OR(LEFT(B45,3)="100",LEFT(B45,3)="104",LEFT(B45,3)="105",LEFT(B45,3)="110",LEFT(B45,3)="132"),"Earthwork",IF(LEFT(B45,3)="247","Base",IF(OR(LEFT(B45,3)="310",LEFT(B45,3)="316",LEFT(B45,3)="340",LEFT(B45,3)="341",LEFT(B45,3)="344",LEFT(B45,3)="354",LEFT(B45,4)="3076",LEFT(B45,4)="3077",LEFT(B45,4)="3080"),"Paving",IF(OR(LEFT(B45,3)="400",LEFT(B45,3)="416",LEFT(B45,3)="420",LEFT(B45,3)="422",LEFT(B45,3)="432",LEFT(B45,3)="450",LEFT(B45,3)="462",LEFT(B45,3)="464",LEFT(B45,3)="465",LEFT(B45,3)="466",LEFT(B45,3)="467",LEFT(B45,3)="496"),"Drainage",IF(OR(LEFT(B45,3)="164",LEFT(B45,3)="168",LEFT(B45,3)="169",LEFT(B45,3)="529",LEFT(B45,3)="530",LEFT(B45,3)="531"),"Roadside",IF(OR(LEFT(B45,3)="540",LEFT(B45,3)="542",LEFT(B45,3)="544",LEFT(B45,3)="545"),"Safety",IF(OR(LEFT(B45,3)="644",LEFT(B45,3)="636",LEFT(B45,3)="658"),"Signing",IF(OR(LEFT(B45,3)="666",LEFT(B45,3)="668",LEFT(B45,3)="672",LEFT(B45,3)="677",LEFT(B45,3)="678"),"Markings","Other"))))))))))))) | E45: =IF(B45="","",'WS Import'!D55) | F45: =IF(B45="","",'WS Import'!E55) | H45: =IF(B45="","",IFERROR(INDEX('Unit Cost'!$N$6:$N$21,MATCH(B45,'Unit Cost'!$B$6:$B$21,0)),0)) | I45: =IF(B45="","",F45*IF(H45>0,H45,G45)) | J45: =IF(B45="","",IF(B45="500-7001",1,MarkupFactor)) | K45: =IF(B45="","",IF(B45="500-7001",Mobilization!C11,IF(F45=0,0,IF(H45>0,H45,G45)*J45))) | M45: =IF(B45="","",IF(L45="",K45,L45)) | N45: =IF(B45="","",F45*M45) | O45: =IF(OR(B45="",$N$156=""),"",N45/$N$156) | S45: =IF(OR(B45="",F45=""),"",IF(M45=0,"ZERO PRICE",IF(AND(M45>0,M45<=0.05,Q45>1),"TOKEN PRICE",IF(AND(Q45>0,M45<P45*0.5),"UNDER BAND",IF(AND(R45>0,M45>R45*1.5),"OVER BAND",IF(AND(B45="500-7001",$N$156>0,N45/$N$156>0.1),"MOB > 10%","OK"))))))
A46: =IF('WS Import'!H56="","",ROW()-5) | B46: =IF('WS Import'!H56="","",'WS Import'!H56) | C46: =IF('WS Import'!H56="","",'WS Import'!C56) | D46: =IF(B46="","",IF('WS Import'!F56<>"",'WS Import'!F56,IF(LEFT(B46,3)="500","Mobilization",IF(OR(LEFT(B46,3)="502",LEFT(B46,3)="503",LEFT(B46,3)="505",LEFT(B46,3)="512"),"Traffic control",IF(LEFT(B46,3)="506","SW3P",IF(OR(LEFT(B46,3)="100",LEFT(B46,3)="104",LEFT(B46,3)="105",LEFT(B46,3)="110",LEFT(B46,3)="132"),"Earthwork",IF(LEFT(B46,3)="247","Base",IF(OR(LEFT(B46,3)="310",LEFT(B46,3)="316",LEFT(B46,3)="340",LEFT(B46,3)="341",LEFT(B46,3)="344",LEFT(B46,3)="354",LEFT(B46,4)="3076",LEFT(B46,4)="3077",LEFT(B46,4)="3080"),"Paving",IF(OR(LEFT(B46,3)="400",LEFT(B46,3)="416",LEFT(B46,3)="420",LEFT(B46,3)="422",LEFT(B46,3)="432",LEFT(B46,3)="450",LEFT(B46,3)="462",LEFT(B46,3)="464",LEFT(B46,3)="465",LEFT(B46,3)="466",LEFT(B46,3)="467",LEFT(B46,3)="496"),"Drainage",IF(OR(LEFT(B46,3)="164",LEFT(B46,3)="168",LEFT(B46,3)="169",LEFT(B46,3)="529",LEFT(B46,3)="530",LEFT(B46,3)="531"),"Roadside",IF(OR(LEFT(B46,3)="540",LEFT(B46,3)="542",LEFT(B46,3)="544",LEFT(B46,3)="545"),"Safety",IF(OR(LEFT(B46,3)="644",LEFT(B46,3)="636",LEFT(B46,3)="658"),"Signing",IF(OR(LEFT(B46,3)="666",LEFT(B46,3)="668",LEFT(B46,3)="672",LEFT(B46,3)="677",LEFT(B46,3)="678"),"Markings","Other"))))))))))))) | E46: =IF(B46="","",'WS Import'!D56) | F46: =IF(B46="","",'WS Import'!E56) | H46: =IF(B46="","",IFERROR(INDEX('Unit Cost'!$N$6:$N$21,MATCH(B46,'Unit Cost'!$B$6:$B$21,0)),0)) | I46: =IF(B46="","",F46*IF(H46>0,H46,G46)) | J46: =IF(B46="","",IF(B46="500-7001",1,MarkupFactor)) | K46: =IF(B46="","",IF(B46="500-7001",Mobilization!C11,IF(F46=0,0,IF(H46>0,H46,G46)*J46))) | M46: =IF(B46="","",IF(L46="",K46,L46)) | N46: =IF(B46="","",F46*M46) | O46: =IF(OR(B46="",$N$156=""),"",N46/$N$156) | S46: =IF(OR(B46="",F46=""),"",IF(M46=0,"ZERO PRICE",IF(AND(M46>0,M46<=0.05,Q46>1),"TOKEN PRICE",IF(AND(Q46>0,M46<P46*0.5),"UNDER BAND",IF(AND(R46>0,M46>R46*1.5),"OVER BAND",IF(AND(B46="500-7001",$N$156>0,N46/$N$156>0.1),"MOB > 10%","OK"))))))
A47: =IF('WS Import'!H57="","",ROW()-5) | B47: =IF('WS Import'!H57="","",'WS Import'!H57) | C47: =IF('WS Import'!H57="","",'WS Import'!C57) | D47: =IF(B47="","",IF('WS Import'!F57<>"",'WS Import'!F57,IF(LEFT(B47,3)="500","Mobilization",IF(OR(LEFT(B47,3)="502",LEFT(B47,3)="503",LEFT(B47,3)="505",LEFT(B47,3)="512"),"Traffic control",IF(LEFT(B47,3)="506","SW3P",IF(OR(LEFT(B47,3)="100",LEFT(B47,3)="104",LEFT(B47,3)="105",LEFT(B47,3)="110",LEFT(B47,3)="132"),"Earthwork",IF(LEFT(B47,3)="247","Base",IF(OR(LEFT(B47,3)="310",LEFT(B47,3)="316",LEFT(B47,3)="340",LEFT(B47,3)="341",LEFT(B47,3)="344",LEFT(B47,3)="354",LEFT(B47,4)="3076",LEFT(B47,4)="3077",LEFT(B47,4)="3080"),"Paving",IF(OR(LEFT(B47,3)="400",LEFT(B47,3)="416",LEFT(B47,3)="420",LEFT(B47,3)="422",LEFT(B47,3)="432",LEFT(B47,3)="450",LEFT(B47,3)="462",LEFT(B47,3)="464",LEFT(B47,3)="465",LEFT(B47,3)="466",LEFT(B47,3)="467",LEFT(B47,3)="496"),"Drainage",IF(OR(LEFT(B47,3)="164",LEFT(B47,3)="168",LEFT(B47,3)="169",LEFT(B47,3)="529",LEFT(B47,3)="530",LEFT(B47,3)="531"),"Roadside",IF(OR(LEFT(B47,3)="540",LEFT(B47,3)="542",LEFT(B47,3)="544",LEFT(B47,3)="545"),"Safety",IF(OR(LEFT(B47,3)="644",LEFT(B47,3)="636",LEFT(B47,3)="658"),"Signing",IF(OR(LEFT(B47,3)="666",LEFT(B47,3)="668",LEFT(B47,3)="672",LEFT(B47,3)="677",LEFT(B47,3)="678"),"Markings","Other"))))))))))))) | E47: =IF(B47="","",'WS Import'!D57) | F47: =IF(B47="","",'WS Import'!E57) | H47: =IF(B47="","",IFERROR(INDEX('Unit Cost'!$N$6:$N$21,MATCH(B47,'Unit Cost'!$B$6:$B$21,0)),0)) | I47: =IF(B47="","",F47*IF(H47>0,H47,G47)) | J47: =IF(B47="","",IF(B47="500-7001",1,MarkupFactor)) | K47: =IF(B47="","",IF(B47="500-7001",Mobilization!C11,IF(F47=0,0,IF(H47>0,H47,G47)*J47))) | M47: =IF(B47="","",IF(L47="",K47,L47)) | N47: =IF(B47="","",F47*M47) | O47: =IF(OR(B47="",$N$156=""),"",N47/$N$156) | S47: =IF(OR(B47="",F47=""),"",IF(M47=0,"ZERO PRICE",IF(AND(M47>0,M47<=0.05,Q47>1),"TOKEN PRICE",IF(AND(Q47>0,M47<P47*0.5),"UNDER BAND",IF(AND(R47>0,M47>R47*1.5),"OVER BAND",IF(AND(B47="500-7001",$N$156>0,N47/$N$156>0.1),"MOB > 10%","OK"))))))
A48: =IF('WS Import'!H58="","",ROW()-5) | B48: =IF('WS Import'!H58="","",'WS Import'!H58) | C48: =IF('WS Import'!H58="","",'WS Import'!C58) | D48: =IF(B48="","",IF('WS Import'!F58<>"",'WS Import'!F58,IF(LEFT(B48,3)="500","Mobilization",IF(OR(LEFT(B48,3)="502",LEFT(B48,3)="503",LEFT(B48,3)="505",LEFT(B48,3)="512"),"Traffic control",IF(LEFT(B48,3)="506","SW3P",IF(OR(LEFT(B48,3)="100",LEFT(B48,3)="104",LEFT(B48,3)="105",LEFT(B48,3)="110",LEFT(B48,3)="132"),"Earthwork",IF(LEFT(B48,3)="247","Base",IF(OR(LEFT(B48,3)="310",LEFT(B48,3)="316",LEFT(B48,3)="340",LEFT(B48,3)="341",LEFT(B48,3)="344",LEFT(B48,3)="354",LEFT(B48,4)="3076",LEFT(B48,4)="3077",LEFT(B48,4)="3080"),"Paving",IF(OR(LEFT(B48,3)="400",LEFT(B48,3)="416",LEFT(B48,3)="420",LEFT(B48,3)="422",LEFT(B48,3)="432",LEFT(B48,3)="450",LEFT(B48,3)="462",LEFT(B48,3)="464",LEFT(B48,3)="465",LEFT(B48,3)="466",LEFT(B48,3)="467",LEFT(B48,3)="496"),"Drainage",IF(OR(LEFT(B48,3)="164",LEFT(B48,3)="168",LEFT(B48,3)="169",LEFT(B48,3)="529",LEFT(B48,3)="530",LEFT(B48,3)="531"),"Roadside",IF(OR(LEFT(B48,3)="540",LEFT(B48,3)="542",LEFT(B48,3)="544",LEFT(B48,3)="545"),"Safety",IF(OR(LEFT(B48,3)="644",LEFT(B48,3)="636",LEFT(B48,3)="658"),"Signing",IF(OR(LEFT(B48,3)="666",LEFT(B48,3)="668",LEFT(B48,3)="672",LEFT(B48,3)="677",LEFT(B48,3)="678"),"Markings","Other"))))))))))))) | E48: =IF(B48="","",'WS Import'!D58) | F48: =IF(B48="","",'WS Import'!E58) | H48: =IF(B48="","",IFERROR(INDEX('Unit Cost'!$N$6:$N$21,MATCH(B48,'Unit Cost'!$B$6:$B$21,0)),0)) | I48: =IF(B48="","",F48*IF(H48>0,H48,G48)) | J48: =IF(B48="","",IF(B48="500-7001",1,MarkupFactor)) | K48: =IF(B48="","",IF(B48="500-7001",Mobilization!C11,IF(F48=0,0,IF(H48>0,H48,G48)*J48))) | M48: =IF(B48="","",IF(L48="",K48,L48)) | N48: =IF(B48="","",F48*M48) | O48: =IF(OR(B48="",$N$156=""),"",N48/$N$156) | S48: =IF(OR(B48="",F48=""),"",IF(M48=0,"ZERO PRICE",IF(AND(M48>0,M48<=0.05,Q48>1),"TOKEN PRICE",IF(AND(Q48>0,M48<P48*0.5),"UNDER BAND",IF(AND(R48>0,M48>R48*1.5),"OVER BAND",IF(AND(B48="500-7001",$N$156>0,N48/$N$156>0.1),"MOB > 10%","OK"))))))
A49: =IF('WS Import'!H59="","",ROW()-5) | B49: =IF('WS Import'!H59="","",'WS Import'!H59) | C49: =IF('WS Import'!H59="","",'WS Import'!C59) | D49: =IF(B49="","",IF('WS Import'!F59<>"",'WS Import'!F59,IF(LEFT(B49,3)="500","Mobilization",IF(OR(LEFT(B49,3)="502",LEFT(B49,3)="503",LEFT(B49,3)="505",LEFT(B49,3)="512"),"Traffic control",IF(LEFT(B49,3)="506","SW3P",IF(OR(LEFT(B49,3)="100",LEFT(B49,3)="104",LEFT(B49,3)="105",LEFT(B49,3)="110",LEFT(B49,3)="132"),"Earthwork",IF(LEFT(B49,3)="247","Base",IF(OR(LEFT(B49,3)="310",LEFT(B49,3)="316",LEFT(B49,3)="340",LEFT(B49,3)="341",LEFT(B49,3)="344",LEFT(B49,3)="354",LEFT(B49,4)="3076",LEFT(B49,4)="3077",LEFT(B49,4)="3080"),"Paving",IF(OR(LEFT(B49,3)="400",LEFT(B49,3)="416",LEFT(B49,3)="420",LEFT(B49,3)="422",LEFT(B49,3)="432",LEFT(B49,3)="450",LEFT(B49,3)="462",LEFT(B49,3)="464",LEFT(B49,3)="465",LEFT(B49,3)="466",LEFT(B49,3)="467",LEFT(B49,3)="496"),"Drainage",IF(OR(LEFT(B49,3)="164",LEFT(B49,3)="168",LEFT(B49,3)="169",LEFT(B49,3)="529",LEFT(B49,3)="530",LEFT(B49,3)="531"),"Roadside",IF(OR(LEFT(B49,3)="540",LEFT(B49,3)="542",LEFT(B49,3)="544",LEFT(B49,3)="545"),"Safety",IF(OR(LEFT(B49,3)="644",LEFT(B49,3)="636",LEFT(B49,3)="658"),"Signing",IF(OR(LEFT(B49,3)="666",LEFT(B49,3)="668",LEFT(B49,3)="672",LEFT(B49,3)="677",LEFT(B49,3)="678"),"Markings","Other"))))))))))))) | E49: =IF(B49="","",'WS Import'!D59) | F49: =IF(B49="","",'WS Import'!E59) | H49: =IF(B49="","",IFERROR(INDEX('Unit Cost'!$N$6:$N$21,MATCH(B49,'Unit Cost'!$B$6:$B$21,0)),0)) | I49: =IF(B49="","",F49*IF(H49>0,H49,G49)) | J49: =IF(B49="","",IF(B49="500-7001",1,MarkupFactor)) | K49: =IF(B49="","",IF(B49="500-7001",Mobilization!C11,IF(F49=0,0,IF(H49>0,H49,G49)*J49))) | M49: =IF(B49="","",IF(L49="",K49,L49)) | N49: =IF(B49="","",F49*M49) | O49: =IF(OR(B49="",$N$156=""),"",N49/$N$156) | S49: =IF(OR(B49="",F49=""),"",IF(M49=0,"ZERO PRICE",IF(AND(M49>0,M49<=0.05,Q49>1),"TOKEN PRICE",IF(AND(Q49>0,M49<P49*0.5),"UNDER BAND",IF(AND(R49>0,M49>R49*1.5),"OVER BAND",IF(AND(B49="500-7001",$N$156>0,N49/$N$156>0.1),"MOB > 10%","OK"))))))
A50: =IF('WS Import'!H60="","",ROW()-5) | B50: =IF('WS Import'!H60="","",'WS Import'!H60) | C50: =IF('WS Import'!H60="","",'WS Import'!C60) | D50: =IF(B50="","",IF('WS Import'!F60<>"",'WS Import'!F60,IF(LEFT(B50,3)="500","Mobilization",IF(OR(LEFT(B50,3)="502",LEFT(B50,3)="503",LEFT(B50,3)="505",LEFT(B50,3)="512"),"Traffic control",IF(LEFT(B50,3)="506","SW3P",IF(OR(LEFT(B50,3)="100",LEFT(B50,3)="104",LEFT(B50,3)="105",LEFT(B50,3)="110",LEFT(B50,3)="132"),"Earthwork",IF(LEFT(B50,3)="247","Base",IF(OR(LEFT(B50,3)="310",LEFT(B50,3)="316",LEFT(B50,3)="340",LEFT(B50,3)="341",LEFT(B50,3)="344",LEFT(B50,3)="354",LEFT(B50,4)="3076",LEFT(B50,4)="3077",LEFT(B50,4)="3080"),"Paving",IF(OR(LEFT(B50,3)="400",LEFT(B50,3)="416",LEFT(B50,3)="420",LEFT(B50,3)="422",LEFT(B50,3)="432",LEFT(B50,3)="450",LEFT(B50,3)="462",LEFT(B50,3)="464",LEFT(B50,3)="465",LEFT(B50,3)="466",LEFT(B50,3)="467",LEFT(B50,3)="496"),"Drainage",IF(OR(LEFT(B50,3)="164",LEFT(B50,3)="168",LEFT(B50,3)="169",LEFT(B50,3)="529",LEFT(B50,3)="530",LEFT(B50,3)="531"),"Roadside",IF(OR(LEFT(B50,3)="540",LEFT(B50,3)="542",LEFT(B50,3)="544",LEFT(B50,3)="545"),"Safety",IF(OR(LEFT(B50,3)="644",LEFT(B50,3)="636",LEFT(B50,3)="658"),"Signing",IF(OR(LEFT(B50,3)="666",LEFT(B50,3)="668",LEFT(B50,3)="672",LEFT(B50,3)="677",LEFT(B50,3)="678"),"Markings","Other"))))))))))))) | E50: =IF(B50="","",'WS Import'!D60) | F50: =IF(B50="","",'WS Import'!E60) | H50: =IF(B50="","",IFERROR(INDEX('Unit Cost'!$N$6:$N$21,MATCH(B50,'Unit Cost'!$B$6:$B$21,0)),0)) | I50: =IF(B50="","",F50*IF(H50>0,H50,G50)) | J50: =IF(B50="","",IF(B50="500-7001",1,MarkupFactor)) | K50: =IF(B50="","",IF(B50="500-7001",Mobilization!C11,IF(F50=0,0,IF(H50>0,H50,G50)*J50))) | M50: =IF(B50="","",IF(L50="",K50,L50)) | N50: =IF(B50="","",F50*M50) | O50: =IF(OR(B50="",$N$156=""),"",N50/$N$156) | S50: =IF(OR(B50="",F50=""),"",IF(M50=0,"ZERO PRICE",IF(AND(M50>0,M50<=0.05,Q50>1),"TOKEN PRICE",IF(AND(Q50>0,M50<P50*0.5),"UNDER BAND",IF(AND(R50>0,M50>R50*1.5),"OVER BAND",IF(AND(B50="500-7001",$N$156>0,N50/$N$156>0.1),"MOB > 10%","OK"))))))
A51: =IF('WS Import'!H61="","",ROW()-5) | B51: =IF('WS Import'!H61="","",'WS Import'!H61) | C51: =IF('WS Import'!H61="","",'WS Import'!C61) | D51: =IF(B51="","",IF('WS Import'!F61<>"",'WS Import'!F61,IF(LEFT(B51,3)="500","Mobilization",IF(OR(LEFT(B51,3)="502",LEFT(B51,3)="503",LEFT(B51,3)="505",LEFT(B51,3)="512"),"Traffic control",IF(LEFT(B51,3)="506","SW3P",IF(OR(LEFT(B51,3)="100",LEFT(B51,3)="104",LEFT(B51,3)="105",LEFT(B51,3)="110",LEFT(B51,3)="132"),"Earthwork",IF(LEFT(B51,3)="247","Base",IF(OR(LEFT(B51,3)="310",LEFT(B51,3)="316",LEFT(B51,3)="340",LEFT(B51,3)="341",LEFT(B51,3)="344",LEFT(B51,3)="354",LEFT(B51,4)="3076",LEFT(B51,4)="3077",LEFT(B51,4)="3080"),"Paving",IF(OR(LEFT(B51,3)="400",LEFT(B51,3)="416",LEFT(B51,3)="420",LEFT(B51,3)="422",LEFT(B51,3)="432",LEFT(B51,3)="450",LEFT(B51,3)="462",LEFT(B51,3)="464",LEFT(B51,3)="465",LEFT(B51,3)="466",LEFT(B51,3)="467",LEFT(B51,3)="496"),"Drainage",IF(OR(LEFT(B51,3)="164",LEFT(B51,3)="168",LEFT(B51,3)="169",LEFT(B51,3)="529",LEFT(B51,3)="530",LEFT(B51,3)="531"),"Roadside",IF(OR(LEFT(B51,3)="540",LEFT(B51,3)="542",LEFT(B51,3)="544",LEFT(B51,3)="545"),"Safety",IF(OR(LEFT(B51,3)="644",LEFT(B51,3)="636",LEFT(B51,3)="658"),"Signing",IF(OR(LEFT(B51,3)="666",LEFT(B51,3)="668",LEFT(B51,3)="672",LEFT(B51,3)="677",LEFT(B51,3)="678"),"Markings","Other"))))))))))))) | E51: =IF(B51="","",'WS Import'!D61) | F51: =IF(B51="","",'WS Import'!E61) | H51: =IF(B51="","",IFERROR(INDEX('Unit Cost'!$N$6:$N$21,MATCH(B51,'Unit Cost'!$B$6:$B$21,0)),0)) | I51: =IF(B51="","",F51*IF(H51>0,H51,G51)) | J51: =IF(B51="","",IF(B51="500-7001",1,MarkupFactor)) | K51: =IF(B51="","",IF(B51="500-7001",Mobilization!C11,IF(F51=0,0,IF(H51>0,H51,G51)*J51))) | M51: =IF(B51="","",IF(L51="",K51,L51)) | N51: =IF(B51="","",F51*M51) | O51: =IF(OR(B51="",$N$156=""),"",N51/$N$156) | S51: =IF(OR(B51="",F51=""),"",IF(M51=0,"ZERO PRICE",IF(AND(M51>0,M51<=0.05,Q51>1),"TOKEN PRICE",IF(AND(Q51>0,M51<P51*0.5),"UNDER BAND",IF(AND(R51>0,M51>R51*1.5),"OVER BAND",IF(AND(B51="500-7001",$N$156>0,N51/$N$156>0.1),"MOB > 10%","OK"))))))
A52: =IF('WS Import'!H62="","",ROW()-5) | B52: =IF('WS Import'!H62="","",'WS Import'!H62) | C52: =IF('WS Import'!H62="","",'WS Import'!C62) | D52: =IF(B52="","",IF('WS Import'!F62<>"",'WS Import'!F62,IF(LEFT(B52,3)="500","Mobilization",IF(OR(LEFT(B52,3)="502",LEFT(B52,3)="503",LEFT(B52,3)="505",LEFT(B52,3)="512"),"Traffic control",IF(LEFT(B52,3)="506","SW3P",IF(OR(LEFT(B52,3)="100",LEFT(B52,3)="104",LEFT(B52,3)="105",LEFT(B52,3)="110",LEFT(B52,3)="132"),"Earthwork",IF(LEFT(B52,3)="247","Base",IF(OR(LEFT(B52,3)="310",LEFT(B52,3)="316",LEFT(B52,3)="340",LEFT(B52,3)="341",LEFT(B52,3)="344",LEFT(B52,3)="354",LEFT(B52,4)="3076",LEFT(B52,4)="3077",LEFT(B52,4)="3080"),"Paving",IF(OR(LEFT(B52,3)="400",LEFT(B52,3)="416",LEFT(B52,3)="420",LEFT(B52,3)="422",LEFT(B52,3)="432",LEFT(B52,3)="450",LEFT(B52,3)="462",LEFT(B52,3)="464",LEFT(B52,3)="465",LEFT(B52,3)="466",LEFT(B52,3)="467",LEFT(B52,3)="496"),"Drainage",IF(OR(LEFT(B52,3)="164",LEFT(B52,3)="168",LEFT(B52,3)="169",LEFT(B52,3)="529",LEFT(B52,3)="530",LEFT(B52,3)="531"),"Roadside",IF(OR(LEFT(B52,3)="540",LEFT(B52,3)="542",LEFT(B52,3)="544",LEFT(B52,3)="545"),"Safety",IF(OR(LEFT(B52,3)="644",LEFT(B52,3)="636",LEFT(B52,3)="658"),"Signing",IF(OR(LEFT(B52,3)="666",LEFT(B52,3)="668",LEFT(B52,3)="672",LEFT(B52,3)="677",LEFT(B52,3)="678"),"Markings","Other"))))))))))))) | E52: =IF(B52="","",'WS Import'!D62) | F52: =IF(B52="","",'WS Import'!E62) | H52: =IF(B52="","",IFERROR(INDEX('Unit Cost'!$N$6:$N$21,MATCH(B52,'Unit Cost'!$B$6:$B$21,0)),0)) | I52: =IF(B52="","",F52*IF(H52>0,H52,G52)) | J52: =IF(B52="","",IF(B52="500-7001",1,MarkupFactor)) | K52: =IF(B52="","",IF(B52="500-7001",Mobilization!C11,IF(F52=0,0,IF(H52>0,H52,G52)*J52))) | M52: =IF(B52="","",IF(L52="",K52,L52)) | N52: =IF(B52="","",F52*M52) | O52: =IF(OR(B52="",$N$156=""),"",N52/$N$156) | S52: =IF(OR(B52="",F52=""),"",IF(M52=0,"ZERO PRICE",IF(AND(M52>0,M52<=0.05,Q52>1),"TOKEN PRICE",IF(AND(Q52>0,M52<P52*0.5),"UNDER BAND",IF(AND(R52>0,M52>R52*1.5),"OVER BAND",IF(AND(B52="500-7001",$N$156>0,N52/$N$156>0.1),"MOB > 10%","OK"))))))
A53: =IF('WS Import'!H63="","",ROW()-5) | B53: =IF('WS Import'!H63="","",'WS Import'!H63) | C53: =IF('WS Import'!H63="","",'WS Import'!C63) | D53: =IF(B53="","",IF('WS Import'!F63<>"",'WS Import'!F63,IF(LEFT(B53,3)="500","Mobilization",IF(OR(LEFT(B53,3)="502",LEFT(B53,3)="503",LEFT(B53,3)="505",LEFT(B53,3)="512"),"Traffic control",IF(LEFT(B53,3)="506","SW3P",IF(OR(LEFT(B53,3)="100",LEFT(B53,3)="104",LEFT(B53,3)="105",LEFT(B53,3)="110",LEFT(B53,3)="132"),"Earthwork",IF(LEFT(B53,3)="247","Base",IF(OR(LEFT(B53,3)="310",LEFT(B53,3)="316",LEFT(B53,3)="340",LEFT(B53,3)="341",LEFT(B53,3)="344",LEFT(B53,3)="354",LEFT(B53,4)="3076",LEFT(B53,4)="3077",LEFT(B53,4)="3080"),"Paving",IF(OR(LEFT(B53,3)="400",LEFT(B53,3)="416",LEFT(B53,3)="420",LEFT(B53,3)="422",LEFT(B53,3)="432",LEFT(B53,3)="450",LEFT(B53,3)="462",LEFT(B53,3)="464",LEFT(B53,3)="465",LEFT(B53,3)="466",LEFT(B53,3)="467",LEFT(B53,3)="496"),"Drainage",IF(OR(LEFT(B53,3)="164",LEFT(B53,3)="168",LEFT(B53,3)="169",LEFT(B53,3)="529",LEFT(B53,3)="530",LEFT(B53,3)="531"),"Roadside",IF(OR(LEFT(B53,3)="540",LEFT(B53,3)="542",LEFT(B53,3)="544",LEFT(B53,3)="545"),"Safety",IF(OR(LEFT(B53,3)="644",LEFT(B53,3)="636",LEFT(B53,3)="658"),"Signing",IF(OR(LEFT(B53,3)="666",LEFT(B53,3)="668",LEFT(B53,3)="672",LEFT(B53,3)="677",LEFT(B53,3)="678"),"Markings","Other"))))))))))))) | E53: =IF(B53="","",'WS Import'!D63) | F53: =IF(B53="","",'WS Import'!E63) | H53: =IF(B53="","",IFERROR(INDEX('Unit Cost'!$N$6:$N$21,MATCH(B53,'Unit Cost'!$B$6:$B$21,0)),0)) | I53: =IF(B53="","",F53*IF(H53>0,H53,G53)) | J53: =IF(B53="","",IF(B53="500-7001",1,MarkupFactor)) | K53: =IF(B53="","",IF(B53="500-7001",Mobilization!C11,IF(F53=0,0,IF(H53>0,H53,G53)*J53))) | M53: =IF(B53="","",IF(L53="",K53,L53)) | N53: =IF(B53="","",F53*M53) | O53: =IF(OR(B53="",$N$156=""),"",N53/$N$156) | S53: =IF(OR(B53="",F53=""),"",IF(M53=0,"ZERO PRICE",IF(AND(M53>0,M53<=0.05,Q53>1),"TOKEN PRICE",IF(AND(Q53>0,M53<P53*0.5),"UNDER BAND",IF(AND(R53>0,M53>R53*1.5),"OVER BAND",IF(AND(B53="500-7001",$N$156>0,N53/$N$156>0.1),"MOB > 10%","OK"))))))
A54: =IF('WS Import'!H64="","",ROW()-5) | B54: =IF('WS Import'!H64="","",'WS Import'!H64) | C54: =IF('WS Import'!H64="","",'WS Import'!C64) | D54: =IF(B54="","",IF('WS Import'!F64<>"",'WS Import'!F64,IF(LEFT(B54,3)="500","Mobilization",IF(OR(LEFT(B54,3)="502",LEFT(B54,3)="503",LEFT(B54,3)="505",LEFT(B54,3)="512"),"Traffic control",IF(LEFT(B54,3)="506","SW3P",IF(OR(LEFT(B54,3)="100",LEFT(B54,3)="104",LEFT(B54,3)="105",LEFT(B54,3)="110",LEFT(B54,3)="132"),"Earthwork",IF(LEFT(B54,3)="247","Base",IF(OR(LEFT(B54,3)="310",LEFT(B54,3)="316",LEFT(B54,3)="340",LEFT(B54,3)="341",LEFT(B54,3)="344",LEFT(B54,3)="354",LEFT(B54,4)="3076",LEFT(B54,4)="3077",LEFT(B54,4)="3080"),"Paving",IF(OR(LEFT(B54,3)="400",LEFT(B54,3)="416",LEFT(B54,3)="420",LEFT(B54,3)="422",LEFT(B54,3)="432",LEFT(B54,3)="450",LEFT(B54,3)="462",LEFT(B54,3)="464",LEFT(B54,3)="465",LEFT(B54,3)="466",LEFT(B54,3)="467",LEFT(B54,3)="496"),"Drainage",IF(OR(LEFT(B54,3)="164",LEFT(B54,3)="168",LEFT(B54,3)="169",LEFT(B54,3)="529",LEFT(B54,3)="530",LEFT(B54,3)="531"),"Roadside",IF(OR(LEFT(B54,3)="540",LEFT(B54,3)="542",LEFT(B54,3)="544",LEFT(B54,3)="545"),"Safety",IF(OR(LEFT(B54,3)="644",LEFT(B54,3)="636",LEFT(B54,3)="658"),"Signing",IF(OR(LEFT(B54,3)="666",LEFT(B54,3)="668",LEFT(B54,3)="672",LEFT(B54,3)="677",LEFT(B54,3)="678"),"Markings","Other"))))))))))))) | E54: =IF(B54="","",'WS Import'!D64) | F54: =IF(B54="","",'WS Import'!E64) | H54: =IF(B54="","",IFERROR(INDEX('Unit Cost'!$N$6:$N$21,MATCH(B54,'Unit Cost'!$B$6:$B$21,0)),0)) | I54: =IF(B54="","",F54*IF(H54>0,H54,G54)) | J54: =IF(B54="","",IF(B54="500-7001",1,MarkupFactor)) | K54: =IF(B54="","",IF(B54="500-7001",Mobilization!C11,IF(F54=0,0,IF(H54>0,H54,G54)*J54))) | M54: =IF(B54="","",IF(L54="",K54,L54)) | N54: =IF(B54="","",F54*M54) | O54: =IF(OR(B54="",$N$156=""),"",N54/$N$156) | S54: =IF(OR(B54="",F54=""),"",IF(M54=0,"ZERO PRICE",IF(AND(M54>0,M54<=0.05,Q54>1),"TOKEN PRICE",IF(AND(Q54>0,M54<P54*0.5),"UNDER BAND",IF(AND(R54>0,M54>R54*1.5),"OVER BAND",IF(AND(B54="500-7001",$N$156>0,N54/$N$156>0.1),"MOB > 10%","OK"))))))
A55: =IF('WS Import'!H65="","",ROW()-5) | B55: =IF('WS Import'!H65="","",'WS Import'!H65) | C55: =IF('WS Import'!H65="","",'WS Import'!C65) | D55: =IF(B55="","",IF('WS Import'!F65<>"",'WS Import'!F65,IF(LEFT(B55,3)="500","Mobilization",IF(OR(LEFT(B55,3)="502",LEFT(B55,3)="503",LEFT(B55,3)="505",LEFT(B55,3)="512"),"Traffic control",IF(LEFT(B55,3)="506","SW3P",IF(OR(LEFT(B55,3)="100",LEFT(B55,3)="104",LEFT(B55,3)="105",LEFT(B55,3)="110",LEFT(B55,3)="132"),"Earthwork",IF(LEFT(B55,3)="247","Base",IF(OR(LEFT(B55,3)="310",LEFT(B55,3)="316",LEFT(B55,3)="340",LEFT(B55,3)="341",LEFT(B55,3)="344",LEFT(B55,3)="354",LEFT(B55,4)="3076",LEFT(B55,4)="3077",LEFT(B55,4)="3080"),"Paving",IF(OR(LEFT(B55,3)="400",LEFT(B55,3)="416",LEFT(B55,3)="420",LEFT(B55,3)="422",LEFT(B55,3)="432",LEFT(B55,3)="450",LEFT(B55,3)="462",LEFT(B55,3)="464",LEFT(B55,3)="465",LEFT(B55,3)="466",LEFT(B55,3)="467",LEFT(B55,3)="496"),"Drainage",IF(OR(LEFT(B55,3)="164",LEFT(B55,3)="168",LEFT(B55,3)="169",LEFT(B55,3)="529",LEFT(B55,3)="530",LEFT(B55,3)="531"),"Roadside",IF(OR(LEFT(B55,3)="540",LEFT(B55,3)="542",LEFT(B55,3)="544",LEFT(B55,3)="545"),"Safety",IF(OR(LEFT(B55,3)="644",LEFT(B55,3)="636",LEFT(B55,3)="658"),"Signing",IF(OR(LEFT(B55,3)="666",LEFT(B55,3)="668",LEFT(B55,3)="672",LEFT(B55,3)="677",LEFT(B55,3)="678"),"Markings","Other"))))))))))))) | E55: =IF(B55="","",'WS Import'!D65) | F55: =IF(B55="","",'WS Import'!E65) | H55: =IF(B55="","",IFERROR(INDEX('Unit Cost'!$N$6:$N$21,MATCH(B55,'Unit Cost'!$B$6:$B$21,0)),0)) | I55: =IF(B55="","",F55*IF(H55>0,H55,G55)) | J55: =IF(B55="","",IF(B55="500-7001",1,MarkupFactor)) | K55: =IF(B55="","",IF(B55="500-7001",Mobilization!C11,IF(F55=0,0,IF(H55>0,H55,G55)*J55))) | M55: =IF(B55="","",IF(L55="",K55,L55)) | N55: =IF(B55="","",F55*M55) | O55: =IF(OR(B55="",$N$156=""),"",N55/$N$156) | S55: =IF(OR(B55="",F55=""),"",IF(M55=0,"ZERO PRICE",IF(AND(M55>0,M55<=0.05,Q55>1),"TOKEN PRICE",IF(AND(Q55>0,M55<P55*0.5),"UNDER BAND",IF(AND(R55>0,M55>R55*1.5),"OVER BAND",IF(AND(B55="500-7001",$N$156>0,N55/$N$156>0.1),"MOB > 10%","OK"))))))
A56: =IF('WS Import'!H66="","",ROW()-5) | B56: =IF('WS Import'!H66="","",'WS Import'!H66) | C56: =IF('WS Import'!H66="","",'WS Import'!C66) | D56: =IF(B56="","",IF('WS Import'!F66<>"",'WS Import'!F66,IF(LEFT(B56,3)="500","Mobilization",IF(OR(LEFT(B56,3)="502",LEFT(B56,3)="503",LEFT(B56,3)="505",LEFT(B56,3)="512"),"Traffic control",IF(LEFT(B56,3)="506","SW3P",IF(OR(LEFT(B56,3)="100",LEFT(B56,3)="104",LEFT(B56,3)="105",LEFT(B56,3)="110",LEFT(B56,3)="132"),"Earthwork",IF(LEFT(B56,3)="247","Base",IF(OR(LEFT(B56,3)="310",LEFT(B56,3)="316",LEFT(B56,3)="340",LEFT(B56,3)="341",LEFT(B56,3)="344",LEFT(B56,3)="354",LEFT(B56,4)="3076",LEFT(B56,4)="3077",LEFT(B56,4)="3080"),"Paving",IF(OR(LEFT(B56,3)="400",LEFT(B56,3)="416",LEFT(B56,3)="420",LEFT(B56,3)="422",LEFT(B56,3)="432",LEFT(B56,3)="450",LEFT(B56,3)="462",LEFT(B56,3)="464",LEFT(B56,3)="465",LEFT(B56,3)="466",LEFT(B56,3)="467",LEFT(B56,3)="496"),"Drainage",IF(OR(LEFT(B56,3)="164",LEFT(B56,3)="168",LEFT(B56,3)="169",LEFT(B56,3)="529",LEFT(B56,3)="530",LEFT(B56,3)="531"),"Roadside",IF(OR(LEFT(B56,3)="540",LEFT(B56,3)="542",LEFT(B56,3)="544",LEFT(B56,3)="545"),"Safety",IF(OR(LEFT(B56,3)="644",LEFT(B56,3)="636",LEFT(B56,3)="658"),"Signing",IF(OR(LEFT(B56,3)="666",LEFT(B56,3)="668",LEFT(B56,3)="672",LEFT(B56,3)="677",LEFT(B56,3)="678"),"Markings","Other"))))))))))))) | E56: =IF(B56="","",'WS Import'!D66) | F56: =IF(B56="","",'WS Import'!E66) | H56: =IF(B56="","",IFERROR(INDEX('Unit Cost'!$N$6:$N$21,MATCH(B56,'Unit Cost'!$B$6:$B$21,0)),0)) | I56: =IF(B56="","",F56*IF(H56>0,H56,G56)) | J56: =IF(B56="","",IF(B56="500-7001",1,MarkupFactor)) | K56: =IF(B56="","",IF(B56="500-7001",Mobilization!C11,IF(F56=0,0,IF(H56>0,H56,G56)*J56))) | M56: =IF(B56="","",IF(L56="",K56,L56)) | N56: =IF(B56="","",F56*M56) | O56: =IF(OR(B56="",$N$156=""),"",N56/$N$156) | S56: =IF(OR(B56="",F56=""),"",IF(M56=0,"ZERO PRICE",IF(AND(M56>0,M56<=0.05,Q56>1),"TOKEN PRICE",IF(AND(Q56>0,M56<P56*0.5),"UNDER BAND",IF(AND(R56>0,M56>R56*1.5),"OVER BAND",IF(AND(B56="500-7001",$N$156>0,N56/$N$156>0.1),"MOB > 10%","OK"))))))
A57: =IF('WS Import'!H67="","",ROW()-5) | B57: =IF('WS Import'!H67="","",'WS Import'!H67) | C57: =IF('WS Import'!H67="","",'WS Import'!C67) | D57: =IF(B57="","",IF('WS Import'!F67<>"",'WS Import'!F67,IF(LEFT(B57,3)="500","Mobilization",IF(OR(LEFT(B57,3)="502",LEFT(B57,3)="503",LEFT(B57,3)="505",LEFT(B57,3)="512"),"Traffic control",IF(LEFT(B57,3)="506","SW3P",IF(OR(LEFT(B57,3)="100",LEFT(B57,3)="104",LEFT(B57,3)="105",LEFT(B57,3)="110",LEFT(B57,3)="132"),"Earthwork",IF(LEFT(B57,3)="247","Base",IF(OR(LEFT(B57,3)="310",LEFT(B57,3)="316",LEFT(B57,3)="340",LEFT(B57,3)="341",LEFT(B57,3)="344",LEFT(B57,3)="354",LEFT(B57,4)="3076",LEFT(B57,4)="3077",LEFT(B57,4)="3080"),"Paving",IF(OR(LEFT(B57,3)="400",LEFT(B57,3)="416",LEFT(B57,3)="420",LEFT(B57,3)="422",LEFT(B57,3)="432",LEFT(B57,3)="450",LEFT(B57,3)="462",LEFT(B57,3)="464",LEFT(B57,3)="465",LEFT(B57,3)="466",LEFT(B57,3)="467",LEFT(B57,3)="496"),"Drainage",IF(OR(LEFT(B57,3)="164",LEFT(B57,3)="168",LEFT(B57,3)="169",LEFT(B57,3)="529",LEFT(B57,3)="530",LEFT(B57,3)="531"),"Roadside",IF(OR(LEFT(B57,3)="540",LEFT(B57,3)="542",LEFT(B57,3)="544",LEFT(B57,3)="545"),"Safety",IF(OR(LEFT(B57,3)="644",LEFT(B57,3)="636",LEFT(B57,3)="658"),"Signing",IF(OR(LEFT(B57,3)="666",LEFT(B57,3)="668",LEFT(B57,3)="672",LEFT(B57,3)="677",LEFT(B57,3)="678"),"Markings","Other"))))))))))))) | E57: =IF(B57="","",'WS Import'!D67) | F57: =IF(B57="","",'WS Import'!E67) | H57: =IF(B57="","",IFERROR(INDEX('Unit Cost'!$N$6:$N$21,MATCH(B57,'Unit Cost'!$B$6:$B$21,0)),0)) | I57: =IF(B57="","",F57*IF(H57>0,H57,G57)) | J57: =IF(B57="","",IF(B57="500-7001",1,MarkupFactor)) | K57: =IF(B57="","",IF(B57="500-7001",Mobilization!C11,IF(F57=0,0,IF(H57>0,H57,G57)*J57))) | M57: =IF(B57="","",IF(L57="",K57,L57)) | N57: =IF(B57="","",F57*M57) | O57: =IF(OR(B57="",$N$156=""),"",N57/$N$156) | S57: =IF(OR(B57="",F57=""),"",IF(M57=0,"ZERO PRICE",IF(AND(M57>0,M57<=0.05,Q57>1),"TOKEN PRICE",IF(AND(Q57>0,M57<P57*0.5),"UNDER BAND",IF(AND(R57>0,M57>R57*1.5),"OVER BAND",IF(AND(B57="500-7001",$N$156>0,N57/$N$156>0.1),"MOB > 10%","OK"))))))
A58: =IF('WS Import'!H68="","",ROW()-5) | B58: =IF('WS Import'!H68="","",'WS Import'!H68) | C58: =IF('WS Import'!H68="","",'WS Import'!C68) | D58: =IF(B58="","",IF('WS Import'!F68<>"",'WS Import'!F68,IF(LEFT(B58,3)="500","Mobilization",IF(OR(LEFT(B58,3)="502",LEFT(B58,3)="503",LEFT(B58,3)="505",LEFT(B58,3)="512"),"Traffic control",IF(LEFT(B58,3)="506","SW3P",IF(OR(LEFT(B58,3)="100",LEFT(B58,3)="104",LEFT(B58,3)="105",LEFT(B58,3)="110",LEFT(B58,3)="132"),"Earthwork",IF(LEFT(B58,3)="247","Base",IF(OR(LEFT(B58,3)="310",LEFT(B58,3)="316",LEFT(B58,3)="340",LEFT(B58,3)="341",LEFT(B58,3)="344",LEFT(B58,3)="354",LEFT(B58,4)="3076",LEFT(B58,4)="3077",LEFT(B58,4)="3080"),"Paving",IF(OR(LEFT(B58,3)="400",LEFT(B58,3)="416",LEFT(B58,3)="420",LEFT(B58,3)="422",LEFT(B58,3)="432",LEFT(B58,3)="450",LEFT(B58,3)="462",LEFT(B58,3)="464",LEFT(B58,3)="465",LEFT(B58,3)="466",LEFT(B58,3)="467",LEFT(B58,3)="496"),"Drainage",IF(OR(LEFT(B58,3)="164",LEFT(B58,3)="168",LEFT(B58,3)="169",LEFT(B58,3)="529",LEFT(B58,3)="530",LEFT(B58,3)="531"),"Roadside",IF(OR(LEFT(B58,3)="540",LEFT(B58,3)="542",LEFT(B58,3)="544",LEFT(B58,3)="545"),"Safety",IF(OR(LEFT(B58,3)="644",LEFT(B58,3)="636",LEFT(B58,3)="658"),"Signing",IF(OR(LEFT(B58,3)="666",LEFT(B58,3)="668",LEFT(B58,3)="672",LEFT(B58,3)="677",LEFT(B58,3)="678"),"Markings","Other"))))))))))))) | E58: =IF(B58="","",'WS Import'!D68) | F58: =IF(B58="","",'WS Import'!E68) | H58: =IF(B58="","",IFERROR(INDEX('Unit Cost'!$N$6:$N$21,MATCH(B58,'Unit Cost'!$B$6:$B$21,0)),0)) | I58: =IF(B58="","",F58*IF(H58>0,H58,G58)) | J58: =IF(B58="","",IF(B58="500-7001",1,MarkupFactor)) | K58: =IF(B58="","",IF(B58="500-7001",Mobilization!C11,IF(F58=0,0,IF(H58>0,H58,G58)*J58))) | M58: =IF(B58="","",IF(L58="",K58,L58)) | N58: =IF(B58="","",F58*M58) | O58: =IF(OR(B58="",$N$156=""),"",N58/$N$156) | S58: =IF(OR(B58="",F58=""),"",IF(M58=0,"ZERO PRICE",IF(AND(M58>0,M58<=0.05,Q58>1),"TOKEN PRICE",IF(AND(Q58>0,M58<P58*0.5),"UNDER BAND",IF(AND(R58>0,M58>R58*1.5),"OVER BAND",IF(AND(B58="500-7001",$N$156>0,N58/$N$156>0.1),"MOB > 10%","OK"))))))
A59: =IF('WS Import'!H69="","",ROW()-5) | B59: =IF('WS Import'!H69="","",'WS Import'!H69) | C59: =IF('WS Import'!H69="","",'WS Import'!C69) | D59: =IF(B59="","",IF('WS Import'!F69<>"",'WS Import'!F69,IF(LEFT(B59,3)="500","Mobilization",IF(OR(LEFT(B59,3)="502",LEFT(B59,3)="503",LEFT(B59,3)="505",LEFT(B59,3)="512"),"Traffic control",IF(LEFT(B59,3)="506","SW3P",IF(OR(LEFT(B59,3)="100",LEFT(B59,3)="104",LEFT(B59,3)="105",LEFT(B59,3)="110",LEFT(B59,3)="132"),"Earthwork",IF(LEFT(B59,3)="247","Base",IF(OR(LEFT(B59,3)="310",LEFT(B59,3)="316",LEFT(B59,3)="340",LEFT(B59,3)="341",LEFT(B59,3)="344",LEFT(B59,3)="354",LEFT(B59,4)="3076",LEFT(B59,4)="3077",LEFT(B59,4)="3080"),"Paving",IF(OR(LEFT(B59,3)="400",LEFT(B59,3)="416",LEFT(B59,3)="420",LEFT(B59,3)="422",LEFT(B59,3)="432",LEFT(B59,3)="450",LEFT(B59,3)="462",LEFT(B59,3)="464",LEFT(B59,3)="465",LEFT(B59,3)="466",LEFT(B59,3)="467",LEFT(B59,3)="496"),"Drainage",IF(OR(LEFT(B59,3)="164",LEFT(B59,3)="168",LEFT(B59,3)="169",LEFT(B59,3)="529",LEFT(B59,3)="530",LEFT(B59,3)="531"),"Roadside",IF(OR(LEFT(B59,3)="540",LEFT(B59,3)="542",LEFT(B59,3)="544",LEFT(B59,3)="545"),"Safety",IF(OR(LEFT(B59,3)="644",LEFT(B59,3)="636",LEFT(B59,3)="658"),"Signing",IF(OR(LEFT(B59,3)="666",LEFT(B59,3)="668",LEFT(B59,3)="672",LEFT(B59,3)="677",LEFT(B59,3)="678"),"Markings","Other"))))))))))))) | E59: =IF(B59="","",'WS Import'!D69) | F59: =IF(B59="","",'WS Import'!E69) | H59: =IF(B59="","",IFERROR(INDEX('Unit Cost'!$N$6:$N$21,MATCH(B59,'Unit Cost'!$B$6:$B$21,0)),0)) | I59: =IF(B59="","",F59*IF(H59>0,H59,G59)) | J59: =IF(B59="","",IF(B59="500-7001",1,MarkupFactor)) | K59: =IF(B59="","",IF(B59="500-7001",Mobilization!C11,IF(F59=0,0,IF(H59>0,H59,G59)*J59))) | M59: =IF(B59="","",IF(L59="",K59,L59)) | N59: =IF(B59="","",F59*M59) | O59: =IF(OR(B59="",$N$156=""),"",N59/$N$156) | S59: =IF(OR(B59="",F59=""),"",IF(M59=0,"ZERO PRICE",IF(AND(M59>0,M59<=0.05,Q59>1),"TOKEN PRICE",IF(AND(Q59>0,M59<P59*0.5),"UNDER BAND",IF(AND(R59>0,M59>R59*1.5),"OVER BAND",IF(AND(B59="500-7001",$N$156>0,N59/$N$156>0.1),"MOB > 10%","OK"))))))
A60: =IF('WS Import'!H70="","",ROW()-5) | B60: =IF('WS Import'!H70="","",'WS Import'!H70) | C60: =IF('WS Import'!H70="","",'WS Import'!C70) | D60: =IF(B60="","",IF('WS Import'!F70<>"",'WS Import'!F70,IF(LEFT(B60,3)="500","Mobilization",IF(OR(LEFT(B60,3)="502",LEFT(B60,3)="503",LEFT(B60,3)="505",LEFT(B60,3)="512"),"Traffic control",IF(LEFT(B60,3)="506","SW3P",IF(OR(LEFT(B60,3)="100",LEFT(B60,3)="104",LEFT(B60,3)="105",LEFT(B60,3)="110",LEFT(B60,3)="132"),"Earthwork",IF(LEFT(B60,3)="247","Base",IF(OR(LEFT(B60,3)="310",LEFT(B60,3)="316",LEFT(B60,3)="340",LEFT(B60,3)="341",LEFT(B60,3)="344",LEFT(B60,3)="354",LEFT(B60,4)="3076",LEFT(B60,4)="3077",LEFT(B60,4)="3080"),"Paving",IF(OR(LEFT(B60,3)="400",LEFT(B60,3)="416",LEFT(B60,3)="420",LEFT(B60,3)="422",LEFT(B60,3)="432",LEFT(B60,3)="450",LEFT(B60,3)="462",LEFT(B60,3)="464",LEFT(B60,3)="465",LEFT(B60,3)="466",LEFT(B60,3)="467",LEFT(B60,3)="496"),"Drainage",IF(OR(LEFT(B60,3)="164",LEFT(B60,3)="168",LEFT(B60,3)="169",LEFT(B60,3)="529",LEFT(B60,3)="530",LEFT(B60,3)="531"),"Roadside",IF(OR(LEFT(B60,3)="540",LEFT(B60,3)="542",LEFT(B60,3)="544",LEFT(B60,3)="545"),"Safety",IF(OR(LEFT(B60,3)="644",LEFT(B60,3)="636",LEFT(B60,3)="658"),"Signing",IF(OR(LEFT(B60,3)="666",LEFT(B60,3)="668",LEFT(B60,3)="672",LEFT(B60,3)="677",LEFT(B60,3)="678"),"Markings","Other"))))))))))))) | E60: =IF(B60="","",'WS Import'!D70) | F60: =IF(B60="","",'WS Import'!E70) | H60: =IF(B60="","",IFERROR(INDEX('Unit Cost'!$N$6:$N$21,MATCH(B60,'Unit Cost'!$B$6:$B$21,0)),0)) | I60: =IF(B60="","",F60*IF(H60>0,H60,G60)) | J60: =IF(B60="","",IF(B60="500-7001",1,MarkupFactor)) | K60: =IF(B60="","",IF(B60="500-7001",Mobilization!C11,IF(F60=0,0,IF(H60>0,H60,G60)*J60))) | M60: =IF(B60="","",IF(L60="",K60,L60)) | N60: =IF(B60="","",F60*M60) | O60: =IF(OR(B60="",$N$156=""),"",N60/$N$156) | S60: =IF(OR(B60="",F60=""),"",IF(M60=0,"ZERO PRICE",IF(AND(M60>0,M60<=0.05,Q60>1),"TOKEN PRICE",IF(AND(Q60>0,M60<P60*0.5),"UNDER BAND",IF(AND(R60>0,M60>R60*1.5),"OVER BAND",IF(AND(B60="500-7001",$N$156>0,N60/$N$156>0.1),"MOB > 10%","OK"))))))
A61: =IF('WS Import'!H71="","",ROW()-5) | B61: =IF('WS Import'!H71="","",'WS Import'!H71) | C61: =IF('WS Import'!H71="","",'WS Import'!C71) | D61: =IF(B61="","",IF('WS Import'!F71<>"",'WS Import'!F71,IF(LEFT(B61,3)="500","Mobilization",IF(OR(LEFT(B61,3)="502",LEFT(B61,3)="503",LEFT(B61,3)="505",LEFT(B61,3)="512"),"Traffic control",IF(LEFT(B61,3)="506","SW3P",IF(OR(LEFT(B61,3)="100",LEFT(B61,3)="104",LEFT(B61,3)="105",LEFT(B61,3)="110",LEFT(B61,3)="132"),"Earthwork",IF(LEFT(B61,3)="247","Base",IF(OR(LEFT(B61,3)="310",LEFT(B61,3)="316",LEFT(B61,3)="340",LEFT(B61,3)="341",LEFT(B61,3)="344",LEFT(B61,3)="354",LEFT(B61,4)="3076",LEFT(B61,4)="3077",LEFT(B61,4)="3080"),"Paving",IF(OR(LEFT(B61,3)="400",LEFT(B61,3)="416",LEFT(B61,3)="420",LEFT(B61,3)="422",LEFT(B61,3)="432",LEFT(B61,3)="450",LEFT(B61,3)="462",LEFT(B61,3)="464",LEFT(B61,3)="465",LEFT(B61,3)="466",LEFT(B61,3)="467",LEFT(B61,3)="496"),"Drainage",IF(OR(LEFT(B61,3)="164",LEFT(B61,3)="168",LEFT(B61,3)="169",LEFT(B61,3)="529",LEFT(B61,3)="530",LEFT(B61,3)="531"),"Roadside",IF(OR(LEFT(B61,3)="540",LEFT(B61,3)="542",LEFT(B61,3)="544",LEFT(B61,3)="545"),"Safety",IF(OR(LEFT(B61,3)="644",LEFT(B61,3)="636",LEFT(B61,3)="658"),"Signing",IF(OR(LEFT(B61,3)="666",LEFT(B61,3)="668",LEFT(B61,3)="672",LEFT(B61,3)="677",LEFT(B61,3)="678"),"Markings","Other"))))))))))))) | E61: =IF(B61="","",'WS Import'!D71) | F61: =IF(B61="","",'WS Import'!E71) | H61: =IF(B61="","",IFERROR(INDEX('Unit Cost'!$N$6:$N$21,MATCH(B61,'Unit Cost'!$B$6:$B$21,0)),0)) | I61: =IF(B61="","",F61*IF(H61>0,H61,G61)) | J61: =IF(B61="","",IF(B61="500-7001",1,MarkupFactor)) | K61: =IF(B61="","",IF(B61="500-7001",Mobilization!C11,IF(F61=0,0,IF(H61>0,H61,G61)*J61))) | M61: =IF(B61="","",IF(L61="",K61,L61)) | N61: =IF(B61="","",F61*M61) | O61: =IF(OR(B61="",$N$156=""),"",N61/$N$156) | S61: =IF(OR(B61="",F61=""),"",IF(M61=0,"ZERO PRICE",IF(AND(M61>0,M61<=0.05,Q61>1),"TOKEN PRICE",IF(AND(Q61>0,M61<P61*0.5),"UNDER BAND",IF(AND(R61>0,M61>R61*1.5),"OVER BAND",IF(AND(B61="500-7001",$N$156>0,N61/$N$156>0.1),"MOB > 10%","OK"))))))
A62: =IF('WS Import'!H72="","",ROW()-5) | B62: =IF('WS Import'!H72="","",'WS Import'!H72) | C62: =IF('WS Import'!H72="","",'WS Import'!C72) | D62: =IF(B62="","",IF('WS Import'!F72<>"",'WS Import'!F72,IF(LEFT(B62,3)="500","Mobilization",IF(OR(LEFT(B62,3)="502",LEFT(B62,3)="503",LEFT(B62,3)="505",LEFT(B62,3)="512"),"Traffic control",IF(LEFT(B62,3)="506","SW3P",IF(OR(LEFT(B62,3)="100",LEFT(B62,3)="104",LEFT(B62,3)="105",LEFT(B62,3)="110",LEFT(B62,3)="132"),"Earthwork",IF(LEFT(B62,3)="247","Base",IF(OR(LEFT(B62,3)="310",LEFT(B62,3)="316",LEFT(B62,3)="340",LEFT(B62,3)="341",LEFT(B62,3)="344",LEFT(B62,3)="354",LEFT(B62,4)="3076",LEFT(B62,4)="3077",LEFT(B62,4)="3080"),"Paving",IF(OR(LEFT(B62,3)="400",LEFT(B62,3)="416",LEFT(B62,3)="420",LEFT(B62,3)="422",LEFT(B62,3)="432",LEFT(B62,3)="450",LEFT(B62,3)="462",LEFT(B62,3)="464",LEFT(B62,3)="465",LEFT(B62,3)="466",LEFT(B62,3)="467",LEFT(B62,3)="496"),"Drainage",IF(OR(LEFT(B62,3)="164",LEFT(B62,3)="168",LEFT(B62,3)="169",LEFT(B62,3)="529",LEFT(B62,3)="530",LEFT(B62,3)="531"),"Roadside",IF(OR(LEFT(B62,3)="540",LEFT(B62,3)="542",LEFT(B62,3)="544",LEFT(B62,3)="545"),"Safety",IF(OR(LEFT(B62,3)="644",LEFT(B62,3)="636",LEFT(B62,3)="658"),"Signing",IF(OR(LEFT(B62,3)="666",LEFT(B62,3)="668",LEFT(B62,3)="672",LEFT(B62,3)="677",LEFT(B62,3)="678"),"Markings","Other"))))))))))))) | E62: =IF(B62="","",'WS Import'!D72) | F62: =IF(B62="","",'WS Import'!E72) | H62: =IF(B62="","",IFERROR(INDEX('Unit Cost'!$N$6:$N$21,MATCH(B62,'Unit Cost'!$B$6:$B$21,0)),0)) | I62: =IF(B62="","",F62*IF(H62>0,H62,G62)) | J62: =IF(B62="","",IF(B62="500-7001",1,MarkupFactor)) | K62: =IF(B62="","",IF(B62="500-7001",Mobilization!C11,IF(F62=0,0,IF(H62>0,H62,G62)*J62))) | M62: =IF(B62="","",IF(L62="",K62,L62)) | N62: =IF(B62="","",F62*M62) | O62: =IF(OR(B62="",$N$156=""),"",N62/$N$156) | S62: =IF(OR(B62="",F62=""),"",IF(M62=0,"ZERO PRICE",IF(AND(M62>0,M62<=0.05,Q62>1),"TOKEN PRICE",IF(AND(Q62>0,M62<P62*0.5),"UNDER BAND",IF(AND(R62>0,M62>R62*1.5),"OVER BAND",IF(AND(B62="500-7001",$N$156>0,N62/$N$156>0.1),"MOB > 10%","OK"))))))
A63: =IF('WS Import'!H73="","",ROW()-5) | B63: =IF('WS Import'!H73="","",'WS Import'!H73) | C63: =IF('WS Import'!H73="","",'WS Import'!C73) | D63: =IF(B63="","",IF('WS Import'!F73<>"",'WS Import'!F73,IF(LEFT(B63,3)="500","Mobilization",IF(OR(LEFT(B63,3)="502",LEFT(B63,3)="503",LEFT(B63,3)="505",LEFT(B63,3)="512"),"Traffic control",IF(LEFT(B63,3)="506","SW3P",IF(OR(LEFT(B63,3)="100",LEFT(B63,3)="104",LEFT(B63,3)="105",LEFT(B63,3)="110",LEFT(B63,3)="132"),"Earthwork",IF(LEFT(B63,3)="247","Base",IF(OR(LEFT(B63,3)="310",LEFT(B63,3)="316",LEFT(B63,3)="340",LEFT(B63,3)="341",LEFT(B63,3)="344",LEFT(B63,3)="354",LEFT(B63,4)="3076",LEFT(B63,4)="3077",LEFT(B63,4)="3080"),"Paving",IF(OR(LEFT(B63,3)="400",LEFT(B63,3)="416",LEFT(B63,3)="420",LEFT(B63,3)="422",LEFT(B63,3)="432",LEFT(B63,3)="450",LEFT(B63,3)="462",LEFT(B63,3)="464",LEFT(B63,3)="465",LEFT(B63,3)="466",LEFT(B63,3)="467",LEFT(B63,3)="496"),"Drainage",IF(OR(LEFT(B63,3)="164",LEFT(B63,3)="168",LEFT(B63,3)="169",LEFT(B63,3)="529",LEFT(B63,3)="530",LEFT(B63,3)="531"),"Roadside",IF(OR(LEFT(B63,3)="540",LEFT(B63,3)="542",LEFT(B63,3)="544",LEFT(B63,3)="545"),"Safety",IF(OR(LEFT(B63,3)="644",LEFT(B63,3)="636",LEFT(B63,3)="658"),"Signing",IF(OR(LEFT(B63,3)="666",LEFT(B63,3)="668",LEFT(B63,3)="672",LEFT(B63,3)="677",LEFT(B63,3)="678"),"Markings","Other"))))))))))))) | E63: =IF(B63="","",'WS Import'!D73) | F63: =IF(B63="","",'WS Import'!E73) | H63: =IF(B63="","",IFERROR(INDEX('Unit Cost'!$N$6:$N$21,MATCH(B63,'Unit Cost'!$B$6:$B$21,0)),0)) | I63: =IF(B63="","",F63*IF(H63>0,H63,G63)) | J63: =IF(B63="","",IF(B63="500-7001",1,MarkupFactor)) | K63: =IF(B63="","",IF(B63="500-7001",Mobilization!C11,IF(F63=0,0,IF(H63>0,H63,G63)*J63))) | M63: =IF(B63="","",IF(L63="",K63,L63)) | N63: =IF(B63="","",F63*M63) | O63: =IF(OR(B63="",$N$156=""),"",N63/$N$156) | S63: =IF(OR(B63="",F63=""),"",IF(M63=0,"ZERO PRICE",IF(AND(M63>0,M63<=0.05,Q63>1),"TOKEN PRICE",IF(AND(Q63>0,M63<P63*0.5),"UNDER BAND",IF(AND(R63>0,M63>R63*1.5),"OVER BAND",IF(AND(B63="500-7001",$N$156>0,N63/$N$156>0.1),"MOB > 10%","OK"))))))
A64: =IF('WS Import'!H74="","",ROW()-5) | B64: =IF('WS Import'!H74="","",'WS Import'!H74) | C64: =IF('WS Import'!H74="","",'WS Import'!C74) | D64: =IF(B64="","",IF('WS Import'!F74<>"",'WS Import'!F74,IF(LEFT(B64,3)="500","Mobilization",IF(OR(LEFT(B64,3)="502",LEFT(B64,3)="503",LEFT(B64,3)="505",LEFT(B64,3)="512"),"Traffic control",IF(LEFT(B64,3)="506","SW3P",IF(OR(LEFT(B64,3)="100",LEFT(B64,3)="104",LEFT(B64,3)="105",LEFT(B64,3)="110",LEFT(B64,3)="132"),"Earthwork",IF(LEFT(B64,3)="247","Base",IF(OR(LEFT(B64,3)="310",LEFT(B64,3)="316",LEFT(B64,3)="340",LEFT(B64,3)="341",LEFT(B64,3)="344",LEFT(B64,3)="354",LEFT(B64,4)="3076",LEFT(B64,4)="3077",LEFT(B64,4)="3080"),"Paving",IF(OR(LEFT(B64,3)="400",LEFT(B64,3)="416",LEFT(B64,3)="420",LEFT(B64,3)="422",LEFT(B64,3)="432",LEFT(B64,3)="450",LEFT(B64,3)="462",LEFT(B64,3)="464",LEFT(B64,3)="465",LEFT(B64,3)="466",LEFT(B64,3)="467",LEFT(B64,3)="496"),"Drainage",IF(OR(LEFT(B64,3)="164",LEFT(B64,3)="168",LEFT(B64,3)="169",LEFT(B64,3)="529",LEFT(B64,3)="530",LEFT(B64,3)="531"),"Roadside",IF(OR(LEFT(B64,3)="540",LEFT(B64,3)="542",LEFT(B64,3)="544",LEFT(B64,3)="545"),"Safety",IF(OR(LEFT(B64,3)="644",LEFT(B64,3)="636",LEFT(B64,3)="658"),"Signing",IF(OR(LEFT(B64,3)="666",LEFT(B64,3)="668",LEFT(B64,3)="672",LEFT(B64,3)="677",LEFT(B64,3)="678"),"Markings","Other"))))))))))))) | E64: =IF(B64="","",'WS Import'!D74) | F64: =IF(B64="","",'WS Import'!E74) | H64: =IF(B64="","",IFERROR(INDEX('Unit Cost'!$N$6:$N$21,MATCH(B64,'Unit Cost'!$B$6:$B$21,0)),0)) | I64: =IF(B64="","",F64*IF(H64>0,H64,G64)) | J64: =IF(B64="","",IF(B64="500-7001",1,MarkupFactor)) | K64: =IF(B64="","",IF(B64="500-7001",Mobilization!C11,IF(F64=0,0,IF(H64>0,H64,G64)*J64))) | M64: =IF(B64="","",IF(L64="",K64,L64)) | N64: =IF(B64="","",F64*M64) | O64: =IF(OR(B64="",$N$156=""),"",N64/$N$156) | S64: =IF(OR(B64="",F64=""),"",IF(M64=0,"ZERO PRICE",IF(AND(M64>0,M64<=0.05,Q64>1),"TOKEN PRICE",IF(AND(Q64>0,M64<P64*0.5),"UNDER BAND",IF(AND(R64>0,M64>R64*1.5),"OVER BAND",IF(AND(B64="500-7001",$N$156>0,N64/$N$156>0.1),"MOB > 10%","OK"))))))
A65: =IF('WS Import'!H75="","",ROW()-5) | B65: =IF('WS Import'!H75="","",'WS Import'!H75) | C65: =IF('WS Import'!H75="","",'WS Import'!C75) | D65: =IF(B65="","",IF('WS Import'!F75<>"",'WS Import'!F75,IF(LEFT(B65,3)="500","Mobilization",IF(OR(LEFT(B65,3)="502",LEFT(B65,3)="503",LEFT(B65,3)="505",LEFT(B65,3)="512"),"Traffic control",IF(LEFT(B65,3)="506","SW3P",IF(OR(LEFT(B65,3)="100",LEFT(B65,3)="104",LEFT(B65,3)="105",LEFT(B65,3)="110",LEFT(B65,3)="132"),"Earthwork",IF(LEFT(B65,3)="247","Base",IF(OR(LEFT(B65,3)="310",LEFT(B65,3)="316",LEFT(B65,3)="340",LEFT(B65,3)="341",LEFT(B65,3)="344",LEFT(B65,3)="354",LEFT(B65,4)="3076",LEFT(B65,4)="3077",LEFT(B65,4)="3080"),"Paving",IF(OR(LEFT(B65,3)="400",LEFT(B65,3)="416",LEFT(B65,3)="420",LEFT(B65,3)="422",LEFT(B65,3)="432",LEFT(B65,3)="450",LEFT(B65,3)="462",LEFT(B65,3)="464",LEFT(B65,3)="465",LEFT(B65,3)="466",LEFT(B65,3)="467",LEFT(B65,3)="496"),"Drainage",IF(OR(LEFT(B65,3)="164",LEFT(B65,3)="168",LEFT(B65,3)="169",LEFT(B65,3)="529",LEFT(B65,3)="530",LEFT(B65,3)="531"),"Roadside",IF(OR(LEFT(B65,3)="540",LEFT(B65,3)="542",LEFT(B65,3)="544",LEFT(B65,3)="545"),"Safety",IF(OR(LEFT(B65,3)="644",LEFT(B65,3)="636",LEFT(B65,3)="658"),"Signing",IF(OR(LEFT(B65,3)="666",LEFT(B65,3)="668",LEFT(B65,3)="672",LEFT(B65,3)="677",LEFT(B65,3)="678"),"Markings","Other"))))))))))))) | E65: =IF(B65="","",'WS Import'!D75) | F65: =IF(B65="","",'WS Import'!E75) | H65: =IF(B65="","",IFERROR(INDEX('Unit Cost'!$N$6:$N$21,MATCH(B65,'Unit Cost'!$B$6:$B$21,0)),0)) | I65: =IF(B65="","",F65*IF(H65>0,H65,G65)) | J65: =IF(B65="","",IF(B65="500-7001",1,MarkupFactor)) | K65: =IF(B65="","",IF(B65="500-7001",Mobilization!C11,IF(F65=0,0,IF(H65>0,H65,G65)*J65))) | M65: =IF(B65="","",IF(L65="",K65,L65)) | N65: =IF(B65="","",F65*M65) | O65: =IF(OR(B65="",$N$156=""),"",N65/$N$156) | S65: =IF(OR(B65="",F65=""),"",IF(M65=0,"ZERO PRICE",IF(AND(M65>0,M65<=0.05,Q65>1),"TOKEN PRICE",IF(AND(Q65>0,M65<P65*0.5),"UNDER BAND",IF(AND(R65>0,M65>R65*1.5),"OVER BAND",IF(AND(B65="500-7001",$N$156>0,N65/$N$156>0.1),"MOB > 10%","OK"))))))
A66: =IF('WS Import'!H76="","",ROW()-5) | B66: =IF('WS Import'!H76="","",'WS Import'!H76) | C66: =IF('WS Import'!H76="","",'WS Import'!C76) | D66: =IF(B66="","",IF('WS Import'!F76<>"",'WS Import'!F76,IF(LEFT(B66,3)="500","Mobilization",IF(OR(LEFT(B66,3)="502",LEFT(B66,3)="503",LEFT(B66,3)="505",LEFT(B66,3)="512"),"Traffic control",IF(LEFT(B66,3)="506","SW3P",IF(OR(LEFT(B66,3)="100",LEFT(B66,3)="104",LEFT(B66,3)="105",LEFT(B66,3)="110",LEFT(B66,3)="132"),"Earthwork",IF(LEFT(B66,3)="247","Base",IF(OR(LEFT(B66,3)="310",LEFT(B66,3)="316",LEFT(B66,3)="340",LEFT(B66,3)="341",LEFT(B66,3)="344",LEFT(B66,3)="354",LEFT(B66,4)="3076",LEFT(B66,4)="3077",LEFT(B66,4)="3080"),"Paving",IF(OR(LEFT(B66,3)="400",LEFT(B66,3)="416",LEFT(B66,3)="420",LEFT(B66,3)="422",LEFT(B66,3)="432",LEFT(B66,3)="450",LEFT(B66,3)="462",LEFT(B66,3)="464",LEFT(B66,3)="465",LEFT(B66,3)="466",LEFT(B66,3)="467",LEFT(B66,3)="496"),"Drainage",IF(OR(LEFT(B66,3)="164",LEFT(B66,3)="168",LEFT(B66,3)="169",LEFT(B66,3)="529",LEFT(B66,3)="530",LEFT(B66,3)="531"),"Roadside",IF(OR(LEFT(B66,3)="540",LEFT(B66,3)="542",LEFT(B66,3)="544",LEFT(B66,3)="545"),"Safety",IF(OR(LEFT(B66,3)="644",LEFT(B66,3)="636",LEFT(B66,3)="658"),"Signing",IF(OR(LEFT(B66,3)="666",LEFT(B66,3)="668",LEFT(B66,3)="672",LEFT(B66,3)="677",LEFT(B66,3)="678"),"Markings","Other"))))))))))))) | E66: =IF(B66="","",'WS Import'!D76) | F66: =IF(B66="","",'WS Import'!E76) | H66: =IF(B66="","",IFERROR(INDEX('Unit Cost'!$N$6:$N$21,MATCH(B66,'Unit Cost'!$B$6:$B$21,0)),0)) | I66: =IF(B66="","",F66*IF(H66>0,H66,G66)) | J66: =IF(B66="","",IF(B66="500-7001",1,MarkupFactor)) | K66: =IF(B66="","",IF(B66="500-7001",Mobilization!C11,IF(F66=0,0,IF(H66>0,H66,G66)*J66))) | M66: =IF(B66="","",IF(L66="",K66,L66)) | N66: =IF(B66="","",F66*M66) | O66: =IF(OR(B66="",$N$156=""),"",N66/$N$156) | S66: =IF(OR(B66="",F66=""),"",IF(M66=0,"ZERO PRICE",IF(AND(M66>0,M66<=0.05,Q66>1),"TOKEN PRICE",IF(AND(Q66>0,M66<P66*0.5),"UNDER BAND",IF(AND(R66>0,M66>R66*1.5),"OVER BAND",IF(AND(B66="500-7001",$N$156>0,N66/$N$156>0.1),"MOB > 10%","OK"))))))
A67: =IF('WS Import'!H77="","",ROW()-5) | B67: =IF('WS Import'!H77="","",'WS Import'!H77) | C67: =IF('WS Import'!H77="","",'WS Import'!C77) | D67: =IF(B67="","",IF('WS Import'!F77<>"",'WS Import'!F77,IF(LEFT(B67,3)="500","Mobilization",IF(OR(LEFT(B67,3)="502",LEFT(B67,3)="503",LEFT(B67,3)="505",LEFT(B67,3)="512"),"Traffic control",IF(LEFT(B67,3)="506","SW3P",IF(OR(LEFT(B67,3)="100",LEFT(B67,3)="104",LEFT(B67,3)="105",LEFT(B67,3)="110",LEFT(B67,3)="132"),"Earthwork",IF(LEFT(B67,3)="247","Base",IF(OR(LEFT(B67,3)="310",LEFT(B67,3)="316",LEFT(B67,3)="340",LEFT(B67,3)="341",LEFT(B67,3)="344",LEFT(B67,3)="354",LEFT(B67,4)="3076",LEFT(B67,4)="3077",LEFT(B67,4)="3080"),"Paving",IF(OR(LEFT(B67,3)="400",LEFT(B67,3)="416",LEFT(B67,3)="420",LEFT(B67,3)="422",LEFT(B67,3)="432",LEFT(B67,3)="450",LEFT(B67,3)="462",LEFT(B67,3)="464",LEFT(B67,3)="465",LEFT(B67,3)="466",LEFT(B67,3)="467",LEFT(B67,3)="496"),"Drainage",IF(OR(LEFT(B67,3)="164",LEFT(B67,3)="168",LEFT(B67,3)="169",LEFT(B67,3)="529",LEFT(B67,3)="530",LEFT(B67,3)="531"),"Roadside",IF(OR(LEFT(B67,3)="540",LEFT(B67,3)="542",LEFT(B67,3)="544",LEFT(B67,3)="545"),"Safety",IF(OR(LEFT(B67,3)="644",LEFT(B67,3)="636",LEFT(B67,3)="658"),"Signing",IF(OR(LEFT(B67,3)="666",LEFT(B67,3)="668",LEFT(B67,3)="672",LEFT(B67,3)="677",LEFT(B67,3)="678"),"Markings","Other"))))))))))))) | E67: =IF(B67="","",'WS Import'!D77) | F67: =IF(B67="","",'WS Import'!E77) | H67: =IF(B67="","",IFERROR(INDEX('Unit Cost'!$N$6:$N$21,MATCH(B67,'Unit Cost'!$B$6:$B$21,0)),0)) | I67: =IF(B67="","",F67*IF(H67>0,H67,G67)) | J67: =IF(B67="","",IF(B67="500-7001",1,MarkupFactor)) | K67: =IF(B67="","",IF(B67="500-7001",Mobilization!C11,IF(F67=0,0,IF(H67>0,H67,G67)*J67))) | M67: =IF(B67="","",IF(L67="",K67,L67)) | N67: =IF(B67="","",F67*M67) | O67: =IF(OR(B67="",$N$156=""),"",N67/$N$156) | S67: =IF(OR(B67="",F67=""),"",IF(M67=0,"ZERO PRICE",IF(AND(M67>0,M67<=0.05,Q67>1),"TOKEN PRICE",IF(AND(Q67>0,M67<P67*0.5),"UNDER BAND",IF(AND(R67>0,M67>R67*1.5),"OVER BAND",IF(AND(B67="500-7001",$N$156>0,N67/$N$156>0.1),"MOB > 10%","OK"))))))
A68: =IF('WS Import'!H78="","",ROW()-5) | B68: =IF('WS Import'!H78="","",'WS Import'!H78) | C68: =IF('WS Import'!H78="","",'WS Import'!C78) | D68: =IF(B68="","",IF('WS Import'!F78<>"",'WS Import'!F78,IF(LEFT(B68,3)="500","Mobilization",IF(OR(LEFT(B68,3)="502",LEFT(B68,3)="503",LEFT(B68,3)="505",LEFT(B68,3)="512"),"Traffic control",IF(LEFT(B68,3)="506","SW3P",IF(OR(LEFT(B68,3)="100",LEFT(B68,3)="104",LEFT(B68,3)="105",LEFT(B68,3)="110",LEFT(B68,3)="132"),"Earthwork",IF(LEFT(B68,3)="247","Base",IF(OR(LEFT(B68,3)="310",LEFT(B68,3)="316",LEFT(B68,3)="340",LEFT(B68,3)="341",LEFT(B68,3)="344",LEFT(B68,3)="354",LEFT(B68,4)="3076",LEFT(B68,4)="3077",LEFT(B68,4)="3080"),"Paving",IF(OR(LEFT(B68,3)="400",LEFT(B68,3)="416",LEFT(B68,3)="420",LEFT(B68,3)="422",LEFT(B68,3)="432",LEFT(B68,3)="450",LEFT(B68,3)="462",LEFT(B68,3)="464",LEFT(B68,3)="465",LEFT(B68,3)="466",LEFT(B68,3)="467",LEFT(B68,3)="496"),"Drainage",IF(OR(LEFT(B68,3)="164",LEFT(B68,3)="168",LEFT(B68,3)="169",LEFT(B68,3)="529",LEFT(B68,3)="530",LEFT(B68,3)="531"),"Roadside",IF(OR(LEFT(B68,3)="540",LEFT(B68,3)="542",LEFT(B68,3)="544",LEFT(B68,3)="545"),"Safety",IF(OR(LEFT(B68,3)="644",LEFT(B68,3)="636",LEFT(B68,3)="658"),"Signing",IF(OR(LEFT(B68,3)="666",LEFT(B68,3)="668",LEFT(B68,3)="672",LEFT(B68,3)="677",LEFT(B68,3)="678"),"Markings","Other"))))))))))))) | E68: =IF(B68="","",'WS Import'!D78) | F68: =IF(B68="","",'WS Import'!E78) | H68: =IF(B68="","",IFERROR(INDEX('Unit Cost'!$N$6:$N$21,MATCH(B68,'Unit Cost'!$B$6:$B$21,0)),0)) | I68: =IF(B68="","",F68*IF(H68>0,H68,G68)) | J68: =IF(B68="","",IF(B68="500-7001",1,MarkupFactor)) | K68: =IF(B68="","",IF(B68="500-7001",Mobilization!C11,IF(F68=0,0,IF(H68>0,H68,G68)*J68))) | M68: =IF(B68="","",IF(L68="",K68,L68)) | N68: =IF(B68="","",F68*M68) | O68: =IF(OR(B68="",$N$156=""),"",N68/$N$156) | S68: =IF(OR(B68="",F68=""),"",IF(M68=0,"ZERO PRICE",IF(AND(M68>0,M68<=0.05,Q68>1),"TOKEN PRICE",IF(AND(Q68>0,M68<P68*0.5),"UNDER BAND",IF(AND(R68>0,M68>R68*1.5),"OVER BAND",IF(AND(B68="500-7001",$N$156>0,N68/$N$156>0.1),"MOB > 10%","OK"))))))
A69: =IF('WS Import'!H79="","",ROW()-5) | B69: =IF('WS Import'!H79="","",'WS Import'!H79) | C69: =IF('WS Import'!H79="","",'WS Import'!C79) | D69: =IF(B69="","",IF('WS Import'!F79<>"",'WS Import'!F79,IF(LEFT(B69,3)="500","Mobilization",IF(OR(LEFT(B69,3)="502",LEFT(B69,3)="503",LEFT(B69,3)="505",LEFT(B69,3)="512"),"Traffic control",IF(LEFT(B69,3)="506","SW3P",IF(OR(LEFT(B69,3)="100",LEFT(B69,3)="104",LEFT(B69,3)="105",LEFT(B69,3)="110",LEFT(B69,3)="132"),"Earthwork",IF(LEFT(B69,3)="247","Base",IF(OR(LEFT(B69,3)="310",LEFT(B69,3)="316",LEFT(B69,3)="340",LEFT(B69,3)="341",LEFT(B69,3)="344",LEFT(B69,3)="354",LEFT(B69,4)="3076",LEFT(B69,4)="3077",LEFT(B69,4)="3080"),"Paving",IF(OR(LEFT(B69,3)="400",LEFT(B69,3)="416",LEFT(B69,3)="420",LEFT(B69,3)="422",LEFT(B69,3)="432",LEFT(B69,3)="450",LEFT(B69,3)="462",LEFT(B69,3)="464",LEFT(B69,3)="465",LEFT(B69,3)="466",LEFT(B69,3)="467",LEFT(B69,3)="496"),"Drainage",IF(OR(LEFT(B69,3)="164",LEFT(B69,3)="168",LEFT(B69,3)="169",LEFT(B69,3)="529",LEFT(B69,3)="530",LEFT(B69,3)="531"),"Roadside",IF(OR(LEFT(B69,3)="540",LEFT(B69,3)="542",LEFT(B69,3)="544",LEFT(B69,3)="545"),"Safety",IF(OR(LEFT(B69,3)="644",LEFT(B69,3)="636",LEFT(B69,3)="658"),"Signing",IF(OR(LEFT(B69,3)="666",LEFT(B69,3)="668",LEFT(B69,3)="672",LEFT(B69,3)="677",LEFT(B69,3)="678"),"Markings","Other"))))))))))))) | E69: =IF(B69="","",'WS Import'!D79) | F69: =IF(B69="","",'WS Import'!E79) | H69: =IF(B69="","",IFERROR(INDEX('Unit Cost'!$N$6:$N$21,MATCH(B69,'Unit Cost'!$B$6:$B$21,0)),0)) | I69: =IF(B69="","",F69*IF(H69>0,H69,G69)) | J69: =IF(B69="","",IF(B69="500-7001",1,MarkupFactor)) | K69: =IF(B69="","",IF(B69="500-7001",Mobilization!C11,IF(F69=0,0,IF(H69>0,H69,G69)*J69))) | M69: =IF(B69="","",IF(L69="",K69,L69)) | N69: =IF(B69="","",F69*M69) | O69: =IF(OR(B69="",$N$156=""),"",N69/$N$156) | S69: =IF(OR(B69="",F69=""),"",IF(M69=0,"ZERO PRICE",IF(AND(M69>0,M69<=0.05,Q69>1),"TOKEN PRICE",IF(AND(Q69>0,M69<P69*0.5),"UNDER BAND",IF(AND(R69>0,M69>R69*1.5),"OVER BAND",IF(AND(B69="500-7001",$N$156>0,N69/$N$156>0.1),"MOB > 10%","OK"))))))
A70: =IF('WS Import'!H80="","",ROW()-5) | B70: =IF('WS Import'!H80="","",'WS Import'!H80) | C70: =IF('WS Import'!H80="","",'WS Import'!C80) | D70: =IF(B70="","",IF('WS Import'!F80<>"",'WS Import'!F80,IF(LEFT(B70,3)="500","Mobilization",IF(OR(LEFT(B70,3)="502",LEFT(B70,3)="503",LEFT(B70,3)="505",LEFT(B70,3)="512"),"Traffic control",IF(LEFT(B70,3)="506","SW3P",IF(OR(LEFT(B70,3)="100",LEFT(B70,3)="104",LEFT(B70,3)="105",LEFT(B70,3)="110",LEFT(B70,3)="132"),"Earthwork",IF(LEFT(B70,3)="247","Base",IF(OR(LEFT(B70,3)="310",LEFT(B70,3)="316",LEFT(B70,3)="340",LEFT(B70,3)="341",LEFT(B70,3)="344",LEFT(B70,3)="354",LEFT(B70,4)="3076",LEFT(B70,4)="3077",LEFT(B70,4)="3080"),"Paving",IF(OR(LEFT(B70,3)="400",LEFT(B70,3)="416",LEFT(B70,3)="420",LEFT(B70,3)="422",LEFT(B70,3)="432",LEFT(B70,3)="450",LEFT(B70,3)="462",LEFT(B70,3)="464",LEFT(B70,3)="465",LEFT(B70,3)="466",LEFT(B70,3)="467",LEFT(B70,3)="496"),"Drainage",IF(OR(LEFT(B70,3)="164",LEFT(B70,3)="168",LEFT(B70,3)="169",LEFT(B70,3)="529",LEFT(B70,3)="530",LEFT(B70,3)="531"),"Roadside",IF(OR(LEFT(B70,3)="540",LEFT(B70,3)="542",LEFT(B70,3)="544",LEFT(B70,3)="545"),"Safety",IF(OR(LEFT(B70,3)="644",LEFT(B70,3)="636",LEFT(B70,3)="658"),"Signing",IF(OR(LEFT(B70,3)="666",LEFT(B70,3)="668",LEFT(B70,3)="672",LEFT(B70,3)="677",LEFT(B70,3)="678"),"Markings","Other"))))))))))))) | E70: =IF(B70="","",'WS Import'!D80) | F70: =IF(B70="","",'WS Import'!E80) | H70: =IF(B70="","",IFERROR(INDEX('Unit Cost'!$N$6:$N$21,MATCH(B70,'Unit Cost'!$B$6:$B$21,0)),0)) | I70: =IF(B70="","",F70*IF(H70>0,H70,G70)) | J70: =IF(B70="","",IF(B70="500-7001",1,MarkupFactor)) | K70: =IF(B70="","",IF(B70="500-7001",Mobilization!C11,IF(F70=0,0,IF(H70>0,H70,G70)*J70))) | M70: =IF(B70="","",IF(L70="",K70,L70)) | N70: =IF(B70="","",F70*M70) | O70: =IF(OR(B70="",$N$156=""),"",N70/$N$156) | S70: =IF(OR(B70="",F70=""),"",IF(M70=0,"ZERO PRICE",IF(AND(M70>0,M70<=0.05,Q70>1),"TOKEN PRICE",IF(AND(Q70>0,M70<P70*0.5),"UNDER BAND",IF(AND(R70>0,M70>R70*1.5),"OVER BAND",IF(AND(B70="500-7001",$N$156>0,N70/$N$156>0.1),"MOB > 10%","OK"))))))
A71: =IF('WS Import'!H81="","",ROW()-5) | B71: =IF('WS Import'!H81="","",'WS Import'!H81) | C71: =IF('WS Import'!H81="","",'WS Import'!C81) | D71: =IF(B71="","",IF('WS Import'!F81<>"",'WS Import'!F81,IF(LEFT(B71,3)="500","Mobilization",IF(OR(LEFT(B71,3)="502",LEFT(B71,3)="503",LEFT(B71,3)="505",LEFT(B71,3)="512"),"Traffic control",IF(LEFT(B71,3)="506","SW3P",IF(OR(LEFT(B71,3)="100",LEFT(B71,3)="104",LEFT(B71,3)="105",LEFT(B71,3)="110",LEFT(B71,3)="132"),"Earthwork",IF(LEFT(B71,3)="247","Base",IF(OR(LEFT(B71,3)="310",LEFT(B71,3)="316",LEFT(B71,3)="340",LEFT(B71,3)="341",LEFT(B71,3)="344",LEFT(B71,3)="354",LEFT(B71,4)="3076",LEFT(B71,4)="3077",LEFT(B71,4)="3080"),"Paving",IF(OR(LEFT(B71,3)="400",LEFT(B71,3)="416",LEFT(B71,3)="420",LEFT(B71,3)="422",LEFT(B71,3)="432",LEFT(B71,3)="450",LEFT(B71,3)="462",LEFT(B71,3)="464",LEFT(B71,3)="465",LEFT(B71,3)="466",LEFT(B71,3)="467",LEFT(B71,3)="496"),"Drainage",IF(OR(LEFT(B71,3)="164",LEFT(B71,3)="168",LEFT(B71,3)="169",LEFT(B71,3)="529",LEFT(B71,3)="530",LEFT(B71,3)="531"),"Roadside",IF(OR(LEFT(B71,3)="540",LEFT(B71,3)="542",LEFT(B71,3)="544",LEFT(B71,3)="545"),"Safety",IF(OR(LEFT(B71,3)="644",LEFT(B71,3)="636",LEFT(B71,3)="658"),"Signing",IF(OR(LEFT(B71,3)="666",LEFT(B71,3)="668",LEFT(B71,3)="672",LEFT(B71,3)="677",LEFT(B71,3)="678"),"Markings","Other"))))))))))))) | E71: =IF(B71="","",'WS Import'!D81) | F71: =IF(B71="","",'WS Import'!E81) | H71: =IF(B71="","",IFERROR(INDEX('Unit Cost'!$N$6:$N$21,MATCH(B71,'Unit Cost'!$B$6:$B$21,0)),0)) | I71: =IF(B71="","",F71*IF(H71>0,H71,G71)) | J71: =IF(B71="","",IF(B71="500-7001",1,MarkupFactor)) | K71: =IF(B71="","",IF(B71="500-7001",Mobilization!C11,IF(F71=0,0,IF(H71>0,H71,G71)*J71))) | M71: =IF(B71="","",IF(L71="",K71,L71)) | N71: =IF(B71="","",F71*M71) | O71: =IF(OR(B71="",$N$156=""),"",N71/$N$156) | S71: =IF(OR(B71="",F71=""),"",IF(M71=0,"ZERO PRICE",IF(AND(M71>0,M71<=0.05,Q71>1),"TOKEN PRICE",IF(AND(Q71>0,M71<P71*0.5),"UNDER BAND",IF(AND(R71>0,M71>R71*1.5),"OVER BAND",IF(AND(B71="500-7001",$N$156>0,N71/$N$156>0.1),"MOB > 10%","OK"))))))
A72: =IF('WS Import'!H82="","",ROW()-5) | B72: =IF('WS Import'!H82="","",'WS Import'!H82) | C72: =IF('WS Import'!H82="","",'WS Import'!C82) | D72: =IF(B72="","",IF('WS Import'!F82<>"",'WS Import'!F82,IF(LEFT(B72,3)="500","Mobilization",IF(OR(LEFT(B72,3)="502",LEFT(B72,3)="503",LEFT(B72,3)="505",LEFT(B72,3)="512"),"Traffic control",IF(LEFT(B72,3)="506","SW3P",IF(OR(LEFT(B72,3)="100",LEFT(B72,3)="104",LEFT(B72,3)="105",LEFT(B72,3)="110",LEFT(B72,3)="132"),"Earthwork",IF(LEFT(B72,3)="247","Base",IF(OR(LEFT(B72,3)="310",LEFT(B72,3)="316",LEFT(B72,3)="340",LEFT(B72,3)="341",LEFT(B72,3)="344",LEFT(B72,3)="354",LEFT(B72,4)="3076",LEFT(B72,4)="3077",LEFT(B72,4)="3080"),"Paving",IF(OR(LEFT(B72,3)="400",LEFT(B72,3)="416",LEFT(B72,3)="420",LEFT(B72,3)="422",LEFT(B72,3)="432",LEFT(B72,3)="450",LEFT(B72,3)="462",LEFT(B72,3)="464",LEFT(B72,3)="465",LEFT(B72,3)="466",LEFT(B72,3)="467",LEFT(B72,3)="496"),"Drainage",IF(OR(LEFT(B72,3)="164",LEFT(B72,3)="168",LEFT(B72,3)="169",LEFT(B72,3)="529",LEFT(B72,3)="530",LEFT(B72,3)="531"),"Roadside",IF(OR(LEFT(B72,3)="540",LEFT(B72,3)="542",LEFT(B72,3)="544",LEFT(B72,3)="545"),"Safety",IF(OR(LEFT(B72,3)="644",LEFT(B72,3)="636",LEFT(B72,3)="658"),"Signing",IF(OR(LEFT(B72,3)="666",LEFT(B72,3)="668",LEFT(B72,3)="672",LEFT(B72,3)="677",LEFT(B72,3)="678"),"Markings","Other"))))))))))))) | E72: =IF(B72="","",'WS Import'!D82) | F72: =IF(B72="","",'WS Import'!E82) | H72: =IF(B72="","",IFERROR(INDEX('Unit Cost'!$N$6:$N$21,MATCH(B72,'Unit Cost'!$B$6:$B$21,0)),0)) | I72: =IF(B72="","",F72*IF(H72>0,H72,G72)) | J72: =IF(B72="","",IF(B72="500-7001",1,MarkupFactor)) | K72: =IF(B72="","",IF(B72="500-7001",Mobilization!C11,IF(F72=0,0,IF(H72>0,H72,G72)*J72))) | M72: =IF(B72="","",IF(L72="",K72,L72)) | N72: =IF(B72="","",F72*M72) | O72: =IF(OR(B72="",$N$156=""),"",N72/$N$156) | S72: =IF(OR(B72="",F72=""),"",IF(M72=0,"ZERO PRICE",IF(AND(M72>0,M72<=0.05,Q72>1),"TOKEN PRICE",IF(AND(Q72>0,M72<P72*0.5),"UNDER BAND",IF(AND(R72>0,M72>R72*1.5),"OVER BAND",IF(AND(B72="500-7001",$N$156>0,N72/$N$156>0.1),"MOB > 10%","OK"))))))
A73: =IF('WS Import'!H83="","",ROW()-5) | B73: =IF('WS Import'!H83="","",'WS Import'!H83) | C73: =IF('WS Import'!H83="","",'WS Import'!C83) | D73: =IF(B73="","",IF('WS Import'!F83<>"",'WS Import'!F83,IF(LEFT(B73,3)="500","Mobilization",IF(OR(LEFT(B73,3)="502",LEFT(B73,3)="503",LEFT(B73,3)="505",LEFT(B73,3)="512"),"Traffic control",IF(LEFT(B73,3)="506","SW3P",IF(OR(LEFT(B73,3)="100",LEFT(B73,3)="104",LEFT(B73,3)="105",LEFT(B73,3)="110",LEFT(B73,3)="132"),"Earthwork",IF(LEFT(B73,3)="247","Base",IF(OR(LEFT(B73,3)="310",LEFT(B73,3)="316",LEFT(B73,3)="340",LEFT(B73,3)="341",LEFT(B73,3)="344",LEFT(B73,3)="354",LEFT(B73,4)="3076",LEFT(B73,4)="3077",LEFT(B73,4)="3080"),"Paving",IF(OR(LEFT(B73,3)="400",LEFT(B73,3)="416",LEFT(B73,3)="420",LEFT(B73,3)="422",LEFT(B73,3)="432",LEFT(B73,3)="450",LEFT(B73,3)="462",LEFT(B73,3)="464",LEFT(B73,3)="465",LEFT(B73,3)="466",LEFT(B73,3)="467",LEFT(B73,3)="496"),"Drainage",IF(OR(LEFT(B73,3)="164",LEFT(B73,3)="168",LEFT(B73,3)="169",LEFT(B73,3)="529",LEFT(B73,3)="530",LEFT(B73,3)="531"),"Roadside",IF(OR(LEFT(B73,3)="540",LEFT(B73,3)="542",LEFT(B73,3)="544",LEFT(B73,3)="545"),"Safety",IF(OR(LEFT(B73,3)="644",LEFT(B73,3)="636",LEFT(B73,3)="658"),"Signing",IF(OR(LEFT(B73,3)="666",LEFT(B73,3)="668",LEFT(B73,3)="672",LEFT(B73,3)="677",LEFT(B73,3)="678"),"Markings","Other"))))))))))))) | E73: =IF(B73="","",'WS Import'!D83) | F73: =IF(B73="","",'WS Import'!E83) | H73: =IF(B73="","",IFERROR(INDEX('Unit Cost'!$N$6:$N$21,MATCH(B73,'Unit Cost'!$B$6:$B$21,0)),0)) | I73: =IF(B73="","",F73*IF(H73>0,H73,G73)) | J73: =IF(B73="","",IF(B73="500-7001",1,MarkupFactor)) | K73: =IF(B73="","",IF(B73="500-7001",Mobilization!C11,IF(F73=0,0,IF(H73>0,H73,G73)*J73))) | M73: =IF(B73="","",IF(L73="",K73,L73)) | N73: =IF(B73="","",F73*M73) | O73: =IF(OR(B73="",$N$156=""),"",N73/$N$156) | S73: =IF(OR(B73="",F73=""),"",IF(M73=0,"ZERO PRICE",IF(AND(M73>0,M73<=0.05,Q73>1),"TOKEN PRICE",IF(AND(Q73>0,M73<P73*0.5),"UNDER BAND",IF(AND(R73>0,M73>R73*1.5),"OVER BAND",IF(AND(B73="500-7001",$N$156>0,N73/$N$156>0.1),"MOB > 10%","OK"))))))
A74: =IF('WS Import'!H84="","",ROW()-5) | B74: =IF('WS Import'!H84="","",'WS Import'!H84) | C74: =IF('WS Import'!H84="","",'WS Import'!C84) | D74: =IF(B74="","",IF('WS Import'!F84<>"",'WS Import'!F84,IF(LEFT(B74,3)="500","Mobilization",IF(OR(LEFT(B74,3)="502",LEFT(B74,3)="503",LEFT(B74,3)="505",LEFT(B74,3)="512"),"Traffic control",IF(LEFT(B74,3)="506","SW3P",IF(OR(LEFT(B74,3)="100",LEFT(B74,3)="104",LEFT(B74,3)="105",LEFT(B74,3)="110",LEFT(B74,3)="132"),"Earthwork",IF(LEFT(B74,3)="247","Base",IF(OR(LEFT(B74,3)="310",LEFT(B74,3)="316",LEFT(B74,3)="340",LEFT(B74,3)="341",LEFT(B74,3)="344",LEFT(B74,3)="354",LEFT(B74,4)="3076",LEFT(B74,4)="3077",LEFT(B74,4)="3080"),"Paving",IF(OR(LEFT(B74,3)="400",LEFT(B74,3)="416",LEFT(B74,3)="420",LEFT(B74,3)="422",LEFT(B74,3)="432",LEFT(B74,3)="450",LEFT(B74,3)="462",LEFT(B74,3)="464",LEFT(B74,3)="465",LEFT(B74,3)="466",LEFT(B74,3)="467",LEFT(B74,3)="496"),"Drainage",IF(OR(LEFT(B74,3)="164",LEFT(B74,3)="168",LEFT(B74,3)="169",LEFT(B74,3)="529",LEFT(B74,3)="530",LEFT(B74,3)="531"),"Roadside",IF(OR(LEFT(B74,3)="540",LEFT(B74,3)="542",LEFT(B74,3)="544",LEFT(B74,3)="545"),"Safety",IF(OR(LEFT(B74,3)="644",LEFT(B74,3)="636",LEFT(B74,3)="658"),"Signing",IF(OR(LEFT(B74,3)="666",LEFT(B74,3)="668",LEFT(B74,3)="672",LEFT(B74,3)="677",LEFT(B74,3)="678"),"Markings","Other"))))))))))))) | E74: =IF(B74="","",'WS Import'!D84) | F74: =IF(B74="","",'WS Import'!E84) | H74: =IF(B74="","",IFERROR(INDEX('Unit Cost'!$N$6:$N$21,MATCH(B74,'Unit Cost'!$B$6:$B$21,0)),0)) | I74: =IF(B74="","",F74*IF(H74>0,H74,G74)) | J74: =IF(B74="","",IF(B74="500-7001",1,MarkupFactor)) | K74: =IF(B74="","",IF(B74="500-7001",Mobilization!C11,IF(F74=0,0,IF(H74>0,H74,G74)*J74))) | M74: =IF(B74="","",IF(L74="",K74,L74)) | N74: =IF(B74="","",F74*M74) | O74: =IF(OR(B74="",$N$156=""),"",N74/$N$156) | S74: =IF(OR(B74="",F74=""),"",IF(M74=0,"ZERO PRICE",IF(AND(M74>0,M74<=0.05,Q74>1),"TOKEN PRICE",IF(AND(Q74>0,M74<P74*0.5),"UNDER BAND",IF(AND(R74>0,M74>R74*1.5),"OVER BAND",IF(AND(B74="500-7001",$N$156>0,N74/$N$156>0.1),"MOB > 10%","OK"))))))
A75: =IF('WS Import'!H85="","",ROW()-5) | B75: =IF('WS Import'!H85="","",'WS Import'!H85) | C75: =IF('WS Import'!H85="","",'WS Import'!C85) | D75: =IF(B75="","",IF('WS Import'!F85<>"",'WS Import'!F85,IF(LEFT(B75,3)="500","Mobilization",IF(OR(LEFT(B75,3)="502",LEFT(B75,3)="503",LEFT(B75,3)="505",LEFT(B75,3)="512"),"Traffic control",IF(LEFT(B75,3)="506","SW3P",IF(OR(LEFT(B75,3)="100",LEFT(B75,3)="104",LEFT(B75,3)="105",LEFT(B75,3)="110",LEFT(B75,3)="132"),"Earthwork",IF(LEFT(B75,3)="247","Base",IF(OR(LEFT(B75,3)="310",LEFT(B75,3)="316",LEFT(B75,3)="340",LEFT(B75,3)="341",LEFT(B75,3)="344",LEFT(B75,3)="354",LEFT(B75,4)="3076",LEFT(B75,4)="3077",LEFT(B75,4)="3080"),"Paving",IF(OR(LEFT(B75,3)="400",LEFT(B75,3)="416",LEFT(B75,3)="420",LEFT(B75,3)="422",LEFT(B75,3)="432",LEFT(B75,3)="450",LEFT(B75,3)="462",LEFT(B75,3)="464",LEFT(B75,3)="465",LEFT(B75,3)="466",LEFT(B75,3)="467",LEFT(B75,3)="496"),"Drainage",IF(OR(LEFT(B75,3)="164",LEFT(B75,3)="168",LEFT(B75,3)="169",LEFT(B75,3)="529",LEFT(B75,3)="530",LEFT(B75,3)="531"),"Roadside",IF(OR(LEFT(B75,3)="540",LEFT(B75,3)="542",LEFT(B75,3)="544",LEFT(B75,3)="545"),"Safety",IF(OR(LEFT(B75,3)="644",LEFT(B75,3)="636",LEFT(B75,3)="658"),"Signing",IF(OR(LEFT(B75,3)="666",LEFT(B75,3)="668",LEFT(B75,3)="672",LEFT(B75,3)="677",LEFT(B75,3)="678"),"Markings","Other"))))))))))))) | E75: =IF(B75="","",'WS Import'!D85) | F75: =IF(B75="","",'WS Import'!E85) | H75: =IF(B75="","",IFERROR(INDEX('Unit Cost'!$N$6:$N$21,MATCH(B75,'Unit Cost'!$B$6:$B$21,0)),0)) | I75: =IF(B75="","",F75*IF(H75>0,H75,G75)) | J75: =IF(B75="","",IF(B75="500-7001",1,MarkupFactor)) | K75: =IF(B75="","",IF(B75="500-7001",Mobilization!C11,IF(F75=0,0,IF(H75>0,H75,G75)*J75))) | M75: =IF(B75="","",IF(L75="",K75,L75)) | N75: =IF(B75="","",F75*M75) | O75: =IF(OR(B75="",$N$156=""),"",N75/$N$156) | S75: =IF(OR(B75="",F75=""),"",IF(M75=0,"ZERO PRICE",IF(AND(M75>0,M75<=0.05,Q75>1),"TOKEN PRICE",IF(AND(Q75>0,M75<P75*0.5),"UNDER BAND",IF(AND(R75>0,M75>R75*1.5),"OVER BAND",IF(AND(B75="500-7001",$N$156>0,N75/$N$156>0.1),"MOB > 10%","OK"))))))
A76: =IF('WS Import'!H86="","",ROW()-5) | B76: =IF('WS Import'!H86="","",'WS Import'!H86) | C76: =IF('WS Import'!H86="","",'WS Import'!C86) | D76: =IF(B76="","",IF('WS Import'!F86<>"",'WS Import'!F86,IF(LEFT(B76,3)="500","Mobilization",IF(OR(LEFT(B76,3)="502",LEFT(B76,3)="503",LEFT(B76,3)="505",LEFT(B76,3)="512"),"Traffic control",IF(LEFT(B76,3)="506","SW3P",IF(OR(LEFT(B76,3)="100",LEFT(B76,3)="104",LEFT(B76,3)="105",LEFT(B76,3)="110",LEFT(B76,3)="132"),"Earthwork",IF(LEFT(B76,3)="247","Base",IF(OR(LEFT(B76,3)="310",LEFT(B76,3)="316",LEFT(B76,3)="340",LEFT(B76,3)="341",LEFT(B76,3)="344",LEFT(B76,3)="354",LEFT(B76,4)="3076",LEFT(B76,4)="3077",LEFT(B76,4)="3080"),"Paving",IF(OR(LEFT(B76,3)="400",LEFT(B76,3)="416",LEFT(B76,3)="420",LEFT(B76,3)="422",LEFT(B76,3)="432",LEFT(B76,3)="450",LEFT(B76,3)="462",LEFT(B76,3)="464",LEFT(B76,3)="465",LEFT(B76,3)="466",LEFT(B76,3)="467",LEFT(B76,3)="496"),"Drainage",IF(OR(LEFT(B76,3)="164",LEFT(B76,3)="168",LEFT(B76,3)="169",LEFT(B76,3)="529",LEFT(B76,3)="530",LEFT(B76,3)="531"),"Roadside",IF(OR(LEFT(B76,3)="540",LEFT(B76,3)="542",LEFT(B76,3)="544",LEFT(B76,3)="545"),"Safety",IF(OR(LEFT(B76,3)="644",LEFT(B76,3)="636",LEFT(B76,3)="658"),"Signing",IF(OR(LEFT(B76,3)="666",LEFT(B76,3)="668",LEFT(B76,3)="672",LEFT(B76,3)="677",LEFT(B76,3)="678"),"Markings","Other"))))))))))))) | E76: =IF(B76="","",'WS Import'!D86) | F76: =IF(B76="","",'WS Import'!E86) | H76: =IF(B76="","",IFERROR(INDEX('Unit Cost'!$N$6:$N$21,MATCH(B76,'Unit Cost'!$B$6:$B$21,0)),0)) | I76: =IF(B76="","",F76*IF(H76>0,H76,G76)) | J76: =IF(B76="","",IF(B76="500-7001",1,MarkupFactor)) | K76: =IF(B76="","",IF(B76="500-7001",Mobilization!C11,IF(F76=0,0,IF(H76>0,H76,G76)*J76))) | M76: =IF(B76="","",IF(L76="",K76,L76)) | N76: =IF(B76="","",F76*M76) | O76: =IF(OR(B76="",$N$156=""),"",N76/$N$156) | S76: =IF(OR(B76="",F76=""),"",IF(M76=0,"ZERO PRICE",IF(AND(M76>0,M76<=0.05,Q76>1),"TOKEN PRICE",IF(AND(Q76>0,M76<P76*0.5),"UNDER BAND",IF(AND(R76>0,M76>R76*1.5),"OVER BAND",IF(AND(B76="500-7001",$N$156>0,N76/$N$156>0.1),"MOB > 10%","OK"))))))
A77: =IF('WS Import'!H87="","",ROW()-5) | B77: =IF('WS Import'!H87="","",'WS Import'!H87) | C77: =IF('WS Import'!H87="","",'WS Import'!C87) | D77: =IF(B77="","",IF('WS Import'!F87<>"",'WS Import'!F87,IF(LEFT(B77,3)="500","Mobilization",IF(OR(LEFT(B77,3)="502",LEFT(B77,3)="503",LEFT(B77,3)="505",LEFT(B77,3)="512"),"Traffic control",IF(LEFT(B77,3)="506","SW3P",IF(OR(LEFT(B77,3)="100",LEFT(B77,3)="104",LEFT(B77,3)="105",LEFT(B77,3)="110",LEFT(B77,3)="132"),"Earthwork",IF(LEFT(B77,3)="247","Base",IF(OR(LEFT(B77,3)="310",LEFT(B77,3)="316",LEFT(B77,3)="340",LEFT(B77,3)="341",LEFT(B77,3)="344",LEFT(B77,3)="354",LEFT(B77,4)="3076",LEFT(B77,4)="3077",LEFT(B77,4)="3080"),"Paving",IF(OR(LEFT(B77,3)="400",LEFT(B77,3)="416",LEFT(B77,3)="420",LEFT(B77,3)="422",LEFT(B77,3)="432",LEFT(B77,3)="450",LEFT(B77,3)="462",LEFT(B77,3)="464",LEFT(B77,3)="465",LEFT(B77,3)="466",LEFT(B77,3)="467",LEFT(B77,3)="496"),"Drainage",IF(OR(LEFT(B77,3)="164",LEFT(B77,3)="168",LEFT(B77,3)="169",LEFT(B77,3)="529",LEFT(B77,3)="530",LEFT(B77,3)="531"),"Roadside",IF(OR(LEFT(B77,3)="540",LEFT(B77,3)="542",LEFT(B77,3)="544",LEFT(B77,3)="545"),"Safety",IF(OR(LEFT(B77,3)="644",LEFT(B77,3)="636",LEFT(B77,3)="658"),"Signing",IF(OR(LEFT(B77,3)="666",LEFT(B77,3)="668",LEFT(B77,3)="672",LEFT(B77,3)="677",LEFT(B77,3)="678"),"Markings","Other"))))))))))))) | E77: =IF(B77="","",'WS Import'!D87) | F77: =IF(B77="","",'WS Import'!E87) | H77: =IF(B77="","",IFERROR(INDEX('Unit Cost'!$N$6:$N$21,MATCH(B77,'Unit Cost'!$B$6:$B$21,0)),0)) | I77: =IF(B77="","",F77*IF(H77>0,H77,G77)) | J77: =IF(B77="","",IF(B77="500-7001",1,MarkupFactor)) | K77: =IF(B77="","",IF(B77="500-7001",Mobilization!C11,IF(F77=0,0,IF(H77>0,H77,G77)*J77))) | M77: =IF(B77="","",IF(L77="",K77,L77)) | N77: =IF(B77="","",F77*M77) | O77: =IF(OR(B77="",$N$156=""),"",N77/$N$156) | S77: =IF(OR(B77="",F77=""),"",IF(M77=0,"ZERO PRICE",IF(AND(M77>0,M77<=0.05,Q77>1),"TOKEN PRICE",IF(AND(Q77>0,M77<P77*0.5),"UNDER BAND",IF(AND(R77>0,M77>R77*1.5),"OVER BAND",IF(AND(B77="500-7001",$N$156>0,N77/$N$156>0.1),"MOB > 10%","OK"))))))
A78: =IF('WS Import'!H88="","",ROW()-5) | B78: =IF('WS Import'!H88="","",'WS Import'!H88) | C78: =IF('WS Import'!H88="","",'WS Import'!C88) | D78: =IF(B78="","",IF('WS Import'!F88<>"",'WS Import'!F88,IF(LEFT(B78,3)="500","Mobilization",IF(OR(LEFT(B78,3)="502",LEFT(B78,3)="503",LEFT(B78,3)="505",LEFT(B78,3)="512"),"Traffic control",IF(LEFT(B78,3)="506","SW3P",IF(OR(LEFT(B78,3)="100",LEFT(B78,3)="104",LEFT(B78,3)="105",LEFT(B78,3)="110",LEFT(B78,3)="132"),"Earthwork",IF(LEFT(B78,3)="247","Base",IF(OR(LEFT(B78,3)="310",LEFT(B78,3)="316",LEFT(B78,3)="340",LEFT(B78,3)="341",LEFT(B78,3)="344",LEFT(B78,3)="354",LEFT(B78,4)="3076",LEFT(B78,4)="3077",LEFT(B78,4)="3080"),"Paving",IF(OR(LEFT(B78,3)="400",LEFT(B78,3)="416",LEFT(B78,3)="420",LEFT(B78,3)="422",LEFT(B78,3)="432",LEFT(B78,3)="450",LEFT(B78,3)="462",LEFT(B78,3)="464",LEFT(B78,3)="465",LEFT(B78,3)="466",LEFT(B78,3)="467",LEFT(B78,3)="496"),"Drainage",IF(OR(LEFT(B78,3)="164",LEFT(B78,3)="168",LEFT(B78,3)="169",LEFT(B78,3)="529",LEFT(B78,3)="530",LEFT(B78,3)="531"),"Roadside",IF(OR(LEFT(B78,3)="540",LEFT(B78,3)="542",LEFT(B78,3)="544",LEFT(B78,3)="545"),"Safety",IF(OR(LEFT(B78,3)="644",LEFT(B78,3)="636",LEFT(B78,3)="658"),"Signing",IF(OR(LEFT(B78,3)="666",LEFT(B78,3)="668",LEFT(B78,3)="672",LEFT(B78,3)="677",LEFT(B78,3)="678"),"Markings","Other"))))))))))))) | E78: =IF(B78="","",'WS Import'!D88) | F78: =IF(B78="","",'WS Import'!E88) | H78: =IF(B78="","",IFERROR(INDEX('Unit Cost'!$N$6:$N$21,MATCH(B78,'Unit Cost'!$B$6:$B$21,0)),0)) | I78: =IF(B78="","",F78*IF(H78>0,H78,G78)) | J78: =IF(B78="","",IF(B78="500-7001",1,MarkupFactor)) | K78: =IF(B78="","",IF(B78="500-7001",Mobilization!C11,IF(F78=0,0,IF(H78>0,H78,G78)*J78))) | M78: =IF(B78="","",IF(L78="",K78,L78)) | N78: =IF(B78="","",F78*M78) | O78: =IF(OR(B78="",$N$156=""),"",N78/$N$156) | S78: =IF(OR(B78="",F78=""),"",IF(M78=0,"ZERO PRICE",IF(AND(M78>0,M78<=0.05,Q78>1),"TOKEN PRICE",IF(AND(Q78>0,M78<P78*0.5),"UNDER BAND",IF(AND(R78>0,M78>R78*1.5),"OVER BAND",IF(AND(B78="500-7001",$N$156>0,N78/$N$156>0.1),"MOB > 10%","OK"))))))
A79: =IF('WS Import'!H89="","",ROW()-5) | B79: =IF('WS Import'!H89="","",'WS Import'!H89) | C79: =IF('WS Import'!H89="","",'WS Import'!C89) | D79: =IF(B79="","",IF('WS Import'!F89<>"",'WS Import'!F89,IF(LEFT(B79,3)="500","Mobilization",IF(OR(LEFT(B79,3)="502",LEFT(B79,3)="503",LEFT(B79,3)="505",LEFT(B79,3)="512"),"Traffic control",IF(LEFT(B79,3)="506","SW3P",IF(OR(LEFT(B79,3)="100",LEFT(B79,3)="104",LEFT(B79,3)="105",LEFT(B79,3)="110",LEFT(B79,3)="132"),"Earthwork",IF(LEFT(B79,3)="247","Base",IF(OR(LEFT(B79,3)="310",LEFT(B79,3)="316",LEFT(B79,3)="340",LEFT(B79,3)="341",LEFT(B79,3)="344",LEFT(B79,3)="354",LEFT(B79,4)="3076",LEFT(B79,4)="3077",LEFT(B79,4)="3080"),"Paving",IF(OR(LEFT(B79,3)="400",LEFT(B79,3)="416",LEFT(B79,3)="420",LEFT(B79,3)="422",LEFT(B79,3)="432",LEFT(B79,3)="450",LEFT(B79,3)="462",LEFT(B79,3)="464",LEFT(B79,3)="465",LEFT(B79,3)="466",LEFT(B79,3)="467",LEFT(B79,3)="496"),"Drainage",IF(OR(LEFT(B79,3)="164",LEFT(B79,3)="168",LEFT(B79,3)="169",LEFT(B79,3)="529",LEFT(B79,3)="530",LEFT(B79,3)="531"),"Roadside",IF(OR(LEFT(B79,3)="540",LEFT(B79,3)="542",LEFT(B79,3)="544",LEFT(B79,3)="545"),"Safety",IF(OR(LEFT(B79,3)="644",LEFT(B79,3)="636",LEFT(B79,3)="658"),"Signing",IF(OR(LEFT(B79,3)="666",LEFT(B79,3)="668",LEFT(B79,3)="672",LEFT(B79,3)="677",LEFT(B79,3)="678"),"Markings","Other"))))))))))))) | E79: =IF(B79="","",'WS Import'!D89) | F79: =IF(B79="","",'WS Import'!E89) | H79: =IF(B79="","",IFERROR(INDEX('Unit Cost'!$N$6:$N$21,MATCH(B79,'Unit Cost'!$B$6:$B$21,0)),0)) | I79: =IF(B79="","",F79*IF(H79>0,H79,G79)) | J79: =IF(B79="","",IF(B79="500-7001",1,MarkupFactor)) | K79: =IF(B79="","",IF(B79="500-7001",Mobilization!C11,IF(F79=0,0,IF(H79>0,H79,G79)*J79))) | M79: =IF(B79="","",IF(L79="",K79,L79)) | N79: =IF(B79="","",F79*M79) | O79: =IF(OR(B79="",$N$156=""),"",N79/$N$156) | S79: =IF(OR(B79="",F79=""),"",IF(M79=0,"ZERO PRICE",IF(AND(M79>0,M79<=0.05,Q79>1),"TOKEN PRICE",IF(AND(Q79>0,M79<P79*0.5),"UNDER BAND",IF(AND(R79>0,M79>R79*1.5),"OVER BAND",IF(AND(B79="500-7001",$N$156>0,N79/$N$156>0.1),"MOB > 10%","OK"))))))
A80: =IF('WS Import'!H90="","",ROW()-5) | B80: =IF('WS Import'!H90="","",'WS Import'!H90) | C80: =IF('WS Import'!H90="","",'WS Import'!C90) | D80: =IF(B80="","",IF('WS Import'!F90<>"",'WS Import'!F90,IF(LEFT(B80,3)="500","Mobilization",IF(OR(LEFT(B80,3)="502",LEFT(B80,3)="503",LEFT(B80,3)="505",LEFT(B80,3)="512"),"Traffic control",IF(LEFT(B80,3)="506","SW3P",IF(OR(LEFT(B80,3)="100",LEFT(B80,3)="104",LEFT(B80,3)="105",LEFT(B80,3)="110",LEFT(B80,3)="132"),"Earthwork",IF(LEFT(B80,3)="247","Base",IF(OR(LEFT(B80,3)="310",LEFT(B80,3)="316",LEFT(B80,3)="340",LEFT(B80,3)="341",LEFT(B80,3)="344",LEFT(B80,3)="354",LEFT(B80,4)="3076",LEFT(B80,4)="3077",LEFT(B80,4)="3080"),"Paving",IF(OR(LEFT(B80,3)="400",LEFT(B80,3)="416",LEFT(B80,3)="420",LEFT(B80,3)="422",LEFT(B80,3)="432",LEFT(B80,3)="450",LEFT(B80,3)="462",LEFT(B80,3)="464",LEFT(B80,3)="465",LEFT(B80,3)="466",LEFT(B80,3)="467",LEFT(B80,3)="496"),"Drainage",IF(OR(LEFT(B80,3)="164",LEFT(B80,3)="168",LEFT(B80,3)="169",LEFT(B80,3)="529",LEFT(B80,3)="530",LEFT(B80,3)="531"),"Roadside",IF(OR(LEFT(B80,3)="540",LEFT(B80,3)="542",LEFT(B80,3)="544",LEFT(B80,3)="545"),"Safety",IF(OR(LEFT(B80,3)="644",LEFT(B80,3)="636",LEFT(B80,3)="658"),"Signing",IF(OR(LEFT(B80,3)="666",LEFT(B80,3)="668",LEFT(B80,3)="672",LEFT(B80,3)="677",LEFT(B80,3)="678"),"Markings","Other"))))))))))))) | E80: =IF(B80="","",'WS Import'!D90) | F80: =IF(B80="","",'WS Import'!E90) | H80: =IF(B80="","",IFERROR(INDEX('Unit Cost'!$N$6:$N$21,MATCH(B80,'Unit Cost'!$B$6:$B$21,0)),0)) | I80: =IF(B80="","",F80*IF(H80>0,H80,G80)) | J80: =IF(B80="","",IF(B80="500-7001",1,MarkupFactor)) | K80: =IF(B80="","",IF(B80="500-7001",Mobilization!C11,IF(F80=0,0,IF(H80>0,H80,G80)*J80))) | M80: =IF(B80="","",IF(L80="",K80,L80)) | N80: =IF(B80="","",F80*M80) | O80: =IF(OR(B80="",$N$156=""),"",N80/$N$156) | S80: =IF(OR(B80="",F80=""),"",IF(M80=0,"ZERO PRICE",IF(AND(M80>0,M80<=0.05,Q80>1),"TOKEN PRICE",IF(AND(Q80>0,M80<P80*0.5),"UNDER BAND",IF(AND(R80>0,M80>R80*1.5),"OVER BAND",IF(AND(B80="500-7001",$N$156>0,N80/$N$156>0.1),"MOB > 10%","OK"))))))
A81: =IF('WS Import'!H91="","",ROW()-5) | B81: =IF('WS Import'!H91="","",'WS Import'!H91) | C81: =IF('WS Import'!H91="","",'WS Import'!C91) | D81: =IF(B81="","",IF('WS Import'!F91<>"",'WS Import'!F91,IF(LEFT(B81,3)="500","Mobilization",IF(OR(LEFT(B81,3)="502",LEFT(B81,3)="503",LEFT(B81,3)="505",LEFT(B81,3)="512"),"Traffic control",IF(LEFT(B81,3)="506","SW3P",IF(OR(LEFT(B81,3)="100",LEFT(B81,3)="104",LEFT(B81,3)="105",LEFT(B81,3)="110",LEFT(B81,3)="132"),"Earthwork",IF(LEFT(B81,3)="247","Base",IF(OR(LEFT(B81,3)="310",LEFT(B81,3)="316",LEFT(B81,3)="340",LEFT(B81,3)="341",LEFT(B81,3)="344",LEFT(B81,3)="354",LEFT(B81,4)="3076",LEFT(B81,4)="3077",LEFT(B81,4)="3080"),"Paving",IF(OR(LEFT(B81,3)="400",LEFT(B81,3)="416",LEFT(B81,3)="420",LEFT(B81,3)="422",LEFT(B81,3)="432",LEFT(B81,3)="450",LEFT(B81,3)="462",LEFT(B81,3)="464",LEFT(B81,3)="465",LEFT(B81,3)="466",LEFT(B81,3)="467",LEFT(B81,3)="496"),"Drainage",IF(OR(LEFT(B81,3)="164",LEFT(B81,3)="168",LEFT(B81,3)="169",LEFT(B81,3)="529",LEFT(B81,3)="530",LEFT(B81,3)="531"),"Roadside",IF(OR(LEFT(B81,3)="540",LEFT(B81,3)="542",LEFT(B81,3)="544",LEFT(B81,3)="545"),"Safety",IF(OR(LEFT(B81,3)="644",LEFT(B81,3)="636",LEFT(B81,3)="658"),"Signing",IF(OR(LEFT(B81,3)="666",LEFT(B81,3)="668",LEFT(B81,3)="672",LEFT(B81,3)="677",LEFT(B81,3)="678"),"Markings","Other"))))))))))))) | E81: =IF(B81="","",'WS Import'!D91) | F81: =IF(B81="","",'WS Import'!E91) | H81: =IF(B81="","",IFERROR(INDEX('Unit Cost'!$N$6:$N$21,MATCH(B81,'Unit Cost'!$B$6:$B$21,0)),0)) | I81: =IF(B81="","",F81*IF(H81>0,H81,G81)) | J81: =IF(B81="","",IF(B81="500-7001",1,MarkupFactor)) | K81: =IF(B81="","",IF(B81="500-7001",Mobilization!C11,IF(F81=0,0,IF(H81>0,H81,G81)*J81))) | M81: =IF(B81="","",IF(L81="",K81,L81)) | N81: =IF(B81="","",F81*M81) | O81: =IF(OR(B81="",$N$156=""),"",N81/$N$156) | S81: =IF(OR(B81="",F81=""),"",IF(M81=0,"ZERO PRICE",IF(AND(M81>0,M81<=0.05,Q81>1),"TOKEN PRICE",IF(AND(Q81>0,M81<P81*0.5),"UNDER BAND",IF(AND(R81>0,M81>R81*1.5),"OVER BAND",IF(AND(B81="500-7001",$N$156>0,N81/$N$156>0.1),"MOB > 10%","OK"))))))
A82: =IF('WS Import'!H92="","",ROW()-5) | B82: =IF('WS Import'!H92="","",'WS Import'!H92) | C82: =IF('WS Import'!H92="","",'WS Import'!C92) | D82: =IF(B82="","",IF('WS Import'!F92<>"",'WS Import'!F92,IF(LEFT(B82,3)="500","Mobilization",IF(OR(LEFT(B82,3)="502",LEFT(B82,3)="503",LEFT(B82,3)="505",LEFT(B82,3)="512"),"Traffic control",IF(LEFT(B82,3)="506","SW3P",IF(OR(LEFT(B82,3)="100",LEFT(B82,3)="104",LEFT(B82,3)="105",LEFT(B82,3)="110",LEFT(B82,3)="132"),"Earthwork",IF(LEFT(B82,3)="247","Base",IF(OR(LEFT(B82,3)="310",LEFT(B82,3)="316",LEFT(B82,3)="340",LEFT(B82,3)="341",LEFT(B82,3)="344",LEFT(B82,3)="354",LEFT(B82,4)="3076",LEFT(B82,4)="3077",LEFT(B82,4)="3080"),"Paving",IF(OR(LEFT(B82,3)="400",LEFT(B82,3)="416",LEFT(B82,3)="420",LEFT(B82,3)="422",LEFT(B82,3)="432",LEFT(B82,3)="450",LEFT(B82,3)="462",LEFT(B82,3)="464",LEFT(B82,3)="465",LEFT(B82,3)="466",LEFT(B82,3)="467",LEFT(B82,3)="496"),"Drainage",IF(OR(LEFT(B82,3)="164",LEFT(B82,3)="168",LEFT(B82,3)="169",LEFT(B82,3)="529",LEFT(B82,3)="530",LEFT(B82,3)="531"),"Roadside",IF(OR(LEFT(B82,3)="540",LEFT(B82,3)="542",LEFT(B82,3)="544",LEFT(B82,3)="545"),"Safety",IF(OR(LEFT(B82,3)="644",LEFT(B82,3)="636",LEFT(B82,3)="658"),"Signing",IF(OR(LEFT(B82,3)="666",LEFT(B82,3)="668",LEFT(B82,3)="672",LEFT(B82,3)="677",LEFT(B82,3)="678"),"Markings","Other"))))))))))))) | E82: =IF(B82="","",'WS Import'!D92) | F82: =IF(B82="","",'WS Import'!E92) | H82: =IF(B82="","",IFERROR(INDEX('Unit Cost'!$N$6:$N$21,MATCH(B82,'Unit Cost'!$B$6:$B$21,0)),0)) | I82: =IF(B82="","",F82*IF(H82>0,H82,G82)) | J82: =IF(B82="","",IF(B82="500-7001",1,MarkupFactor)) | K82: =IF(B82="","",IF(B82="500-7001",Mobilization!C11,IF(F82=0,0,IF(H82>0,H82,G82)*J82))) | M82: =IF(B82="","",IF(L82="",K82,L82)) | N82: =IF(B82="","",F82*M82) | O82: =IF(OR(B82="",$N$156=""),"",N82/$N$156) | S82: =IF(OR(B82="",F82=""),"",IF(M82=0,"ZERO PRICE",IF(AND(M82>0,M82<=0.05,Q82>1),"TOKEN PRICE",IF(AND(Q82>0,M82<P82*0.5),"UNDER BAND",IF(AND(R82>0,M82>R82*1.5),"OVER BAND",IF(AND(B82="500-7001",$N$156>0,N82/$N$156>0.1),"MOB > 10%","OK"))))))
